Workbook
Name \a: #REF!
Name \b: #REF!
Name \C: #REF!
Name \D: #REF!
Name \E: #REF!
Name \F: #REF!
Name \I: #REF!
Name \J: #REF!
Name \O: #REF!
Name \P: #REF!
Name \Q: #REF!
Name \R: #REF!
Name \S: #REF!
Name \T: #REF!
Name \X: #REF!
Name \Z: #REF!
Name __: #REF!
Name ________: #REF!
Name __________ssmdndkdsldsjsld: #REF!
Name ___bot1: #REF!
Name ___bot2: #REF!
Name ___bot3: #REF!
Name ___bot4: #REF!
Name ___bot5: #REF!
Name ___bot6: #REF!
Name ___top1: #REF!
Name ___top2: #REF!
Name ___top3: #REF!
Name ___top4: #REF!
Name ___top5: #REF!
Name ___top6: #REF!
Name __ano1990: #REF!
Name __bot1: #REF!
Name __bot2: #REF!
Name __bot3: #REF!
Name __bot4: #REF!
Name __bot5: #REF!
Name __bot6: #REF!
Name __EXP10: #REF!
Name __EXP30: #REF!
Name __EXP5: #REF!
Name __OI10: #REF!
Name __OI30: #REF!
Name __Ois1: #REF!
Name __OIS2: #REF!
Name __OIS3: #REF!
Name __top1: #REF!
Name __top2: #REF!
Name __top3: #REF!
Name __top4: #REF!
Name __top5: #REF!
Name __top6: #REF!
Name _ano1990: #REF!
Name _bot1: #REF!
Name _bot2: #REF!
Name _bot3: #REF!
Name _bot4: #REF!
Name _bot5: #REF!
Name _bot6: #REF!
Name _DI_NACE: #REF!

Sheet Capa
A1: s
A48: Nota: Neste ficheiro são disponiblizados os dados subjacentes aos gráficos e quadros do Boletim Económico – março 2024.
A49: Note: This file contains the data used in the charts and tables of the Economic Bulletin – March 2024.

Sheet Índice
B1: Classificação de Segurança - Público
A5: Boletim Económico - março 2024 / Economic Bulletin - March 2024
A6: ÍNDICE/CONTENTS
A7: Parte I. Projeções para a economia portuguesa: 2024-26 / Part I. Projections for the Portuguese economy: 2024-26
A8: =HYPERLINK("#"&C8,INDIRECT(C8)) -> Quadro I.1.1 • Projeções do Banco de Portugal para 2024-26 | Taxa de variação anual em percentagem (exceto onde indicado) | C8: QI.1.1!A$10
A9: =HYPERLINK("#"&C9,INDIRECT(C9)) -> Table I.1.1 • Projections of Banco de Portugal for 2024-26| Annual rate of change in percentage (unless otherwise stated) | C9: QI.1.1!A$11
A10: =HYPERLINK("#"&C10,INDIRECT(C10)) -> Gráfico I.1.1 • Projeções trimestrais para o PIB e para a inflação | C10: GI.1.1!A$10
A11: =HYPERLINK("#"&C11,INDIRECT(C11)) -> Chart I.1.1 • Quarterly projections for GDP and inflation | C11: GI.1.1!A$11
A12: =HYPERLINK("#"&C12,INDIRECT(C12)) -> Gráfico I.1.2 • IHPC, deflator das importações e deflator do PIB - Taxa de variação anual | Percentagem | C12: GI.1.2!A$10
A13: =HYPERLINK("#"&C13,INDIRECT(C13)) -> Chart I.1.2 • HICP, imports deflator and GDP deflator - Annual rate of change | Percentage | C13: GI.1.2!A$11
A14: =HYPERLINK("#"&C14,INDIRECT(C14)) -> Gráfico I.1.3 • Decomposição da taxa de variação do deflator do PIB na ótica do rendimento | Percentagem e pp | C14: GI.1.3!A$10
A15: =HYPERLINK("#"&C15,INDIRECT(C15)) -> Chart I.1.3 • Decomposition of GDP deflator rate of change (income side) | Percentage and percentage points | C15: GI.1.3!A$11
A16: =HYPERLINK("#"&C16,INDIRECT(C16)) -> Gráfico I.1.4 • PIB e agregados da despesa em Portugal e na área do euro – taxa de variação média 2024-26| Em percentagem | C16: GI.1.4!A$10
A17: =HYPERLINK("#"&C17,INDIRECT(C17)) -> Chart I.1.4 • GDP and expenditure side aggregates in Portugal and the euro area – average rate of change 2024-26 | Percentage | C17: GI.1.4!A$11
A18: =HYPERLINK("#"&C18,INDIRECT(C18)) -> Gráfico I.1.5 • Endividamento dos particulares, empresas não financeiras e administrações públicas em Portugal e na área do euro | Em percentagem do PIB | C18: GI.1.5!A$10
A19: =HYPERLINK("#"&C19,INDIRECT(C19)) -> Chart I.1.5 • Debt of households, non-financial corporations and public administrations in Portugal and the euro area | Percentage of GDP | C19: GI.1.5!A$11
... A27: =HYPERLINK("#"&C27,INDIRECT(C27)) -> Chart I.1.9 • Change in jobs between 2019 and 2023 and average monthly wages in 2023 - by technological and knowledge intensity | Thousands and euros | C27: GI.1.9!A$11
A29: Caixa 1- Enquadramento e políticas / Box 1-External environment, financing conditions and policies
A30: =HYPERLINK("#"&C30,INDIRECT(C30)) -> Quadro C1.1 • Hipóteses do exercício de projeção | C30: QC1.1!A$10
A31: =HYPERLINK("#"&C31,INDIRECT(C31)) -> Table C1.1 • Eurosystem staff projection assumptions | C31: QC1.1!A$11
A32: =HYPERLINK("#"&C32,INDIRECT(C32)) -> Gráfico C1.1 • PIB da área do euro e maiores países | Taxa de variação anual | C32: GC1.1!A$10
A33: =HYPERLINK("#"&C33,INDIRECT(C33)) -> Chart C1.1 • Euro area and major countries GDP | Annual rate of change | C33: GC1.1!A$11
A35: Caixa 2 - Expetativas de taxas de juro e de consumo das famílias / Box 2 - Consumers' expectations on interest rates and consumption
A36: =HYPERLINK("#"&C36,INDIRECT(C36)) -> Quadro C2.1 • Características dos consumidores inquiridos | Valores médios e percentagem | C36: QC2.1!A$10
A37: =HYPERLINK("#"&C37,INDIRECT(C37)) -> Table C2.1 • Characteristics of the surveyed consumers | Mean values and percentage | C37: QC2.1!A$11
A38: =HYPERLINK("#"&C38,INDIRECT(C38)) -> Gráfico C2.1 • Situação financeira dos consumidores em Portugal total e por situação de crédito | Saldo de respostas extremas | C38: GC2.1!A$10
A39: =HYPERLINK("#"&C39,INDIRECT(C39)) -> Chart C2.1 • Consumers' financial situation in Portugal in total and by housing type | Net percentage | C39: GC2.1!A$11
A40: =HYPERLINK("#"&C40,INDIRECT(C40)) -> Gráfico C2.2 • Impacto do aumento de 1 pp nas expetativas de taxas de juro sobre as expetativas de consumo nos 12 meses seguintes | Pontos percentuais | C40: GC2.2!A$10
A41: =HYPERLINK("#"&C41,INDIRECT(C41)) -> Chart C2.2 • Impact of an increase of 1 pp of expectatations for interest rates on spending expectations in the next 12 months | Percentage points | C41: GC2.2!A$11
A43: Caixa 3 - Evolução dos empréstimos às empresas na sequência das medidas de apoio ao crédito na pandemia / Box 3 - Evolution of corporate loans following the credit support measures during the pandemic
A44: =HYPERLINK("#"&C44,INDIRECT(C44)) -> Quadro C3.1 • Características das empresas dos grupos analisados em 2019 | Valores médios | C44: QC3.1!A$10
A45: =HYPERLINK("#"&C45,INDIRECT(C45)) -> Table C3.1 • Firm Characteristics by group in 2019 | Mean values | C45: QC3.1!A$11
A46: =HYPERLINK("#"&C46,INDIRECT(C46)) -> Gráfico C3.1 • Empréstimos a sociedades não financeiras – Decomposição dos fluxos líquidos mensais | Soma dos últimos três meses, milhões de euros | C46: GC3.1!A$10
A47: =HYPERLINK("#"&C47,INDIRECT(C47)) -> Chart C3.1 • Loans to non-financial corporations – Breakdown of monthly net flows | Sum of the last three months, millions of euros | C47: GC3.1!A$11
A48: =HYPERLINK("#"&C48,INDIRECT(C48)) -> Gráfico C3.2 • Decomposição dos fluxos líquidos mensais dos empréstimos| Soma dos últimos três meses, em milhões de euros | C48: GC3.2!A$10
A49: =HYPERLINK("#"&C49,INDIRECT(C49)) -> Chart C3.2 • Breakdown of monthly net loan flows | Sum of the last three months, in millions of euros | C49: GC3.2!A$11
A50: =HYPERLINK("#"&C50,INDIRECT(C50)) -> Gráfico C3.3 • Decomposição dos fluxos líquidos mensais dos empréstimos: Empresas elegíveis sem crédito com garantia pública e sem moratória | Soma dos últimos três meses, em milhões de euros | C50: GC3.3!A$10
A51: =HYPERLINK("#"&C51,INDIRECT(C51)) -> Chart C3.3 • Breakdown of monthly net loan flows: Eligible firms without public guaranteed credit and without moratorium | Sum of the last three months, in millions of euros | C51: GC3.3!A$11
A52: =HYPERLINK("#"&C52,INDIRECT(C52)) -> Gráfico C3.4 • Empréstimos a sociedades não financeiras – Decomposição dos fluxos líquidos mensais | Soma dos últimos três meses, milhões de euros | C52: GC3.4!A$10
A53: =HYPERLINK("#"&C53,INDIRECT(C53)) -> Chart C3.4 • Loans to non-financial corporations – Breakdown of monthly net flows | Sum of the last three months, millions of euros | C53: GC3.4!A$11
A55: Caixa 4 - Impacto da política monetária sobre o mercado residencial em Portugal / Box 4 - Monetary policy impact on the portuguese residential market
A56: =HYPERLINK("#"&C56,INDIRECT(C56)) -> Gráfico C4.1 • Impacto de um choque de política monetária no índice de preços da habitação e no número total de transações | Percentagem | C56: GC4.1!A$10
A57: =HYPERLINK("#"&C57,INDIRECT(C57)) -> Chart C4.1 • Impact of a monetary policy shock on the housing price index and total number of transactions | Percentage | C57: GC4.1!A$11
A58: =HYPERLINK("#"&C58,INDIRECT(C58)) -> Gráfico C4.2 • Impacto de um choque de política monetária no índice de preços da habitação e no número total de transações de habitações novas e habitações existentes | Percentagem | C58: GC4.2!A$10
A59: =HYPERLINK("#"&C59,INDIRECT(C59)) -> Chart C4.2 • Impact of a monetary policy shock on the housing price index and total number of transactions of new and existing houses | Percentage | C59: GC4.2!A$11
A61: Parte II. Tema em Destaque: Bem-estar e PIB per capita em Portugal face à EU / Part II. Special issue: Welfare and GDP per capita in Portugal compared to the EU
A62: =HYPERLINK("#"&C62,INDIRECT(C62)) -> Gráfico 1 • Consumo, lazer, esperança de vida e desigualdade em 2022 | C62: TED.G1!A$10
A63: =HYPERLINK("#"&C63,INDIRECT(C63)) -> Chart 1 • Consumption, leisure, life expectancy and inequality in 2022 | C63: TED.G1!A$11
A64: =HYPERLINK("#"&C64,INDIRECT(C64)) -> Gráfico 2 • Índice de Bem-estar e contributos das quatro componentes em 2022 | Logaritmo do índice de bem-estar | C64: TED.G2!A$10
A65: =HYPERLINK("#"&C65,INDIRECT(C65)) -> Chart 2 • Welfare index and contributions of the four components in 2022 | Logarithm of the welfare index | C65: TED.G2!A$11
A66: =HYPERLINK("#"&C66,INDIRECT(C66)) -> Gráfico 3 • Índice de bem-estar e PIB per capita, em 2022 | Em percentagem da UE | C66: TED.G3!A$10
A67: =HYPERLINK("#"&C67,INDIRECT(C67)) -> Chart 3 • Welfare index and GDP per capita in 2022 | Percentage of the EU | C67: TED.G3!A$11
A68: =HYPERLINK("#"&C68,INDIRECT(C68)) -> Gráfico 4 • Convergência beta absoluta na UE no período 1995-2022 | Índice de bem-estar: logaritmo e taxa de variação, dados encadeados em volume, em euros | C68: TED.G4!A$10
A69: =HYPERLINK("#"&C69,INDIRECT(C69)) -> Chart 4 • Absolute beta convergence in the EU over the period 1995-2022 | Welfare index: logarithm and rate of change, chain-linked volume data, in euros | C69: TED.G4!A$11
A70: =HYPERLINK("#"&C70,INDIRECT(C70)) -> Gráfico 5 • Índice de bem-estar e PIB per capita em Portugal entre 1995 e 2022| Em percentagem da EU | C70: TED.G5!A$10
A71: =HYPERLINK("#"&C71,INDIRECT(C71)) -> Chart 5 • Welfare index and GDP per capita in Portugal between 1995 and 2022| Percentage of the EU | C71: TED.G5!A$11
A72: =HYPERLINK("#"&C72,INDIRECT(C72)) -> Quadro 1 • Índice de Bem-estar e PIB per capita em 2022 e decomposição da diferença entre as duas medidas | C72: TED.Q1!A$10
A73: =HYPERLINK("#"&C73,INDIRECT(C73)) -> Table 1 • Welfare Index and GDP per capita in 2022 and decomposition of the difference between the two measures | C73: TED.Q1!A$11
... A75: =HYPERLINK("#"&C75,INDIRECT(C75)) -> Table 2 • Welfare Index and GDP per capita growth between 1995 and 2022, and decomposition of the difference | Percentage and percentage points | C75: TED.Q2!A$11
A77: Parte III. Políticas em análise: Evidência do PISA sobre as competências dos jovens portugueses / Part III. Policy insights: Evidence from PISA on the skills of Portuguese students
A78: =HYPERLINK("#"&C78,INDIRECT(C78)) -> Gráfico 1 • Escolaridade da população adulta em Portugal e na área do euro | Em percentagem | C78: PEA.G1!A$10
A79: =HYPERLINK("#"&C79,INDIRECT(C79)) -> Chart 1 • Education of the adult population in Portugal and the euro area | In percentage | C79: PEA.G1!A$11
A80: =HYPERLINK("#"&C80,INDIRECT(C80)) -> Gráfico 2 • Resultados do PISA em Portugal e na área do euro | Em pontos | C80: PEA.G2!A$10
A81: =HYPERLINK("#"&C81,INDIRECT(C81)) -> Chart 2 • PISA results in Portugal and the euro area | In points | C81: PEA.G2!A$11
A82: =HYPERLINK("#"&C82,INDIRECT(C82)) -> Gráfico 3 • Estudantes nos extremos de competências a matemática | Em percentagem | C82: PEA.G3!A$10
A83: =HYPERLINK("#"&C83,INDIRECT(C83)) -> Chart 3 • Low and top performers in mathematics | In percentage | C83: PEA.G3!A$11
A84: =HYPERLINK("#"&C84,INDIRECT(C84)) -> Gráfico 4 • Decomposição da evolução dos resultados do PISA em Portugal | Em pontos | C84: PEA.G4!A$10
A85: =HYPERLINK("#"&C85,INDIRECT(C85)) -> Chart 4 • Decomposition of the change in PISA results in Portugal | In points | C85: PEA.G4!A$11
A86: =HYPERLINK("#"&C86,INDIRECT(C86)) -> Gráfico 5 • Variação dos resultados a matemática em 2022 nos diferentes países da área do euro | Em pontos | C86: PEA.G5!A$10
A87: =HYPERLINK("#"&C87,INDIRECT(C87)) -> Chart 5 • Change in mathematics results in 2022 in euro area countries | In points | C87: PEA.G5!A$11
A88: =HYPERLINK("#"&C88,INDIRECT(C88)) -> Gráfico 6 • Variação entre 2018 e 2022 da diferença entre o último e o primeiro decil das pontuações a matemática | Em pontos | C88: PEA.G6!A$10
A89: =HYPERLINK("#"&C89,INDIRECT(C89)) -> Chart 6 • Change between 2018 and 2022 in the gap between the last and first decile of mathematics scores | In points | C89: PEA.G6!A$11
... A91: =HYPERLINK("#"&C91,INDIRECT(C91)) -> Chart 7 • Change in mathematics results in 2022 by socio-economic status along the distribution | In points | C91: PEA.G7!A$11

Sheet QI.1.1
A5: Índice/Contents
A6: =+Índice!$A$5 -> Boletim Económico - março 2024 / Economic Bulletin - March 2024
A7: =+Índice!$A$7 -> Parte I. Projeções para a economia portuguesa: 2024-26 / Part I. Projections for the Portuguese economy: 2024-26
A10: Quadro I.1.1 • Projeções do Banco de Portugal para 2024-26 | Taxa de variação anual em percentagem (exceto onde indicado)
A11: Table I.1.1 • Projections of Banco de Portugal for 2024-26| Annual rate of change in percentage (unless otherwise stated)
A13: Unidade/Unit | C13: % | E13: % | F13: % | G13: % | H13: % | J13: % | K13: % | L13: % | M13: %
C14: Pesos | E14: BE março 2024 | J14: BE dezembro 2023
C15: Weights | E15: EB March 2024 | J15: EB December 2023
C16: 2023 | E16: 2023 | F16: 2024 (p) | G16: 2025 (p) | H16: 2026 (p) | J16: 2023 (p) | K16: 2024 (p) | L16: 2025 (p) | M16: 2026 (p)
A18: Produto interno bruto | B18: Gross domestic product | C18: 100 | E18: 2.28052 | F18: 2.0459739 | G18: 2.2967685 | H18: 2.2083861 | J18: 2.1064862 | K18: 1.2181047 | L18: 2.1663045 | M18: 2.0093188
A20: Consumo privado | B20: Private consumption | C20: 62.500411 | E20: 1.6336574 | F20: 2.0820899 | G20: 1.925106 | H20: 1.826615 | J20: 0.97115535 | K20: 1.0098223 | L20: 1.7062625 | M20: 1.5234711
A21: Consumo público | B21: Public consumption | C21: 17.093261 | E21: 1.2415149 | F21: 1.1926705 | G21: 0.877828 | H21: 0.92772281 | J21: 1.0823475 | K21: 1.0157233 | L21: 0.85860336 | M21: 0.89481758
A22: Formação bruta de capital fixo | B22: Gross fixed capital formation | C22: 19.351306 | E22: 2.4401542 | F22: 3.6218192 | G22: 5.4391424 | H22: 4.119236 | J22: 0.88737301 | K22: 2.4420366 | L22: 5.2029813 | M22: 4.0580137
A23: Procura interna | B23: Domestic demand | C23: 99.137515 | E23: 1.4102447 | F23: 2.3656595 | G23: 2.4059002 | H23: 2.1184762 | J23: 0.74604004 | K23: 1.3910888 | L23: 2.2102242 | M23: 1.900546
A24: Exportações | B24: Exports | C24: 47.429847 | E24: 4.1830157 | F24: 3.5118923 | G24: 4.0090788 | H24: 3.2996928 | J24: 4.3270104 | K24: 2.4349847 | L24: 3.969907 | M24: 2.9953467
A25: Importações | B25: Imports | C25: 46.567361 | E25: 2.2315081 | F25: 4.2144287 | G25: 4.2560516 | H25: 3.1101558 | J25: 1.3022178 | K25: 2.7937696 | L25: 4.0979024 | M25: 2.7792001
A27: Emprego (a) | B27: Employment (a) | E27: 0.8631955 | F27: 0.69846792 | G27: 0.58508385 | H27: 0.45415575 | J27: 0.82568162 | K27: 0.12659846 | L27: 0.34132223 | M27: 0.32691028
A28: Taxa de desemprego (b) | B28: Unemployment rate (b) | E28: 6.5091485 | F28: 6.5148295 | G28: 6.4592335 | H28: 6.4636811 | J28: 6.5494816 | K28: 7.0574451 | L28: 7.2950097 | M28: 7.1504139
A30: Balança corrente e de capital (% PIB) | B30: Current and capital account (% of GDP) | E30: 2.7255972 | F30: 3.595957 | G30: 3.8835519 | H30: 4.08046 | J30: 3.0458346 | K30: 3.4560927 | L30: 3.71566 | M30: 4.0260773
A31: Balança de bens e serviços (% PIB) | B31: Trade balance (% of GDP) | E31: 1.2327243 | F31: 1.1249379 | G31: 1.2303927 | H31: 1.4790873 | J31: 1.1704602 | K31: 1.3318268 | L31: 1.4852096 | M31: 1.7574905
A33: Índice harmonizado de preços no consumidor | B33: Harmonised index of consumer prices | E33: 5.2642832 | F33: 2.3577992 | G33: 1.9997807 | H33: 1.9371263 | J33: 5.307806 | K33: 2.9234759 | L33: 1.9742583 | M33: 1.9632434
A34: Bens energéticos | B34: Energy | E34: -8.9092019 | F34: 3.6141984 | G34: 2.1580193 | H34: 0.58776934 | J34: -8.7558142 | K34: 3.4777526 | L34: 0.21741877 | M34: -0.13480671
A35: Bens alimentares | B35: Food | E35: 9.2039871 | F35: 3.0211879 | G35: 1.2980433 | H35: 1.5 | J35: 9.1615556 | K35: 4.4084926 | L35: 2.1626541 | M35: 2.1
A36: Excluindo bens energéticos | B36: Excluding energy | E36: 6.5476591 | F36: 2.2791734 | G36: 1.9902956 | H36: 2.022027 | J36: 6.5803952 | K36: 2.8786934 | L36: 2.1093382 | M36: 2.1215695
A37: Excluindo bens energéticos e alimentares | B37: Excluding energy and food | E37: 5.3698003 | F37: 2.0207849 | G37: 2.2275851 | H37: 2.1964871 | J37: 5.4270985 | K37: 2.3385621 | L37: 2.0903421 | M37: 2.1115218
A39: Fontes: Banco de Portugal e INE. | Notas: (p) – projetado. O fecho de dados do exercício de projeção ocorreu a 12 de março. A projeção corresponde ao valor mais provável condicional ao conjunto de hipóteses consideradas. Pesos de 2023 a preços correntes. (a) De acordo com o conceito de Contas Nacionais. (b) Em percentagem da população ativa.
A40: Sources: Banco de Portugal and Statistics Portugal. | Notes: (p) - projected. Cut-off date for macroeconomic projections: March 12. The projection corresponds to the most likely value conditional on the set of hypotheses considered. 2023 weights at current prices. (a) According to the National Accounts concept. (b) As a percentage of the labour force.

Sheet GI.1.1
A5: Índice/Contents
A6: =+Índice!$A$5 -> Boletim Económico - março 2024 / Economic Bulletin - March 2024
A7: =+Índice!$A$7 -> Parte I. Projeções para a economia portuguesa: 2024-26 / Part I. Projections for the Portuguese economy: 2024-26
A10: Gráfico I.1.1 • Projeções trimestrais para o PIB e para a inflação
A11: Chart I.1.1 • Quarterly projections for GDP and inflation
A13: Unidade/Unit | C13: % | D13: % | E13: % | F13: % | G13: % | H13: % | I13: % | J13: % | K13: % | L13: % | M13: % | N13: % | O13: % | P13: % | Q13: % | R13: %
C14: 2023 | G14: 2024 | K14: 2025 | O14: 2026
C15: T1 | D15: T2 | E15: T3 | F15: T4 | G15: T1 | H15: T2 | I15: T3 | J15: T4 | K15: T1 | L15: T2 | M15: T3 | N15: T4 | O15: T1 | P15: T2 | Q15: T3 | R15: T4
C16: Q1 | D16: Q2 | E16: Q3 | F16: Q4 | G16: Q1 | H16: Q2 | I16: Q3 | J16: Q4 | K16: Q1 | L16: Q2 | M16: Q3 | N16: Q4 | O16: Q1 | P16: Q2 | Q16: Q3 | R16: Q4
A18: Painel A – PIB - taxa de variação em cadeia | Percentagem | B18: Panel A – GDP - quarter-on-quarter growth rate | Percentage
A19: BE de março 2024 | B19: EB March 2024 | C19: 1.460228 | D19: 0.087780531 | E19: -0.19607811 | F19: 0.79644871 | G19: 0.66983929 | H19: 0.55876798 | I19: 0.56552396 | J19: 0.55192475 | K19: 0.59769204 | L19: 0.58541301 | M19: 0.56310902 | N19: 0.49053571 | O19: 0.52966022 | P19: 0.58876109 | Q19: 0.57612743 | R19: 0.54041728
A20: BE de dezembro 2023 | B20: EB December 2023 | C20: 1.4658033 | D20: 0.07 | E20: -0.19152501 | F20: 0.13618401 | G20: 0.32765093 | H20: 0.51440007 | I20: 0.63396056 | J20: 0.62972357 | K20: 0.5339378 | L20: 0.45148494 | M20: 0.46489295 | N20: 0.50790859 | O20: 0.46618294 | P20: 0.54435163 | Q20: 0.52799978 | R20: 0.51732294
A23: Painel B – IHPC - taxa de variação em cadeia | Percentagem | B23: Panel B – HICP - quarter-on-quarter growth rate | Percentage
A24: BE de março 2024 | B24: EB March 2024 | C24: 8.394319 | D24: 5.6535438 | E24: 4.8143413 | F24: 2.4454348 | G24: 2.3345525 | H24: 2.6090358 | I24: 2.2353349 | J24: 2.2522741 | K24: 1.9240392 | L24: 1.8929787 | M24: 2.0596441 | N24: 2.1206954 | O24: 2.0855065 | P24: 1.9645688 | Q24: 1.8761986 | R24: 1.8264064
A25: BE de dezembro 2023 | B25: EB December 2023 | C25: 8.394319 | D25: 5.6535438 | E25: 4.8143413 | F25: 2.6140738 | G25: 2.9430326 | H25: 3.1911721 | I25: 2.790058 | J25: 2.7710286 | K25: 1.9763091 | L25: 1.8486801 | M25: 2.0081865 | N25: 2.0641355 | O25: 2.0264003 | P25: 1.9571619 | Q25: 1.9165498 | R25: 1.9546981
A28: Fontes: Banco de Portugal e INE. | Nota: As linhas a tracejado correspondem aos valores projetados nos BE de dezembro de 2023 e março de 2024.
A29: Sources: Banco de Portugal and Statistics Portugal. | Note: The dashed lines correspond to the projected values in the EB of December 2023 and March 2024.

Sheet GI.1.2
A5: Índice/Contents
A6: =+Índice!$A$5 -> Boletim Económico - março 2024 / Economic Bulletin - March 2024
A7: =+Índice!$A$7 -> Parte I. Projeções para a economia portuguesa: 2024-26 / Part I. Projections for the Portuguese economy: 2024-26
A10: Gráfico I.1.2 • IHPC, deflator das importações e deflator do PIB - Taxa de variação anual | Percentagem
A11: Chart I.1.2 • HICP, imports deflator and GDP deflator - Annual rate of change | Percentage
A13: Unidade/Unit | C13: % | D13: % | E13: % | F13: % | G13: % | H13: % | I13: % | J13: %
C14: 2019 | D14: 2020 | E14: 2021 | F14: 2022 | G14: 2023 | H14: 2024 (p) | I14: 2025 (p) | J14: 2026 (p)
A16: IHPC | B16: HICP | C16: 0.29982107 | D16: -0.12133777 | E16: 0.94130898 | F16: 8.1026581 | G16: 5.2642832 | H16: 2.3577992 | I16: 1.9997807 | J16: 1.9371263
A17: Deflator do PIB | B17: GDP deflator | C17: 1.7494519 | D17: 2.003475 | E17: 1.9005944 | F17: 4.9984106 | G17: 7.2113015 | H17: 3.1631487 | I17: 2.5503928 | J17: 2.4030174
A18: Deflator das importações | B18: Imports deflator | C18: -0.2719493 | D18: -3.4588542 | E18: 8.3224915 | F18: 18.772999 | G18: -3.9548596 | H18: -0.3039723 | I18: 1.892491 | J18: 1.8833207
A20: Fontes: Banco de Portugal e INE. | Notas: (p) – projetado.
A21: Sources: Banco de Portugal and Statistics Portugal. | Notes: (p) - projected.

Sheet GI.1.3
A5: Índice/Contents
A6: =+Índice!$A$5 -> Boletim Económico - março 2024 / Economic Bulletin - March 2024
A7: =+Índice!$A$7 -> Parte I. Projeções para a economia portuguesa: 2024-26 / Part I. Projections for the Portuguese economy: 2024-26
A10: Gráfico I.1.3 • Decomposição da taxa de variação do deflator do PIB na ótica do rendimento | Percentagem e pp
A11: Chart I.1.3 • Decomposition of GDP deflator rate of change (income side) | Percentage and percentage points
C13: Unidade/Unit | F13: 2019 | G13: 2020 | H13: 2021 | I13: 2022 | J13: 2023 | K13: 2024 (p) | L13: 2025 (p) | M13: 2026 (p)
A15: Deflator do PIB | B15: GDP deflator | C15: % | F15: 1.7494519 | G15: 2.003475 | H15: 1.9005944 | I15: 4.9984106 | J15: 7.2113015 | K15: 3.1631487 | L15: 2.5503928 | M15: 2.4030174
A16: Custos unitários do trabalho | B16: Unit labour costs | C16: pp | F16: 1.6889966 | G16: 4.2260436 | H16: 0.82875743 | I16: 0.46199847 | J16: 3.5153165 | K16: 1.5773966 | L16: 1.0420234 | M16: 1.0165858
A17: Excedente bruto de exploração | B17: Gross operating surplus | C17: pp | F17: -0.11825524 | G17: -1.8696562 | H17: 0.24418441 | I17: 3.7917704 | J17: 3.33875 | K17: 0.87070908 | L17: 1.0495191 | M17: 1.1130452
A18: Impostos indirectos líquidos | B18: Net indirect taxes | C18: pp | F18: 0.17871054 | G18: -0.35291236 | H18: 0.82765255 | I18: 0.74464174 | J18: 0.35723504 | K18: 0.715043 | L18: 0.45885027 | M18: 0.2733865
A21: Fontes: Banco de Portugal e INE. | Notas: (p) – projetado.
A22: Sources: Banco de Portugal and Statistics Portugal. | Notes: (p) - projected.

Sheet GI.1.4
A5: Índice/Contents
A6: =+Índice!$A$5 -> Boletim Económico - março 2024 / Economic Bulletin - March 2024
A7: =+Índice!$A$7 -> Parte I. Projeções para a economia portuguesa: 2024-26 / Part I. Projections for the Portuguese economy: 2024-26
A10: Gráfico I.1.4 • PIB e agregados da despesa em Portugal e na área do euro – taxa de variação média 2024-26| Em percentagem
A11: Chart I.1.4 • GDP and expenditure side aggregates in Portugal and the euro area – average rate of change 2024-26 | Percentage
G13: Por memória: Média 2015-19 | H13: Média 2024-26 (p)
E14: Unidade/unit | G14: Memorandum: 2015-19 average | H14: 2024-26 average (p)
A16: PIB | B16: PT | C16: GDP | D16: PT | E16: % | G16: 2.5699926 | H16: 2.1837095
B17: AE | D17: EA | E17: % | G17: 1.9746334 | H17: 1.2543626
A19: Consumo privado | B19: PT | C19: Private consumption | D19: PT | E19: % | G19: 2.5154342 | H19: 1.9446036
B20: AE | D20: EA | E20: % | G20: 1.7038409 | H20: 1.4126527
A22: Consumo público | B22: PT | C22: Public consumption | D22: PT | E22: % | G22: 0.91751522 | H22: 0.99940712
B23: AE | D23: EA | E23: % | G23: 1.4295846 | H23: 1.2818287
A25: FBCF | B25: PT | C25: GFCF | D25: PT | E25: % | G25: 6.305135 | H25: 4.3933992
B26: AE | D26: EA | E26: % | G26: 4.4164514 | H26: 1.0997625
A28: Exportações | B28: PT | C28: Exports | D28: PT | E28: % | G28: 5.4613035 | H28: 3.606888
B29: AE | D29: EA | E29: % | G29: 4.4448561 | H29: 2.3614353
A31: Importações | B31: PT | C31: Imports | D31: PT | E31: % | G31: 6.2151654 | H31: 3.860212
B32: AE | D32: EA | E32: % | G32: 5.2603534 | H32: 2.4406704
A34: Fontes: BCE, INE e Banco de Portugal. | Notas: (p) – projetado. As projeções para a área do euro correspondem ao exercício de projeção do BCE de março de 2024 (https://www.ecb.europa.eu/pub/projections/html/ecb.projections202403_ecbstaff~f2f2d34d5a.en.html#toc2).
A35: Sources: ECB, Statistics Portugal and Banco de Portugal. | Note: (p) – projected. The projections for the euro area refer to the ECB's staff Macroeconomic projection exercise of March 2024 (https://www.ecb.europa.eu/pub/projections/html/ecb.projections202403_ecbstaff~f2f2d34d5a.en.html#toc2).

Sheet GI.1.5
A5: Índice/Contents
A6: =+Índice!$A$5 -> Boletim Económico - março 2024 / Economic Bulletin - March 2024
A7: =+Índice!$A$7 -> Parte I. Projeções para a economia portuguesa: 2024-26 / Part I. Projections for the Portuguese economy: 2024-26
A10: Gráfico I.1.5 • Endividamento dos particulares, empresas não financeiras e administrações públicas em Portugal e na área do euro | Em percentagem do PIB
A11: Chart I.1.5 • Debt of households, non-financial corporations and public administrations in Portugal and the euro area | Percentage of GDP
A13: Unidade: % PIB
A14: Unit: % GDP
C15: 2001 | D15: 2002 | E15: 2003 | F15: 2004 | G15: 2005 | H15: 2006 | I15: 2007 | J15: 2008 | K15: 2009 | L15: 2010 | M15: 2011 | N15: 2012 | O15: 2013 | P15: 2014 | Q15: 2015 | R15: 2016 | S15: 2017 | T15: 2018 | U15: 2019 | V15: 2020 | W15: 2021 | X15: 2022 | Y15: 2023 T3
C16: 2001 | D16: 2002 | E16: 2003 | F16: 2004 | G16: 2005 | H16: 2006 | I16: 2007 | J16: 2008 | K16: 2009 | L16: 2010 | M16: 2011 | N16: 2012 | O16: 2013 | P16: 2014 | Q16: 2015 | R16: 2016 | S16: 2017 | T16: 2018 | U16: 2019 | V16: 2020 | W16: 2021 | X16: 2022 | Y16: 2023 Q3
A18: Painel A – Particulares | B18: Panel A – Households
A19: Portugal | B19: Portugal | C19: 65.235864 | D19: 69.147003 | E19: 73.21734 | F19: 77.53711 | G19: 81.589905 | H19: 85.553109 | I19: 88.504667 | J19: 90.6379 | K19: 93.929054 | L19: 92.606357 | M19: 92.26095 | N19: 92.231186 | O19: 87.812779 | P19: 83.538236 | Q19: 78.599698 | R19: 74.143461 | S19: 70.72262 | T19: 67.575891 | U19: 65.000232 | V19: 70.540996 | W19: 67.732389 | X19: 62.015143 | Y19: 57.296168
A20: Área do euro | B20: Euro area | C20: 49.345074 | D20: 50.646123 | E20: 52.560791 | F20: 54.351031 | G20: 57.047185 | H20: 58.838992 | I20: 59.60687 | J20: 60.457412 | K20: 63.865 | L20: 63.708441 | M20: 62.805646 | N20: 62.480853 | O20: 61.427911 | P20: 60.092343 | Q20: 58.822552 | R20: 58.203561 | S20: 57.483435 | T20: 57.313479 | U20: 57.401249 | V20: 61.747593 | W20: 59.546099 | X20: 56.909988
A23: Painel B – Sociedades não-financeiras | B23: Panel B – Non-financial corporations
A24: Portugal | B24: Portugal | C24: 94.580071 | D24: 94.379289 | E24: 96.717308 | F24: 95.33027 | G24: 96.602831 | H24: 98.083508 | I24: 104.4798 | J24: 112.84386 | K24: 117.60785 | L24: 117.0471 | M24: 120.57014 | N24: 126.73869 | O24: 121.70446 | P24: 113.75857 | Q24: 108.19208 | R24: 102.80363 | S24: 100.2001 | T24: 95.439938 | U24: 92.620712 | V24: 101.14969 | W24: 97.437664 | X24: 88.5505 | Y24: 82.284166
A25: Área do euro | B25: Euro area | C25: 74.276106 | D25: 74.144889 | E25: 75.377438 | F25: 74.595731 | G25: 77.286116 | H25: 80.117674 | I25: 83.675778 | J25: 88.393153 | K25: 92.586638 | L25: 91.944825 | M25: 92.431521 | N25: 92.896599 | O25: 91.100699 | P25: 90.393229 | Q25: 92.098436 | R25: 91.863732 | S25: 89.239583 | T25: 89.646477 | U25: 89.610057 | V25: 96.997077 | W25: 94.557441 | X25: 89.762436
C28: 2001 | D28: 2002 | E28: 2003 | F28: 2004 | G28: 2005 | H28: 2006 | I28: 2007 | J28: 2008 | K28: 2009 | L28: 2010 | M28: 2011 | N28: 2012 | O28: 2013 | P28: 2014 | Q28: 2015 | R28: 2016 | S28: 2017 | T28: 2018 | U28: 2019 | V28: 2020 | W28: 2021 | X28: 2022 | Y28: 2023
A29: Painel C – Administrações públicas | B29: Panel C – Public administrations
A30: Portugal | B30: Portugal | C30: 57.380219 | D30: 60.043717 | E30: 63.897284 | F30: 67.099504 | G30: 72.249078 | H30: 73.679394 | I30: 72.727965 | J30: 75.642544 | K30: 87.79906 | L30: 100.21448 | M30: 114.40307 | N30: 129.03504 | O30: 131.42974 | P30: 132.94068 | Q30: 131.17912 | R30: 131.50573 | S30: 126.14343 | T30: 121.48136 | U30: 116.60778 | V30: 134.89747 | W30: 124.54758 | X30: 112.41826 | Y30: 98.984575
A31: Área do euro | B31: Euro area | C31: 68.1 | D31: 68 | E31: 69.3 | F31: 69.6 | G31: 70.3 | H31: 68.3 | I31: 65.9 | J31: 69.6 | K31: 80.2 | L31: 85.6 | M31: 87.5 | N31: 91 | O31: 93 | P31: 93.2 | Q31: 91.3 | R31: 90.4 | S31: 88.1 | T31: 86.1 | U31: 84.1 | V31: 97.2 | W31: 94.7 | X31: 90.9 | Y31: 89.9
A33: Fontes: Banco de Portugal e BCE. | Notas: Valores consolidados. As séries de endividamento de particulares e empresas não financeiras para a área do euro têm periodicidade anual (última observação: 2022). No caso das administrações públicas, a última observação disponível para a área do euro corresponde a 2023 T3.
A34: Sources: Banco de Portugal and ECB. | Notes: Consolidated values.The euro area debt series for households and non-financial corporations are annualised (last observation: 2022). For the public administrations debt series, the last observation available for the euro area corresponds to 2023 Q3.

Sheet GI.1.6
A5: Índice/Contents
A6: =+Índice!$A$5 -> Boletim Económico - março 2024 / Economic Bulletin - March 2024
A7: =+Índice!$A$7 -> Parte I. Projeções para a economia portuguesa: 2024-26 / Part I. Projections for the Portuguese economy: 2024-26
A10: Gráfico I.1.6 • Consumo privado, rendimento disponível real e taxa de poupança
A11: Chart I.1.6 • Private consumption, real disposable income and savings rate
C12: Unidade | D12: Unit | E12: 2016 | F12: 2017 | G12: 2018 | H12: 2019 | I12: 2020 | J12: 2021 | K12: 2022 | L12: 2023 | M12: 2024 (p) | N12: 2025 (p) | O12: 2026 (p)
A14: Consumo privado | B14: Private consumption | C14: Dados encadeados em volume, em milhões de euros | D14: Chain linked volumes, million euros | E14: 122.02435 | F14: 124.58793 | G14: 127.84622 | H14: 132.01822 | I14: 122.74821 | J14: 128.55117 | K14: 135.68604 | L14: 137.90268 | M14: 140.77394 | N14: 143.48399 | O14: 146.10489
A15: Rendimento disponível real | B15: Real disposable income | C15: Dados encadeados em volume, em milhões de euros | D15: Chain linked volumes, million euros | E15: 131.24924 | F15: 133.34189 | G15: 137.115 | H15: 142.27015 | I15: 139.33862 | J15: 143.83725 | K15: 145.06643 | L15: 147.88607 | M15: 153.78489 | N15: 156.80328 | O15: 159.62067
A16: Taxa de poupança (esc. direita) | B16: Savings rate (r.h.s.) | C16: Em percentagem do rendimento disponível | D16: Percentage of disposable income | E16: 7.0285319 | F16: 6.5650436 | G16: 6.7598567 | H16: 7.2059566 | I16: 11.90654 | J16: 10.62734 | K16: 6.4662763 | L16: 6.7507289 | M16: 8.460487 | N16: 8.4942682 | O16: 8.4674355
A19: Fontes: Banco de Portugal e INE. | Nota: (p) – projetado.
A20: Sources: Banco de Portugal and Statistics Portugal. | Note: (p) – projected.

Sheet GI.1.7
A5: Índice/Contents
A6: =+Índice!$A$5 -> Boletim Económico - março 2024 / Economic Bulletin - March 2024
A7: =+Índice!$A$7 -> Parte I. Projeções para a economia portuguesa: 2024-26 / Part I. Projections for the Portuguese economy: 2024-26
A10: Gráfico I.1.7 • FBCF em percentagem do PIB | Percentagem
A11: Chart I.1.7 • GFCF percentage of GDP | Percentage
C13: Unidade/Unit | D13: 2000 | E13: 2001 | F13: 2002 | G13: 2003 | H13: 2004 | I13: 2005 | J13: 2006 | K13: 2007 | L13: 2008 | M13: 2009 | N13: 2010 | O13: 2011 | P13: 2012 | Q13: 2013 | R13: 2014 | S13: 2015 | T13: 2016 | U13: 2017 | V13: 2018 | W13: 2019 | X13: 2020 | Y13: 2021 | Z13: 2022 | AA13: 2023 | AB13: 2024 (p) | AC13: 2025 (p) | AD13: 2026 (p)
A15: FBCF total | B15: Total GFCF | C15: % | D15: 24.848814 | E15: 24.61209 | F15: 23.595373 | G15: 22.075048 | H15: 21.728076 | I15: 21.583264 | J15: 21.077413 | K15: 21.196592 | L15: 21.218611 | M15: 20.251365 | N15: 19.681436 | O15: 17.499926 | P15: 15.191621 | Q15: 14.596259 | R15: 14.812947 | S15: 15.41353 | T15: 15.493265 | U15: 16.688141 | V15: 17.228985 | W15: 17.68285 | X15: 18.863619 | Y15: 19.278872 | Z15: 18.587558 | AA15: 18.616569 | AB15: 18.904055 | AC15: 19.484754 | AD15: 19.849034
A16: FBCF pública | B16: Public GFCF | C16: % | D16: 4.2199233 | E16: 4.6483026 | F16: 4.2763878 | G16: 4.1215508 | H16: 4.1691025 | I16: 3.856509 | J16: 3.1777109 | K16: 3.0668756 | L16: 3.4803788 | M16: 3.941604 | N16: 5.0675423 | O16: 3.3177071 | P16: 2.375338 | Q16: 2.1519388 | R16: 1.9675556 | S16: 2.242846 | T16: 1.5419046 | U16: 1.7720809 | V16: 1.8033576 | W16: 1.7652773 | X16: 2.2615707 | Y16: 2.4468567 | Z16: 2.1786811 | AA16: 2.4042469 | AB16: 2.6426301 | AC16: 2.8484384 | AD16: 2.8556879
A17: FBCF residencial | B17: Residential GFCF | C17: % | D17: 7.7060372 | E17: 7.3226399 | F17: 7.0162557 | G17: 5.9999625 | H17: 5.8292267 | I17: 5.8201641 | J17: 5.3245693 | K17: 4.9037369 | L17: 4.2478582 | M17: 3.7326928 | N17: 3.4165304 | O17: 3.0478115 | P17: 2.9361341 | Q17: 2.5476179 | R17: 2.5122854 | S17: 2.5019207 | T17: 2.6152356 | U17: 2.734291 | V17: 2.8313415 | W17: 2.8165809 | X17: 2.8336877 | Y17: 3.078137 | Z17: 2.9702712 | AA17: 2.8739712 | AB17: 2.8037936 | AC17: 2.7912645 | AD17: 2.7986456
A18: FBCF privada não residencial | B18: Private-sector non-residential GFCF | C18: % | D18: 12.922853 | E18: 12.641148 | F18: 12.302729 | G18: 11.953534 | H18: 11.729747 | I18: 11.906591 | J18: 12.575133 | K18: 13.22598 | L18: 13.490374 | M18: 12.577068 | N18: 11.197364 | O18: 11.134407 | P18: 9.880149 | Q18: 9.8967026 | R18: 10.333106 | S18: 10.668764 | T18: 11.336125 | U18: 12.181769 | V18: 12.594286 | W18: 13.100991 | X18: 13.76836 | Y18: 13.753878 | Z18: 13.438606 | AA18: 13.338351 | AB18: 13.457632 | AC18: 13.845051 | AD18: 14.1947
A21: Fontes: Banco de Portugal e INE. | Notas: (p) projetado. Rácio do investimento sobre o PIB, dados encadeados em volume (base 2016).
A22: Sources: Banco de Portugal and Statistics Portugal. | Notes: (p) - projected. Investment to GDP ratio, chain linked volumes (2016).

Sheet GI.1.8
A5: Índice/Contents
A6: =+Índice!$A$5 -> Boletim Económico - março 2024 / Economic Bulletin - March 2024
A7: =+Índice!$A$7 -> Parte I. Projeções para a economia portuguesa: 2024-26 / Part I. Projections for the Portuguese economy: 2024-26
A10: Gráfico I.1.8 • Balança corrente e de capital| Em percentagem do PIB
A11: Chart I.1.8 • Current and capital account | Percentage of GDP
D13: Unidade/unit | E13: 2001 | F13: 2002 | G13: 2003 | H13: 2004 | I13: 2005 | J13: 2006 | K13: 2007 | L13: 2008 | M13: 2009 | N13: 2010 | O13: 2011 | P13: 2012 | Q13: 2013 | R13: 2014 | S13: 2015 | T13: 2016 | U13: 2017 | V13: 2018 | W13: 2019 | X13: 2020 | Y13: 2021 | Z13: 2022 | AA13: 2023 | AB13: 2024 (p) | AC13: 2025 (p) | AD13: 2026 (p)
A15: Balança corrente e de capital | B15: Current and capital account | D15: % | E15: -8.9133228 | F15: -6.4957542 | G15: -4.4388352 | H15: -6.2394112 | I15: -8.1620089 | J15: -9.070667 | K15: -8.4784722 | L15: -10.62894 | M15: -9.1274675 | N15: -8.8654226 | O15: -4.4829763 | P15: 0.46765212 | Q15: 3.2883846 | R15: 1.4769496 | S15: 1.4773052 | T15: 2.0876594 | U15: 2.1500439 | V15: 1.5474591 | W15: 1.3235582 | X15: -0.051471457 | Y15: 0.9584793 | Z15: -0.20254121 | AA15: 2.7255972 | AB15: 3.595957 | AC15: 3.8835519 | AD15: 4.08046
A16: Balança de bens | B16: Goods account | D16: % | E16: -12.81871 | F16: -10.875434 | G16: -9.1812796 | H16: -10.801884 | I16: -11.399418 | J16: -11.249533 | K16: -11.421162 | L16: -13.398861 | M16: -10.358466 | N16: -10.848176 | O16: -8.2332002 | P16: -5.5535012 | Q16: -4.7667925 | R16: -5.5874448 | S16: -5.4230871 | T16: -5.3687058 | U16: -6.7918982 | V16: -7.623305 | W16: -7.5972319 | X16: -6.2377506 | Y16: -7.4275571 | Z16: -10.907819 | AA16: -9.3102581 | AB16: -9.3592208 | AC16: -9.4321019 | AD16: -9.291397
A17: Balança de serviços | B17: Services account | D17: % | E17: 2.7692818 | F17: 2.8060698 | G17: 2.8302553 | H17: 3.0679075 | I17: 2.8678941 | J17: 3.4659391 | K17: 4.1201951 | L17: 4.1503448 | M17: 3.5932637 | N17: 3.5166424 | O17: 4.5260003 | P17: 5.5552656 | Q17: 6.5069952 | R17: 6.3800646 | S17: 6.8253161 | T17: 7.0710723 | U17: 8.2569825 | V17: 8.5244645 | W17: 8.3729701 | X17: 4.3012241 | Y17: 4.8602074 | Z17: 8.9758785 | AA17: 10.542982 | AB17: 10.484159 | AC17: 10.662495 | AD17: 10.770484
A18: Balanças de rendimento e capital | B18: Income and capital accounts | D18: % | E18: 1.1361057 | F18: 1.5736098 | G18: 1.9121891 | H18: 1.4945655 | I18: 0.36951521 | J18: -1.2870734 | K18: -1.1775056 | L18: -1.3804242 | M18: -2.3622654 | N18: -1.5338886 | O18: -0.77577642 | P18: 0.46588773 | Q18: 1.5481819 | R18: 0.68432976 | S18: 0.075076272 | T18: 0.38529293 | U18: 0.68495957 | V18: 0.64629955 | W18: 0.54782001 | X18: 1.885055 | Y18: 3.525829 | Z18: 1.7293993 | AA18: 1.4928729 | AB18: 2.4710191 | AC18: 2.6531593 | AD18: 2.6013727
A21: Fontes: Banco de Portugal e INE. | Notas: (p) – projetado.
A22: Sources: Banco de Portugal and Statistics Portugal. | Notes: (p) - projected.

Sheet GI.1.9
A5: Índice/Contents
A6: =+Índice!$A$5 -> Boletim Económico - março 2024 / Economic Bulletin - March 2024
A7: =+Índice!$A$7 -> Parte I. Projeções para a economia portuguesa: 2024-26 / Part I. Projections for the Portuguese economy: 2024-26
A10: Gráfico I.1.9 • Variação de postos de trabalho entre 2019 e 2023 e remuneração média mensal em 2023 - por intensidade tecnológica e de conhecimento | Em milhares e em euros
A11: Chart I.1.9 • Change in jobs between 2019 and 2023 and average monthly wages in 2023 - by technological and knowledge intensity | Thousands and euros
E13: Total da economia | F13: Indústrias de alta e média tecnologia e Serviços intensivos em conhecimento | G13: Indústrias de baixa tecnologia e Serviços pouco intensivos em conhecimento | H13: Outros setores
E14: Total economy | F14: High- and medium-tech industries and knowledge-intensive services | G14: Low-tech industries and low knowledge-intensive services | H14: Other sectors
C15: Unidade | D15: unit | E15: (100) | F15: (47) | G15: (42) | H15: (11)
A17: Variação de postos de trabalho - 2023 vs. 2019 | B17: Change in jobs - 2023 vs. 2019 | C17: Milhares de postos de trabalho | D17: Thousands of jobs | E17: 456.7 | F17: 215.8 | G17: 148.3 | H17: 92.6
A18: Remuneração média mensal - 2023 (esc. direita) | B18: Average monthly wages - 2023 (r.h.s.) | C18: Euros | D18: Euros | E18: 1505 | F18: 1803.0773 | G18: 1263.569 | H18: 1165.1551
A21: Fonte: INE (com base em informação da Segurança Social e Caixa Geral de Aposentações). | Notas: A informação apresentada relativa aos postos de trabalho e à remuneração média por intensidade tecnológica e de conhecimento foi obtida através da classificação da atividade económica das empresas. Indústrias de alta e média tecnologia e Serviços intensivos em conhecimento – inclui a Indústria transformadora com exceção das indústrias alimentar, têxtil, madeira e papel e os Serviços de transporte de água e aéreos, de informação e de comunicação, financeiros e seguros, de consultoria e científicos, Administração Pública, Saúde e Educação, Atividades artísticas. Indústrias de baixa tecnologia e Serviços pouco intensivos em conhecimento – inclui as Indústrias alimentar, têxtil, madeira e papel e os Serviços de armazenagem, transportes terrestres, Alojamento e restauração e Outros serviços. Outros setores - inclui: Agricultura, silvicultura e pesca, Indústrias extrativas, Energia e Construção. Os valores entre parêntesis correspondem à percentagem do emprego em cada setor no emprego total da economia em 2023.
A22: Source: Statistics Portugal (based on information from Social Security and Caixa Geral de Aposentações). | Notes: the information presented on jobs and average wages by technological and knowledge intensity was obtained through classifying companies by economic activity. High- and medium-tech industries and knowledge-intensive services - includes Manufacturing, with the exception of Food, Textiles, Wood and Paper, Water and air transport, Information and communication, Financial and insurance, Consultancy and scientific services, Public administration, Health and education, Artistic activities. Low-tech industries and services that are low knowledge-intensive - includes food, textiles, wood and paper industries and storage services, land transport, accommodation and food services and other services. Other sectors - includes: Agriculture, forestry and fishing, Mining and quarrying, Energy and Construction. The values in brackets correspond to the share of each sector in the economy's total employment in 2023.

Sheet QC1.1
A5: Índice/Contents
A6: =+Índice!$A$5 -> Boletim Económico - março 2024 / Economic Bulletin - March 2024
A7: =+Índice!$A$29 -> Caixa 1- Enquadramento e políticas / Box 1-External environment, financing conditions and policies
A10: Quadro C1.1 • Hipóteses do exercício de projeção
A11: Table C1.1 • Eurosystem staff projection assumptions
E13: BE março 2024 | I13: Revisões face ao BE dezembro 2023
C14: Unidade | D14: Unit | E14: EB March 2024 | I14: Revisions from EB December 2023
E15: 2023 | F15: 2024 | G15: 2025 | H15: 2026 | I15: 2023 | J15: 2024 | K15: 2025 | L15: 2026
A17: Enquadramento internacional | B17: International environment
A18: PIB mundial | B18: World GDP | C18: tva | D18: yoy | E18: 3.1132813 | F18: 3.0306096 | G18: 3.0380423 | H18: 3.0372859 | I18: 0.13105938 | J18: 0.22196955 | K18: 0.04499832 | L18: 0.010746717
A19: PIB Área do euro | B19: Euro area GDP | C19: tva | D19: yoy | E19: 0.5 | F19: 0.6 | G19: 1.5 | H19: 1.6 | I19: -0.061546105 | J19: -0.24940954 | K19: -0.025214233 | L19: 0.056078019
A20: Comércio mundial | B20: World trade | C20: tva | D20: yoy | E20: 0.55748729 | F20: 2.3258895 | G20: 3.1307363 | H20: 3.2328624 | I20: -0.17036155 | J20: -0.42342613 | K20: 0.084163578 | L20: 0.14114455
A21: Procura externa | B21: External demand | C21: tva | D21: yoy | E21: -0.46342756 | F21: 1.5468758 | G21: 3.1400998 | H21: 3.1352816 | I21: -0.12955271 | J21: -0.48779565 | K21: 0.1178946 | L21: 0.21999729
A23: Preços internacionais | B23: International prices
A24: Preço do petróleo | B24: Oil prices | C24: vma | D24: aav | E24: 77.451136 | F24: 73.749327 | G24: 69.332302 | H24: 66.840435 | I24: -0.28959686 | J24: -0.16370936 | K24: -1.2978501 | L24: -1.0849984
A25: Preço do gás (MWh) | B25: Gas prices (MWh) | C25: vma | D25: aav | E25: 40.613095 | F25: 29.98618 | G25: 32.086875 | H25: 29.541692 | I25: -0.91096472 | J25: -17.403778 | K25: -12.082983 | L25: -7.341225
A26: Matérias-primas não energéticas | B26: Non-oil commodity prices | C26: tva | D26: yoy | E26: -14.529676 | F26: 0.62146628 | G26: 2.0979264 | H26: 0.069662752 | I26: 0.68728707 | J26: 3.2083115 | K26: -0.34037183 | L26: -1.607026
A27: Preço de importação dos concorrentes | B27: Competitors' import prices | C27: tva | D27: yoy | E27: -1.3084794 | F27: 1.038034 | G27: 2.644447 | H27: 2.4174107 | I27: -0.29985759 | J27: -0.92467597 | K27: -0.0082151102 | L27: 0.17440592
A29: Condições monetárias e financeiras | B29: Monetary and financial conditions
A30: Taxa de juro de curto prazo (EURIBOR a 3 meses) | B30: Short-term interest rate (3-month EURIBOR) | C30: % | D30: % | E30: 3.4308006 | F30: 3.4278973 | G30: 2.4458333 | H30: 2.3529167 | I30: -0.0043677092 | J30: -0.17460263 | K30: -0.39458334 | L30: -0.33500004
A31: Taxa de juro implícita da dívida pública portuguesa | B31: Implicit interest rate in portuguese public debt | C31: % | D31: % | E31: 2.1169839 | F31: 2.3353418 | G31: 2.3544669 | H31: 2.4016181 | I31: 0.02488075 | J31: 0.018396698 | K31: 0.00172273 | L31: -0.012677878
A32: Índice de taxa de câmbio efetiva | B32: Effective exchange rate index | C32: tva | D32: yoy | E32: 4.8827668 | F32: 1.0657872 | G32: -0.033893056 | H32: 0 | I32: -0.023350962 | J32: -0.31553381 | K32: -0.033893056 | L32: 0
A33: Taxa de câmbio euro-dólar | B33: Euro-dollar exchange rate | C33: vma | D33: aav | E33: 1.0813067 | F33: 1.0808436 | G33: 1.07998 | H33: 1.07998 | I33: 0.0006369475 | J33: -0.0027564062 | K33: -0.00362 | L33: -0.00362
A36: Fontes: Banco de Portugal e Eurosistema (cálculos do Banco de Portugal). | Notas: tva – taxa de variação anual, % – em percentagem, vma – valor médio anual, MWh – megawatt-hora. As hipóteses técnicas e de enquadramento externo e as projeções para o PIB e inflação da área do euro coincidem com as do exercício de projeção do BCE divulgado a 7 de março (ver “Projeções macroeconómicas para a área do euro elaboradas por especialistas do Eurosistema”, março de 2024), incluindo a informação disponível até 12 de fevereiro. Os preços internacionais são medidos em euros. A hipótese técnica para o preço do petróleo, gás e matérias-primas não energéticas assenta nos mercados de futuros. O preço de importação dos concorrentes corresponde a uma média ponderada dos deflatores de exportação dos países dos quais Portugal importa, ponderada pelo peso relativo nas importações portuguesas (para mais informação, ver “Trade consistency in the context of the Eurosystem projection exercises: an overview”, ECB Ocasional Paper 108, março de 2010). A evolução da taxa EURIBOR a 3 meses tem por base as expetativas implícitas nos contratos de futuros. A taxa de juro implícita da dívida pública é calculada como o rácio entre a despesa em juros do ano e a média simples do stock da dívida no final do ano e no final do ano anterior. Um aumento da taxa de câmbio corresponde a uma apreciação. O índice de taxa de câmbio efetiva do euro é calculado face a um grupo de 41 países parceiros. A revisão da taxa de câmbio euro-dólar é apresentada em percentagem. A hipótese técnica para as taxas de câmbio bilaterais pressupõe a manutenção ao longo do horizonte de projeção dos níveis médios observados nas duas semanas anteriores à data de fecho da informação.
A37: Sources: Banco de Portugal and Eurosystem (Banco de Portugal calculations). | Notes: yoy – year-on-year rate of change, % – in percentage, aav – annual average value, MWh – megawatt-hour. Technical and external environment assumptions, as well as projections for euro area GDP and inflation, coincide with those in the ECB projection exercise released on March 7 ("Eurosystem staff macroeconomic projections for the euro area", March 2024), which include information up to February 12. International prices are in euros. The technical assumption for the price of oil, gas and non-energy commodities is based on futures markets. The import price of competitors corresponds to a weighted average of the export deflators of the countries from which Portugal imports, weighted by their share on total Portuguese imports (for more information, see "Trade consistency in the context of the Eurosystem projection exercises: an overview", ECB Occasional Paper 108, March 2010). The evolution of the 3-month EURIBOR is based on expectations implied in futures contracts. The implicit interest rate on public debt is computed as the ratio of interest expenditure for the year to the simple average of the stock of debt at the end of the same year and at the end of the preceding year. An increase in the exchange rate corresponds to an appreciation of the euro. The effective exchange rate of the euro is computed against 41 trading partner countries. Revisions in the euro-dollar exchange rate are in percentage. The technical assumption for bilateral exchange rates assumes that the average levels observed in the two weeks prior to the cut-off date are maintained over the projection horizon.

Sheet GC1.1
A5: Índice/Contents
A6: =+Índice!$A$5 -> Boletim Económico - março 2024 / Economic Bulletin - March 2024
A7: =+Índice!$A$29 -> Caixa 1- Enquadramento e políticas / Box 1-External environment, financing conditions and policies
A10: Gráfico C1.1 • PIB da área do euro e maiores países | Taxa de variação anual
A11: Chart C1.1 • Euro area and major countries GDP | Annual rate of change
C14: Área do euro | D14: Alemanha | E14: França | F14: Itália | G14: Espanha
B15: Unidade/unit | C15: Euro area | D15: Germany | E15: France | F15: Italy | G15: Spain
A17: 2020 | B17: % | C17: -6.2447671 | D17: -4.1974209 | E17: -7.6786926 | F17: -9.0496266 | G17: -11.167321
A18: 2021 | B18: % | C18: 5.889132 | D18: 3.1243151 | E18: 6.364221 | F18: 8.2783689 | G18: 6.4031926
A19: 2022 | B19: % | C19: 3.4622487 | D19: 1.8814451 | E19: 2.5261547 | F19: 4.1451845 | G19: 5.770717
A20: 2023 | B20: % | C20: 0.53539515 | D20: -0.10871221 | E20: 0.86885782 | F20: 1.01723 | G20: 2.5016792
A23: Fonte: Eurostat (cálculos do Banco de Portugal).
A24: Source: Eurostat (Banco de Portugal calculations).

Sheet QC2.1
A5: Índice/Contents
A6: =+Índice!$A$5 -> Boletim Económico - março 2024 / Economic Bulletin - March 2024
A7: =+Índice!$A$35 -> Caixa 2 - Expetativas de taxas de juro e de consumo das famílias / Box 2 - Consumers' expectations on interest rates and consumption
A10: Quadro C2.1 • Características dos consumidores inquiridos | Valores médios e percentagem
A11: Table C2.1 • Characteristics of the surveyed consumers | Mean values and percentage
C14: Unidade/Unit | D14: Com crédito à habitação | E14: Sem crédito à habitação | F14: Todos os consumidores
D15: With mortgage | E15: Withouth mortgage | F15: All consumers
A16: Idade | B16: Age | C16: Anos / Years | D16: 41.5 | E16: 40.6 | F16: 40.9
A17: Educação | B17: Education | C17: Percentagem com ensino superior / Percentage with higher education | D17: 57 | E17: 51 | F17: 54
A18: Rendimento anual | B18: Yearly income | C18: Euros / Euro | D18: 25562.9 | E18: 21894.9 | F18: 23330.3
A19: Poupanças nos últimos 3 meses | B19: Savings in the last 3 months | C19: Euros / Euro | D19: 1011.5 | E19: 1256.8 | F19: 1157.6
A20: Número de famílias | B20: Number of aggregates | C20: Número e percentagem / Number and percentage | D20: 1599 (39%) | E20: 2487 (61%) | F20: 4086 (100%)
A23: Fonte: Inquérito sobre as Expetativas dos Consumidores (BCE). | Nota: Os valores médios da idade, do rendimento e da poupança são calculados com o ponto médio de cada intervalo de resposta. Para a idade, existem quatro intervalos: 18-34, 35-54, 55-70 e +70. Para a educação, existem três níveis de resposta: Ensino Básico, Secundário e Superior. Para o rendimento anual e para a poupança existem 10 intervalos de resposta. A definição da situação relativamente ao crédito à habitação de cada consumidor é construída através da questão: “Qual das seguintes opções melhor descreve a sua (e do seu agregado familiar) residência?”.
A24: Sources: Consumer Expectations Survey (ECB). | Note: The mean values for age, income and savings are computed with the mean value of each bracket. For age, there are four brackets: 18-34, 35-54, 55-70 and +70. For education, there are three possible respondes: Primary Education, Secondary Education and Higher Education. For the yearly income and for savings there are 10 possible brackets. The classification by housing type for each consumer is done with the question: "Which of the following describes your (and your family’s) main place of residence?".

Sheet GC2.1
A5: Índice/Contents
A6: =+Índice!$A$5 -> Boletim Económico - março 2024 / Economic Bulletin - March 2024
A7: =+Índice!$A$35 -> Caixa 2 - Expetativas de taxas de juro e de consumo das famílias / Box 2 - Consumers' expectations on interest rates and consumption
A10: Gráfico C2.1 • Situação financeira dos consumidores em Portugal total e por situação de crédito | Saldo de respostas extremas
A11: Chart C2.1 • Consumers' financial situation in Portugal in total and by housing type | Net percentage
A13: Unidade/Unit
C14: Meses | D14: abr 2022 | E14: mai 2022 | F14: jun 2022 | G14: jul 2022 | H14: ago 2022 | I14: set 2022 | J14: out 2022 | K14: nov 2022 | L14: dez 2022 | M14: jan 2023 | N14: fev 2023 | O14: mar 2023 | P14: abr 2023 | Q14: mai 2023 | R14: jun 2023 | S14: jul 2023 | T14: ago 2023 | U14: set 2023 | V14: out 2023 | W14: nov 2023 | X14: dez 2023
C15: Months | D15: apr 2022 | E15: may 2022 | F15: jun 2022 | G15: jul 2022 | H15: aug 2022 | I15: sep 2022 | J15: oct 2022 | K15: nov 2022 | L15: dec 2022 | M15: jan 2023 | N15: feb 2023 | O15: mar 2023 | P15: apr 2023 | Q15: may 2023 | R15: jun 2023 | S15: jul 2023 | T15: aug 2023 | U15: sep 2023 | V15: oct 2023 | W15: nov 2023 | X15: dec 2023
B17: Painel A - Últimos 12 meses | C17: Panel A: Last 12 months
A18: S.R.E / Net percentage | B18: Todos os consumidores | C18: All consumers | D18: -45.543541 | E18: -47.099003 | F18: -52.714321 | G18: -47.820717 | H18: -47.417629 | I18: -51.71402 | J18: -55.701748 | K18: -54.805828 | L18: -55.360119 | M18: -52.654766 | N18: -54.864407 | O18: -55.618893 | P18: -51.978989 | Q18: -47.580296 | R18: -44.827164 | S18: -39.573837 | T18: -36.420158 | U18: -43.632675 | V18: -40.416271 | W18: -40.733833 | X18: -39.576805
A19: S.R.E / Net percentage | B19: Com crédito à habitação | C19: With mortgage | D19: -49.086838 | E19: -50.23686 | F19: -53.551596 | G19: -51.256279 | H19: -47.466251 | I19: -57.600185 | J19: -63.169003 | K19: -61.725046 | L19: -58.387814 | M19: -55.188545 | N19: -57.007074 | O19: -56.342489 | P19: -59.840986 | Q19: -54.828539 | R19: -53.267044 | S19: -49.881516 | T19: -49.685043 | U19: -46.499666 | V19: -47.851738 | W19: -49.505829 | X19: -43.798344
A20: S.R.E / Net percentage | B20: Sem crédito à habitação | C20: Without mortgage | D20: -43.651447 | E20: -45.448654 | F20: -52.255856 | G20: -45.921253 | H20: -47.393082 | I20: -48.893433 | J20: -51.892166 | K20: -51.032829 | L20: -53.808918 | M20: -51.412457 | N20: -53.795105 | O20: -55.264065 | P20: -48.006702 | Q20: -43.439953 | R20: -40.074997 | S20: -33.523422 | T20: -29.04187 | U20: -42.128601 | V20: -36.34288 | W20: -36.045994 | X20: -37.296978
B22: Painel B - Próximos 12 meses | C22: Panel B: Next 12 months
A23: S.R.E / Net percentage | B23: Todos os consumidores | C23: All consumers | D23: -30.723333 | E23: -31.459055 | F23: -37.083076 | G23: -31.759291 | H23: -30.716162 | I23: -36.375626 | J23: -42.163052 | K23: -36.766991 | L23: -35.454388 | M23: -33.602627 | N23: -27.440767 | O23: -27.142879 | P23: -19.131081 | Q23: -15.568834 | R23: -14.746832 | S23: -11.816614 | T23: -13.945408 | U23: -15.686953 | V23: -20.116486 | W23: -18.63155 | X23: -16.817703
A24: S.R.E / Net percentage | B24: Com crédito à habitação | C24: With mortgage | D24: -41.247543 | E24: -39.749611 | F24: -36.712227 | G24: -34.230743 | H24: -33.056908 | I24: -47.320572 | J24: -49.144672 | K24: -46.578545 | L24: -42.981792 | M24: -38.870605 | N24: -36.662086 | O24: -31.936535 | P24: -29.315941 | Q24: -21.366671 | R24: -19.665657 | S24: -20.641647 | T24: -25.382534 | U24: -21.743393 | V24: -25.594881 | W24: -22.795879 | X24: -14.140606
A25: S.R.E / Net percentage | B25: Sem crédito à habitação | C25: Without mortgage | D25: -25.10347 | E25: -27.098646 | F25: -37.286144 | G25: -30.39286 | H25: -29.534441 | I25: -31.13092 | J25: -38.601227 | K25: -31.416819 | L25: -31.597834 | M25: -31.019756 | N25: -22.838858 | O25: -24.792246 | P25: -13.985161 | Q25: -12.256998 | R25: -11.977232 | S25: -6.6364956 | T25: -7.5837669 | U25: -12.509634 | V25: -17.11524 | W25: -16.406094 | X25: -18.263462
A28: Fonte: Inquérito sobre as Expetativas dos Consumidores (BCE). | Notas: As questões correspondentes são, respetivamente: “A situação financeira do seu agregado familiar está melhor ou pior do que estava há 12 meses?” (Painel A) e “Em termos prospetivos, a situação financeira do seu agregado familiar estará melhor ou pior em 12 meses?” (Painel B). A definição da situação relativamente ao crédito à habitação de cada consumidor é construída através da questão: “Qual das seguintes opções melhor descreve a sua (e do seu agregado familiar) residência?”. O saldo de respostas extremas é calculado como a diferença entre a percentagem de respostas “Melhoria” e “Deterioração”. As estatísticas apresentadas são calculadas com ponderadores mensais que garantem a representatividade da amostra com a estrutura demográfica da população.
A29: Sources: Consumer Expectations Survey (ECB). | Notes: The corresponding questions are, respectively: "Do you think your household is financially better off or worse off now than it was 12 months ago?" (Panel A) and "And looking ahead, do you think your household will be financially better off or worse off in 12 months from now than it is today?" (Panel B). The classification by housing type for each consumer is done with the question: "Which of the following describes your (and your family’s) main place of residence?". The net percentage is calculated as the difference between the percentage of "better off" and "worse off" responses. The presented statistics are calculated using monthly weights that ensure the representativeness of the sample with the demographic structure of the population.

Sheet GC2.2
A5: Índice/Contents
A6: =+Índice!$A$5 -> Boletim Económico - março 2024 / Economic Bulletin - March 2024
A7: =+Índice!$A$35 -> Caixa 2 - Expetativas de taxas de juro e de consumo das famílias / Box 2 - Consumers' expectations on interest rates and consumption
A10: Gráfico C2.2 • Impacto do aumento de 1 pp nas expetativas de taxas de juro sobre as expetativas de consumo nos 12 meses seguintes | Pontos percentuais
A11: Chart C2.2 • Impact of an increase of 1 pp of expectatations for interest rates on spending expectations in the next 12 months | Percentage points
A14: Unidade/Unit | D14: Coeficiente | E14: Limite inferior do intervalo de confiança | F14: Limite superior do intervalo de confiança
D15: Coefficient | E15: Lower bound of the confidence interval | F15: Upper bound of the confidence interval
B17: Painel A: Expetativas de taxas de juro no crédito à habitação | C17: Panel A: Expectations on interest rates of mortgages
A18: Pontos percentuais/Percentage points | B18: Todos os consumidores | C18: All consumers | D18: -0.2251589 | E18: -0.168 | F18: -0.1108411
A19: Pontos percentuais/Percentage points | B19: Com crédito à habitação | C19: With mortgage | D19: -0.7680296 | E19: -0.668 | F19: -0.5679704
A20: Pontos percentuais/Percentage points | B20: Sem crédito à habitação | C20: Without mortgage | D20: 0.0034253 | E20: 0.072632 | F20: 0.1418387
B22: Painel B: Expetativas de taxas de juro nos depósitos | C22: Panel B: Expectations on interest rates of savings accounts
A23: Pontos percentuais/Percentage points | B23: Todos os consumidores | C23: All consumers | D23: 0.132793 | E23: 0.285304 | F23: 0.437815
A24: Pontos percentuais/Percentage points | B24: Com crédito à habitação | C24: With mortgage | D24: -0.0354244 | E24: 0.2240634 | F24: 0.4835512
A25: Pontos percentuais/Percentage points | B25: Sem crédito à habitação | C25: Without mortgage | D25: 0.1290993 | E25: 0.3176151 | F25: 0.5061309
A28: Fonte: Inquérito sobre as Expetativas dos Consumidores (BCE) e cálculos do Banco de Portugal. | Notas: Cada barra mostra a elasticidade das expetativas de consumo real a uma alteração nas expetativas de taxa de juro no crédito à habitação (Painel A) e nos depósitos (Painel B) de 1%. Os intervalos de confiança correspondem a um nível de confiança de 95%. O intervalo temporal inclui os dados de abril de 2022 até dezembro de 2023. As questões correspondentes são: “Quanto é que os gastos do seu agregado familiar com todos os bens e serviços irão mudar nos próximos 12 meses?” para as expetativas sobre o crescimento nominal do consumo; “Nos próximos 12 meses, o que espera que aconteça com o rendimento líquido total do seu agregado familiar (após impostos e deduções obrigatórias)?” para as expetativas sobre o crescimento nominal do rendimento; “Daqui a 12 meses, qual é será o valor das taxas de juro nos créditos à habitação do país em que reside?” para as expetativas de taxa de juro no crédito à habitação e “Daqui a 12 meses, qual é será a taxa de juro nos depósitos do país em que reside?” para as expetativas de taxa de juro nos depósitos. Foram apenas consideradas as respostas as estas duas últimas perguntas entre o 5º e 95º percentil para cada país e mês.
A29: Sources: Consumer Expectations Survey (ECB) and calculations by Banco de Portugal. | Notes: Each bar shows the elasticity of real spending expectations to a 1% change in expectations of interest rates on mortgages (Panel A) and interest rates on saving accounts (Panel B). Confidence intervals correspond to a confidence level of 95%. The time interval includes data from April 2022 to December 2023. The corresponding questions are: "By what percent do you expect your household spending on all goods and services to change during the next 12 months compared with your spending in the past 12 months?" for expectations about nominal consumption growth; "By about what percentage do you expect the total net income (that is after tax and compulsory deductions) of your household to change?" for expectations about nominal income growth; "In 12 months from now, what do you think will be the interest rate on mortgages in the country you currently live in?" for expectations for interest rates on mortgages, and "In 12 months from now, what do you think will be the interest rate on savings accounts in the country you currently live in?" for expectations for interest rates on savings accounts. Only responses to the last two questions were considered between the 5th and 95th percentiles for each country and month.

Sheet QC3.1
A5: Índice/Contents
A6: =+Índice!$A$5 -> Boletim Económico - março 2024 / Economic Bulletin - March 2024
A7: =+Índice!$A$43 -> Caixa 3 - Evolução dos empréstimos às empresas na sequência das medidas de apoio ao crédito na pandemia / Box 3 - Evolution of corporate loans following the credit support measures during the pandemic
A10: Quadro C3.1 • Características das empresas dos grupos analisados em 2019 | Valores médios
A11: Table C3.1 • Firm Characteristics by group in 2019 | Mean values
C13: Com garantia pública e com moratória | D13: Com garantia pública e sem moratória | E13: Sem garantia pública e com moratória | F13: Sem garantia pública e sem moratória
C14: With public guarantees and with moratorium | D14: With public guarantees and without moratorium | E14: Without public guarantees and with moratorium | F14: Without public guarantees and without moratorium
F15: Totais | G15: Elegíveis
F16: Total | G16: Eligible
A18: Ativo (1000 euros) | B18: Total assets (1000 euros) | C18: 1875.6 | D18: 934.5 | E18: 1209.6 | F18: 917.3 | G18: 822.9
A19: Turnover (1000 euros) | B19: Turnover (1000 euros) | C19: 1673.9 | D19: 1066.7 | E19: 708.1 | F19: 683 | G19: 627.9
A20: Número de empregados | B20: Number of workers | C20: 16.6 | D20: 10.5 | E20: 7.5 | F20: 6.4 | G20: 6.8
A21: Dívida (1000 euros) | B21: Total Debt (1000 euros) | C21: 636 | D21: 193.6 | E21: 434.6 | F21: 203.5 | G21: 176.1
A22: Empresa exportadora | B22: Exporting firms | C22: 0.651 | D22: 0.444 | E22: 0.337 | F22: 0.292 | G22: 0.292
A23: Idade | B23: Age | C23: 16.7 | D23: 15.2 | E23: 13.3 | F23: 14 | G23: 13.7
A24: EBIT/Ativo (%) | B24: EBIT/Assets (%) | C24: 4.5 | D24: 6.8 | E24: 3 | F24: 5.1 | G24: 5.5
A25: Dívida/Ativo (%) | B25: Debt/Assets (%) | C25: 33.9 | D25: 20.7 | E25: 35.9 | F25: 22.2 | G25: 21.4
A26: Número de empresas | B26: Number of firms | C26: 24200 | D26: 30805 | E26: 34123 | F26: 132229 | G26: 123 697
A28: Fontes: Banco de Portugal. | Notas: Dados da Central de Balanços. Distinguem-se quatro grupos de empresas: (i) empresas com crédito com garantia pública e que beneficiaram das moratórias, (ii) empresas com crédito com garantia pública e que não beneficiaram das moratórias, (iii) empresas sem crédito com garantia pública e que beneficiaram das moratórias e (iv) empresas sem crédito com garantia pública e que não beneficiaram das moratórias. O útimo grupo inclui o sub-conjunto das empresas sem garantia pública e sem moratória, mas que eram elegíveis para ambas as medidas. EBIT/Ativo e Dívida/Ativo são calculados como média ponderada.
A29: Sources: Banco de Portugal. | Notes: Central Balance Sheet Database. Firms are classified into four groups: (i) firms benefited from public guarantee programs as well as from the moratoriums, (ii) firms benefited from public guarantee programs but did not benefit from the moratoriums, (iii) firms that did not benefit from public guarantee programs but benefited from the moratoriums and (iv) firms that benefited neither from public guarantee programs nor from the moratoriums. The last group includes the subset of firms that benefited neither from public guarantee programs nor from the moratoriums, but were eligible for both measures. EBIT/Assets and Debt/Assets are calculated as the weighted average.

Sheet GC3.1
A5: Índice/Contents
A6: =+Índice!$A$5 -> Boletim Económico - março 2024 / Economic Bulletin - March 2024
A7: =+Índice!$A$43 -> Caixa 3 - Evolução dos empréstimos às empresas na sequência das medidas de apoio ao crédito na pandemia / Box 3 - Evolution of corporate loans following the credit support measures during the pandemic
A10: Gráfico C3.1 • Empréstimos a sociedades não financeiras – Decomposição dos fluxos líquidos mensais | Soma dos últimos três meses, milhões de euros
A11: Chart C3.1 • Loans to non-financial corporations – Breakdown of monthly net flows | Sum of the last three months, millions of euros
B14: Novos empréstimos | C14: Reembolsos previstos no contrato | D14: Fluxo líquido | E14: Reembolsos antecipados parciais | F14: Reembolsos antecipados totais
B15: New Loans | C15: Repayments under contract | D15: Net Flow | E15: Partial early repayments | F15: Full early repayments
A17: 43525 | B17: 5725.7165 | C17: -4747.2446 | D17: -19.606351 | E17: -290.57384 | F17: -707.50439
A18: 43556 | B18: 5627.2253 | C18: -4548.123 | D18: -95.255829 | E18: -331.3966 | F18: -842.96153
A19: 43586 | B19: 6014.4732 | C19: -4485.5186 | D19: 254.76406 | E19: -358.19082 | F19: -915.99977
A20: 43617 | B20: 6101.4582 | C20: -4705.4803 | D20: -55.558738 | E20: -514.80742 | F20: -936.72916
A21: 43647 | B21: 6359.5898 | C21: -5069.7186 | D21: -196.66781 | E21: -577.70466 | F21: -908.8344
A22: 43678 | B22: 5901.4222 | C22: -5320.3134 | D22: -761.89092 | E22: -569.48922 | F22: -773.51047
A23: 43709 | B23: 5746.793 | C23: -5567.5066 | D23: -1052.0436 | E23: -432.0226 | F23: -799.30731
A24: 43739 | B24: 5801.5825 | C24: -5474.8646 | D24: -788.52067 | E24: -360.24524 | F24: -754.99332
A25: 43770 | B25: 5992.7449 | C25: -5701.6843 | D25: -1384.5787 | E25: -443.93759 | F25: -1231.7017
A26: 43800 | B26: 6901.7264 | C26: -5877.8614 | D26: -1049.6462 | E26: -743.4986 | F26: -1330.0126
A27: 43831 | B27: 6520.9242 | C27: -5967.2313 | D27: -1505.3859 | E27: -756.88876 | F27: -1302.19
A28: 43862 | B28: 6356.855 | C28: -5701.8968 | D28: -1178.5811 | E28: -718.51604 | F28: -1115.0234
... A73: 45231 | B73: 4519.5116 | C73: -4632.2725 | D73: -2102.2099 | E73: -484.30074 | F73: -1505.1483
A75: Fontes: Banco de Portugal. | Notas: O fluxo líquido corresponde à diferença entre novos empréstimos e reembolsos totais. Os empréstimos excluem descobertos, cartões de crédito, ultrapassagens de crédito, crédito renovável, factoring e confirming.
A76: Sources: Banco de Portugal. | Notes: Net flow corresponds to the difference between new loans and total repayments. Overdrafts, credit cards, credit overruns, revolving credit, factoring and confirming are excluded from the analyses.

Sheet GC3.2
A5: Índice/Contents
A6: =+Índice!$A$5 -> Boletim Económico - março 2024 / Economic Bulletin - March 2024
A7: =+Índice!$A$43 -> Caixa 3 - Evolução dos empréstimos às empresas na sequência das medidas de apoio ao crédito na pandemia / Box 3 - Evolution of corporate loans following the credit support measures during the pandemic
A10: Gráfico C3.2 • Decomposição dos fluxos líquidos mensais dos empréstimos| Soma dos últimos três meses, em milhões de euros
A11: Chart C3.2 • Breakdown of monthly net loan flows | Sum of the last three months, in millions of euros
B14: Painel A - Empresas com crédito com garantia pública e com moratória | I14: Painel B - Empresas com crédito com garantia pública e sem moratória | O14: Painel C - Empresas sem crédito com garantia pública e com moratória | V14: Painel D - Empresas sem crédito com garantia pública e sem moratória
B15: Panel A - Firms with public guarantees and with moratorium | I15: Panel B - Firms with public guarantees and without moratorium | O15: Panel C - Firms without public guarantees and with moratorium | V15: Panel D - Firms without public guarantees and without moratorium
B16: Novos empréstimos | C16: Reembolsos previstos no contrato | D16: Fluxo líquido | E16: Reembolsos antecipados parciais | F16: Reembolsos antecipados totais | G16: Reembolsos previstos no contrato (empréstimos com moratória) | I16: Novos empréstimos | J16: Reembolsos previstos no contrato | K16: Fluxo líquido | L16: Reembolsos antecipados parciais | M16: Reembolsos antecipados totais | O16: Novos empréstimos | P16: Reembolsos previstos no contrato | Q16: Fluxo líquido | R16: Reembolsos antecipados parciais | S16: Reembolsos antecipados totais | T16: Reembolsos previstos no contrato (empréstimos com moratória) | V16: Novos empréstimos | W16: Reembolsos previstos no contrato | X16: Fluxo líquido | Y16: Reembolsos antecipados parciais | Z16: Reembolsos antecipados totais
B17: New Loans | C17: Repayments under contract | D17: Net Flow | E17: Partial early repayments | F17: Full early repayments | G17: Repayments under contract: Firms with moratorium | I17: New Loans | J17: Repayments under contract | K17: Net Flow | L17: Partial early repayments | M17: Full early repayments | O17: New Loans | P17: Repayments under contract | Q17: Net Flow | R17: Partial early repayments | S17: Full early repayments | T17: Repayments under contract: Firms with moratorium | V17: New Loans | W17: Repayments under contract | X17: Net Flow | Y17: Partial early repayments | Z17: Full early repayments
A19: 43525 | B19: 2009.5813 | C19: -1560.7518 | D19: 299.46593 | E19: -57.744712 | F19: -91.618882 | G19: -393.72808 | I19: 568.84577 | J19: -518.22588 | K19: -21.29771 | L19: -22.309794 | M19: -49.607812 | O19: 1581.5164 | P19: -1077.3794 | Q19: 307.58279 | R19: -60.953371 | S19: -135.60087 | T19: -360.76476 | V19: 1565.773 | W19: -1590.8875 | X19: -605.35736 | Y19: -149.56596 | Z19: -430.67682
A20: 43556 | B20: 1983.7361 | C20: -1550.0284 | D20: 226.32327 | E20: -53.290914 | F20: -154.09355 | G20: -408.33083 | I20: 581.9183 | J20: -503.27083 | K20: -16.924046 | L20: -23.92451 | M20: -71.647013 | O20: 1583.0271 | P20: -1005.1791 | Q20: 368.61303 | R20: -54.339116 | S20: -154.89587 | T20: -361.77635 | V20: 1478.5438 | W20: -1489.6448 | X20: -673.26808 | Y20: -199.84206 | Z20: -462.3251
A21: 43586 | B21: 2154.2276 | C21: -1560.4199 | D21: 329.9869 | E21: -63.592639 | F21: -200.22814 | G21: -417.89187 | I21: 613.93367 | J21: -499.92048 | K21: -8.8276606 | L21: -23.650525 | M21: -99.190326 | O21: 1570.5862 | P21: -995.65244 | Q21: 372.50805 | R21: -63.080209 | S21: -139.34553 | T21: -382.61567 | V21: 1675.7258 | W21: -1429.5257 | X21: -438.90322 | Y21: -207.86745 | Z21: -477.23578
A22: 43617 | B22: 2123.4164 | C22: -1566.449 | D22: 292.78076 | E22: -54.879493 | F22: -209.30711 | G22: -419.11786 | I22: 600.9491 | J22: -496.68396 | K22: -10.061168 | L22: -25.805662 | M22: -88.520649 | O22: 1521.8721 | P22: -987.62587 | Q22: 276.79068 | R22: -80.805674 | S22: -176.64993 | T22: -386.2944 | V22: 1855.2205 | W22: -1654.7215 | X22: -615.06901 | Y22: -353.31659 | Z22: -462.25148
A23: 43647 | B23: 2269.4981 | C23: -1622.6034 | D23: 385.02783 | E23: -94.215417 | F23: -167.65139 | G23: -450.8206 | I23: 603.46314 | J23: -505.89606 | K23: 4.7237508 | L23: -21.237102 | M23: -71.606233 | O23: 1587.0402 | P23: -1162.5426 | Q23: 114.61542 | R23: -124.65327 | S23: -185.22887 | T23: -446.00758 | V23: 1899.5884 | W23: -1778.6765 | X23: -701.03482 | Y23: -337.59887 | Z23: -484.34791
A24: 43678 | B24: 2098.0514 | C24: -1623.0872 | D24: 236.03728 | E24: -96.3227 | F24: -142.60428 | G24: -449.71427 | I24: 547.6666 | J24: -498.52493 | K24: -19.155765 | L24: -21.223274 | M24: -47.074161 | O24: 1626.1899 | P24: -1259.3356 | Q24: 75.024757 | R24: -127.40978 | S24: -164.41973 | T24: -485.24583 | V24: 1629.5143 | W24: -1939.3657 | X24: -1053.7972 | Y24: -324.53346 | Z24: -419.4123
A25: 43709 | B25: 2150.0724 | C25: -1790.518 | D25: 103.36577 | E25: -111.00477 | F25: -145.18387 | G25: -540.99276 | I25: 518.30586 | J25: -621.51083 | K25: -161.46704 | L25: -20.152557 | M25: -38.109514 | O25: 1673.8056 | P25: -1354.1789 | Q25: 40.649547 | R25: -139.25071 | S25: -139.72646 | T25: -520.57452 | V25: 1404.6091 | W25: -1801.2989 | X25: -1034.5918 | Y25: -161.61456 | Z25: -476.28745
A26: 43739 | B26: 2140.1566 | C26: -1807.7736 | D26: 84.03682 | E26: -92.819938 | F26: -155.52623 | G26: -513.48533 | I26: 522.39839 | J26: -633.25749 | K26: -169.655 | L26: -20.855426 | M26: -37.940478 | O26: 1641.7113 | P26: -1380.0681 | Q26: 14.460439 | R26: -104.05687 | S26: -143.12593 | T26: -455.02004 | V26: 1497.3162 | W26: -1653.7654 | X26: -717.36293 | Y26: -142.513 | Z26: -418.40068
A27: 43770 | B27: 2197.4378 | C27: -1867.2852 | D27: 107.8419 | E27: -89.735419 | F27: -132.57534 | G27: -521.20519 | I27: 598.29755 | J27: -640.51637 | K27: -103.1375 | L27: -22.726776 | M27: -38.191904 | O27: 1463.1402 | P27: -1317.2665 | Q27: -197.52747 | R27: -157.89788 | S27: -185.50326 | T27: -400.19855 | V27: 1733.8693 | W27: -1876.6162 | X27: -1191.7556 | Y27: -173.57751 | Z27: -875.43115
A28: 43800 | B28: 2375.67 | C28: -1794.4002 | D28: 331.21441 | E28: -96.563327 | F28: -153.49209 | G28: -466.15698 | I28: 667.76137 | J28: -543.24159 | K28: 42.372207 | L28: -24.745129 | M28: -57.402452 | O28: 1735.5915 | P28: -1225.5526 | Q28: -37.4303 | R28: -265.77905 | S28: -281.69019 | T28: -390.28133 | V28: 2122.7035 | W28: -2314.6671 | X28: -1385.8025 | Y28: -356.41109 | Z28: -837.42786
A29: 43831 | B29: 2321.8082 | C29: -1777.3056 | D29: 323.34904 | E29: -78.149631 | F29: -143.0039 | G29: -484.13406 | I29: 672.55158 | J29: -540.19708 | K29: 45.930312 | L29: -26.683309 | M29: -59.740883 | O29: 1588.1665 | P29: -1191.8393 | Q29: -156.54234 | R29: -289.66131 | S29: -263.2083 | T29: -400.96864 | V29: 1938.398 | W29: -2457.8894 | X29: -1718.1229 | Y29: -362.39451 | Z29: -836.23695
A30: 43862 | B30: 2337.5019 | C30: -1763.885 | D30: 369.11663 | E30: -66.766013 | F30: -137.73429 | G30: -493.68329 | I30: 699.12198 | J30: -556.58329 | K30: 58.11644 | L30: -21.043366 | M30: -63.378881 | O30: 1629.7777 | P30: -1288.4204 | Q30: -182.27642 | R30: -281.29577 | S30: -242.33794 | T30: -441.75267 | V30: 1690.4534 | W30: -2093.0081 | X30: -1423.5378 | Y30: -349.41089 | Z30: -671.57226
... A75: 45231 | B75: 1357.3687 | C75: -1859.7913 | D75: -895.76048 | E75: -110.86231 | F75: -282.47555 | G75: -389.50692 | I75: 629.51481 | J75: -772.33729 | K75: -349.05942 | L75: -31.379997 | M75: -174.85695 | O75: 709.96163 | P75: -981.3403 | Q75: -572.98884 | R75: -77.206953 | S75: -224.40322 | T75: -331.31792 | V75: 1822.6665 | W75: -1018.8036 | X75: -284.40118 | Y75: -264.85148 | Z75: -823.41261
A77: Fontes: Banco de Portugal. | Notas: Distinguem-se quatro grupos de empresas: (i) empresas com crédito com garantia pública e que beneficiaram das moratórias, (ii) empresas com crédito com garantia pública e que não beneficiaram das moratórias, (iii) empresas sem crédito com garantia pública e que beneficiaram das moratórias e (iv) empresas sem crédito com garantia pública e que não beneficiaram das moratórias. O fluxo líquido corresponde à diferença entre novos empréstimos e reembolsos totais. Os empréstimos excluem descobertos, cartões de crédito, ultrapassagens de crédito, crédito renovável, factoring e confirming.
A78: Sources: Banco de Portugal. | Notes: Firms are classified into four groups: (i) firms benefited from public guarantee programs as well as from the moratoriums, (ii) firms benefited from public guarantee programs but did not benefit from the moratoriums, (iii) firms that did not benefit from public guarantee programs but benefited from the moratoriums and (iv) firms that benefited neither from public guarantee programs nor from the moratoriums. The last group includes the subset of firms that benefited neither from public guarantee programs nor from the moratoriums, but were eligible for both measures. Net flow corresponds to the difference between new loans and total repayments. Overdrafts, credit cards, credit overruns, revolving credit, factoring and confirming are excluded from the analyses.

Sheet GC3.3
A5: Índice/Contents
A6: =+Índice!$A$5 -> Boletim Económico - março 2024 / Economic Bulletin - March 2024
A7: =+Índice!$A$43 -> Caixa 3 - Evolução dos empréstimos às empresas na sequência das medidas de apoio ao crédito na pandemia / Box 3 - Evolution of corporate loans following the credit support measures during the pandemic
A10: Gráfico C3.3 • Decomposição dos fluxos líquidos mensais dos empréstimos: Empresas elegíveis sem crédito com garantia pública e sem moratória | Soma dos últimos três meses, em milhões de euros
A11: Chart C3.3 • Breakdown of monthly net loan flows: Eligible firms without public guaranteed credit and without moratorium | Sum of the last three months, in millions of euros
B14: Novos empréstimos | C14: Reembolsos previstos no contrato | D14: Fluxo líquido | E14: Reembolsos antecipados parciais | F14: Reembolsos antecipados totais
B15: New Loans | C15: Repayments under contract | D15: Net Flow | E15: Partial early repayments | F15: Full early repayments
A17: 43525 | B17: 1405.5209 | C17: -1096.2464 | D17: -16.757237 | E17: -72.98162 | F17: -253.05003
A18: 43556 | B18: 1242.8618 | C18: -1044.9395 | D18: -232.60054 | E18: -127.30469 | F18: -303.21817
A19: 43586 | B19: 1329.6362 | C19: -1080.6896 | D19: -205.62553 | E19: -134.52418 | F19: -320.04794
A20: 43617 | B20: 1368.82 | C20: -1304.0919 | D20: -413.0457 | E20: -157.23799 | F20: -320.53587
A21: 43647 | B21: 1490.3624 | C21: -1443.3695 | D21: -406.63042 | E21: -139.38452 | F21: -314.23881
A22: 43678 | B22: 1337.815 | C22: -1467.9596 | D22: -526.52018 | E22: -122.36728 | F22: -274.00828
A23: 43709 | B23: 1260.1865 | C23: -1407.6087 | D23: -457.01454 | E23: -99.821128 | F23: -209.77127
A24: 43739 | B24: 1349.9968 | C24: -1234.2778 | D24: -152.92905 | E24: -75.588329 | F24: -193.05974
A25: 43770 | B25: 1590.9765 | C25: -1433.8798 | D25: -419.02907 | E25: -108.52184 | F25: -467.60399
A26: 43800 | B26: 1946.4229 | C26: -1424.2489 | D26: -153.1162 | E26: -142.59772 | F26: -532.69247
A27: 43831 | B27: 1733.9998 | C27: -1556.5629 | D27: -491.9863 | E27: -154.10957 | F27: -515.31357
A28: 43862 | B28: 1474.8561 | C28: -1353.1992 | D28: -370.22574 | E28: -133.10985 | F28: -358.77277
... A73: 45231 | B73: 1705.377 | C73: -1161.1247 | D73: -112.81149 | E73: -259.33301 | F73: -397.73079
A75: Fontes: Banco de Portugal. | Notas: O fluxo líquido corresponde à diferença entre novos empréstimos e reembolsos totais. Os empréstimos excluem descobertos, cartões de crédito, ultrapassagens de crédito, crédito renovável, factoring e confirming.
A76: Sources: Banco de Portugal. | Notes: Net flow corresponds to the difference between new loans and total repayments. Overdrafts, credit cards, credit overruns, revolving credit, factoring and confirming are excluded from the analyses.

Sheet GC3.4
A5: Índice/Contents
A6: =+Índice!$A$5 -> Boletim Económico - março 2024 / Economic Bulletin - March 2024
A7: =+Índice!$A$43 -> Caixa 3 - Evolução dos empréstimos às empresas na sequência das medidas de apoio ao crédito na pandemia / Box 3 - Evolution of corporate loans following the credit support measures during the pandemic
A10: Gráfico C3.4 • Empréstimos a sociedades não financeiras – Decomposição dos fluxos líquidos mensais | Soma dos últimos três meses, milhões de euros
A11: Chart C3.4 • Loans to non-financial corporations – Breakdown of monthly net flows | Sum of the last three months, millions of euros
B14: Empresas com crédito com garantia pública e com moratória | C14: Empresas com crédito com garantia pública e sem moratória | D14: Empresas sem crédito com garantia pública e com moratória | E14: Empresas sem crédito com garantia pública e sem moratória | F14: Fluxo líquido
B15: Firms with public guarantees and with moratorium | C15: Firms with public guarantees and without moratorium | D15: Firms without public guarantees and with moratorium | E15: Firms without public guarantees and without moratorium | F15: Net Flow
A17: 43525 | B17: 299.46593 | C17: -21.29771 | D17: 307.58279 | E17: -605.35736 | F17: -19.606351
A18: 43556 | B18: 226.32327 | C18: -16.924046 | D18: 368.61303 | E18: -673.26808 | F18: -95.255829
A19: 43586 | B19: 329.9869 | C19: -8.8276606 | D19: 372.50805 | E19: -438.90322 | F19: 254.76406
A20: 43617 | B20: 292.78076 | C20: -10.061168 | D20: 276.79068 | E20: -615.06901 | F20: -55.558738
A21: 43647 | B21: 385.02783 | C21: 4.7237508 | D21: 114.61542 | E21: -701.03482 | F21: -196.66781
A22: 43678 | B22: 236.03728 | C22: -19.155765 | D22: 75.024757 | E22: -1053.7972 | F22: -761.89092
A23: 43709 | B23: 103.36577 | C23: -161.46704 | D23: 40.649547 | E23: -1034.5918 | F23: -1052.0436
A24: 43739 | B24: 84.03682 | C24: -169.655 | D24: 14.460439 | E24: -717.36293 | F24: -788.52067
A25: 43770 | B25: 107.8419 | C25: -103.1375 | D25: -197.52747 | E25: -1191.7556 | F25: -1384.5787
A26: 43800 | B26: 331.21441 | C26: 42.372207 | D26: -37.4303 | E26: -1385.8025 | F26: -1049.6462
A27: 43831 | B27: 323.34904 | C27: 45.930312 | D27: -156.54234 | E27: -1718.1229 | F27: -1505.3859
A28: 43862 | B28: 369.11663 | C28: 58.11644 | D28: -182.27642 | E28: -1423.5378 | F28: -1178.5811
... A73: 45231 | B73: -895.76048 | C73: -349.05942 | D73: -572.98884 | E73: -284.40118 | F73: -2102.2099
A75: Fontes: Banco de Portugal. | Notas: Distinguem-se quatro grupos de empresas: (i) empresas com crédito com garantia pública e que beneficiaram das moratórias, (ii) empresas com crédito com garantia pública e que não beneficiaram das moratórias, (iii) empresas sem crédito com garantia pública e que beneficiaram das moratórias e (iv) empresas sem crédito com garantia pública e que não beneficiaram das moratórias. O fluxo líquido corresponde à diferença entre novos empréstimos e reembolsos totais. Os empréstimos excluem descobertos, cartões de crédito, ultrapassagens de crédito, crédito renovável, factoring e confirming.
A76: Sources: Banco de Portugal. | Notes: Firms are classified into four groups: (i) firms benefited from public guarantee programs as well as from the moratoriums, (ii) firms benefited from public guarantee programs but did not benefit from the moratoriums, (iii) firms that did not benefit from public guarantee programs but benefited from the moratoriums and (iv) firms that benefited neither from public guarantee programs nor from the moratoriums. The last group includes the subset of firms that benefited neither from public guarantee programs nor from the moratoriums, but were eligible for both measures. Net flow corresponds to the difference between new loans and total repayments. Overdrafts, credit cards, credit overruns, revolving credit, factoring and confirming are excluded from the analyses.

Sheet GC4.1
A5: Índice/Contents
A6: =+Índice!$A$5 -> Boletim Económico - março 2024 / Economic Bulletin - March 2024
A7: =+Índice!$A$55 -> Caixa 4 - Impacto da política monetária sobre o mercado residencial em Portugal / Box 4 - Monetary policy impact on the portuguese residential market
A10: Gráfico C4.1 • Impacto de um choque de política monetária no índice de preços da habitação e no número total de transações | Percentagem
A11: Chart C4.1 • Impact of a monetary policy shock on the housing price index and total number of transactions | Percentage
A14: Painel A: IPHab
A15: Panel A: Housing Price Index
A17: Trimestres após o choque | B17: Coeficiente | C17: Limite inferior do intervalo de confiança | D17: Limite superior do intervalo de confiança
A18: Quarters after shock | B18: Coefficient | C18: Lower bound of the confidence interval | D18: Upper bound of the confidence interval
A19: 0 | B19: -0.051219721 | C19: -0.41611942 | D19: 0.31367998
A20: 1 | B20: -0.14957244 | C20: -0.59660633 | D20: 0.29746144
A21: 2 | B21: -0.22307153 | C21: -0.80112569 | D21: 0.35498263
A22: 3 | B22: -0.51781706 | C22: -0.98339559 | D22: -0.052238532
A23: 4 | B23: -0.77795537 | C23: -1.4542343 | D23: -0.10167644
A24: 5 | B24: -0.80965442 | C24: -1.6233448 | D24: 0.0040359336
A25: 6 | B25: -0.61092879 | C25: -1.3988781 | D25: 0.17702051
A26: 7 | B26: -0.6392315 | C26: -1.445238 | D26: 0.16677502
A27: 8 | B27: -0.81880224 | C27: -1.7828917 | D27: 0.14528727
A30: Painel B: Número de transações
A31: Panel B: Number of transactions
A33: Trimestres após o choque | B33: Coeficiente | C33: Limite inferior do intervalo de confiança | D33: Limite superior do intervalo de confiança
A34: Quarters after shock | B34: Coefficient | C34: Lower bound of the confidence interval | D34: Upper bound of the confidence interval
A35: 0 | B35: -1.3555253 | C35: -3.0056369 | D35: 0.29458631
A36: 1 | B36: -4.7527208 | C36: -8.2795725 | D36: -1.225869
A37: 2 | B37: -2.9723987 | C37: -5.8245974 | D37: -0.12020005
A38: 3 | B38: -3.3286889 | C38: -6.246316 | D38: -0.41106172
A39: 4 | B39: -3.9512524 | C39: -6.3610379 | D39: -1.5414669
A40: 5 | B40: -2.6579639 | C40: -6.4106554 | D40: 1.0947276
A41: 6 | B41: -2.0705762 | C41: -5.2619225 | D41: 1.1207702
A42: 7 | B42: -1.2126888 | C42: -3.845043 | D42: 1.4196654
A43: 8 | B43: -1.9900031 | C43: -5.7332552 | D43: 1.7532491
A46: Fontes: Cálculos do Banco de Portugal. | Notas: O choque simulado é de um desvio-padrão, a que corresponde um aumento de 17 pontos base nas taxas de juro sem risco a 1 ano. A linha a tracejado apresenta o intervalo de confiança de 90%. O cálculo dos intervalos de confiança foi feito com erros padrão robustos a heterocedasticidade.
A47: Sources: Banco de Portugal calculations. | Notes: The simulated shock is one standard deviation, which corresponds to an increase of 17 basis points in 1-year risk-free interest rates. The dashed line shows the 90% confidence interval. The confidence intervals were calculated using standard errors robust to heteroscedasticity.

Sheet GC4.2
A5: Índice/Contents
A6: =+Índice!$A$5 -> Boletim Económico - março 2024 / Economic Bulletin - March 2024
A7: =+Índice!$A$55 -> Caixa 4 - Impacto da política monetária sobre o mercado residencial em Portugal / Box 4 - Monetary policy impact on the portuguese residential market
A10: Gráfico C4.2 • Impacto de um choque de política monetária no índice de preços da habitação e no número total de transações de habitações novas e habitações existentes | Percentagem
A11: Chart C4.2 • Impact of a monetary policy shock on the housing price index and total number of transactions of new and existing houses | Percentage
A14: Painel A: IPHab - novas
A15: Panel A: Housing Price Index - new
A17: Trimestres após o choque | B17: Coeficiente | C17: Limite inferior do intervalo de confiança | D17: Limite superior do intervalo de confiança
A18: Quarters after shock | B18: Coefficient | C18: Lower bound of the confidence interval | D18: Upper bound of the confidence interval
A19: 0 | B19: -0.11753668 | C19: -0.59514781 | D19: 0.36007444
A20: 1 | B20: -0.38480555 | C20: -0.96261509 | D20: 0.193004
A21: 2 | B21: -0.36841912 | C21: -1.0604241 | D21: 0.32358589
A22: 3 | B22: -0.63241098 | C22: -1.1840236 | D22: -0.08079838
A23: 4 | B23: -0.9128431 | C23: -1.5157106 | D23: -0.3099756
A24: 5 | B24: -0.87597049 | C24: -1.4818231 | D24: -0.27011787
A25: 6 | B25: -0.72921347 | C25: -1.355504 | D25: -0.10292298
A26: 7 | B26: -0.62349674 | C26: -1.1377026 | D26: -0.10929084
A27: 8 | B27: -0.28059778 | C27: -0.81849527 | D27: 0.25729972
A30: Painel B: IPHab - existing
A31: Panel B: Housing Price Index - existing
A33: Trimestres após o choque | B33: Coeficiente | C33: Limite inferior do intervalo de confiança | D33: Limite superior do intervalo de confiança
A34: Quarters after shock | B34: Coefficient | C34: Lower bound of the confidence interval | D34: Upper bound of the confidence interval
A35: 0 | B35: -0.052997364 | C35: -0.44615591 | D35: 0.34016118
A36: 1 | B36: -0.071620395 | C36: -0.47531947 | D36: 0.33207868
A37: 2 | B37: -0.20622304 | C37: -0.76716364 | D37: 0.35471756
A38: 3 | B38: -0.47357022 | C38: -1.0101835 | D38: 0.063043025
A39: 4 | B39: -0.67227602 | C39: -1.3695615 | D39: 0.025009438
A40: 5 | B40: -0.65014993 | C40: -1.5420284 | D40: 0.24172852
A41: 6 | B41: -0.43737113 | C41: -1.2807924 | D41: 0.40605011
A42: 7 | B42: -0.60042361 | C42: -1.5738732 | D42: 0.37302601
A43: 8 | B43: -1.0123756 | C43: -2.2383492 | D43: 0.21359795
A46: Painel C: Nº de transações - novas
A47: Panel C: Number of transactions - new
A49: Trimestres após o choque | B49: Coeficiente | C49: Limite inferior do intervalo de confiança | D49: Limite superior do intervalo de confiança
A50: Quarters after shock | B50: Coefficient | C50: Lower bound of the confidence interval | D50: Upper bound of the confidence interval
A51: 0 | B51: -1.6779651 | C51: -3.9616588 | D51: 0.6057286
A52: 1 | B52: -4.3248809 | C52: -7.3457799 | D52: -1.3039818
A53: 2 | B53: -1.2336901 | C53: -4.3588777 | D53: 1.8914974
A54: 3 | B54: -2.9823714 | C54: -5.9932449 | D54: 0.028502048
A55: 4 | B55: -2.102765 | C55: -4.4288061 | D55: 0.22327608
A56: 5 | B56: 0.052582289 | C56: -3.5451232 | D56: 3.6502878
A57: 6 | B57: 0.68064929 | C57: -2.6705224 | D57: 4.0318209
A58: 7 | B58: 1.1533626 | C58: -1.1994593 | D58: 3.5061846
A59: 8 | B59: 0.89416824 | C59: -1.8071587 | D59: 3.5954951
A62: Painel D: Nº de transações - existentes
A63: Panel D: Number of transactions - existing
A65: Trimestres após o choque | B65: Coeficiente | C65: Limite inferior do intervalo de confiança | D65: Limite superior do intervalo de confiança
A66: Quarters after shock | B66: Coefficient | C66: Lower bound of the confidence interval | D66: Upper bound of the confidence interval
A67: 0 | B67: -1.0523737 | C67: -2.7790178 | D67: 0.67427046
A68: 1 | B68: -4.6392257 | C68: -8.5925314 | D68: -0.68591997
A69: 2 | B69: -3.4588038 | C69: -6.7585641 | D69: -0.15904356
A70: 3 | B70: -3.2041109 | C70: -6.2983572 | D70: -0.10986469
A71: 4 | B71: -3.9728585 | C71: -6.5633791 | D71: -1.3823379
A72: 5 | B72: -3.2629851 | C72: -7.151327 | D72: 0.62535679
A73: 6 | B73: -2.8625051 | C73: -6.1946436 | D73: 0.46963341
A74: 7 | B74: -1.9320922 | C74: -4.6599877 | D74: 0.79580325
A75: 8 | B75: -2.6690768 | C75: -6.7694324 | D75: 1.4312789
A78: Fontes: Cálculos do Banco de Portugal. | Notas: O choque simulado é de um desvio-padrão, a que corresponde um aumento de 17 pontos base nas taxas de juro sem risco a 1 ano. A linha a tracejado apresenta o intervalo de confiança de 90%. O cálculo dos intervalos de confiança foi feito com erros padrão robustos a heterocedasticidade.
A79: Sources: Banco de Portugal calculations. | Notes: The simulated shock is one standard deviation, which corresponds to an increase of 17 basis points in 1-year risk-free interest rates. The dashed line shows the 90% confidence interval. The confidence intervals were calculated using standard errors robust to heteroscedasticity.

Sheet TED.G1
A5: Índice/Contents
A6: =+Índice!$A$5 -> Boletim Económico - março 2024 / Economic Bulletin - March 2024
A7: =Índice!$A$61 -> Parte II. Tema em Destaque: Bem-estar e PIB per capita em Portugal face à EU / Part II. Special issue: Welfare and GDP per capita in Portugal compared to the EU
A10: Gráfico 1 • Consumo, lazer, esperança de vida e desigualdade em 2022
A11: Chart 1 • Consumption, leisure, life expectancy and inequality in 2022
A14: Unidade/Unit | D14: % da UE/ % of EU (PPS) | E14: % da UE/ % of EU (PPS) | F14: % | G14: Anos/ Years | H14: Desvio-padrão/ Standard deviation
D16: PIB per capita | E16: Consumo per capita | F16: Tempo de lazer per capita | G16: Esperança média de vida à nascença | H16: Desigualdade do consumo
D17: GDP per capita | E17: Consumption per capita | F17: Leisure time per capita | G17: Life expectancy at birth | H17: Consumption inequality
A18: UE | B18: União Europeia | C18: European Union | D18: 100 | E18: 100 | F18: 86.889151 | G18: 80.7 | H18: 0.51008101
A19: BE | B19: Bélgica | C19: Belgium | D19: 119.59785 | E19: 121.20335 | F19: 88.305168 | G19: 81.8 | H19: 0.41867255
A20: BG | B20: Bulgária | C20: Bulgaria | D20: 62.121221 | E20: 64.583808 | F20: 85.234827 | G20: 74.3 | H20: 0.67531273
A21: CZ | B21: Chéquia | C21: Czechia | D21: 90.416376 | E21: 82.247185 | F21: 84.541234 | G21: 79.1 | H21: 0.42159036
A22: DK | B22: Dinamarca | C22: Denmark | D22: 136.45849 | E22: 120.71533 | F22: 87.195614 | G22: 81.3 | H22: 0.46852973
A23: DE | B23: Alemanha | C23: Germany | D23: 116.67011 | E23: 115.87529 | F23: 87.45144 | G23: 80.7 | H23: 0.50645397
A24: EE | B24: Estónia | C24: Estonia | D24: 85.038688 | E24: 82.099185 | F24: 84.030651 | G24: 78.2 | H24: 0.5399382
A25: IE | B25: Irlanda | C25: Ireland | D25: 234.94685 | E25: 114.74768 | F25: 85.867636 | G25: 82.7 | H25: 0.47029971
A26: EL | B26: Grécia | C26: Greece | D26: 67.247116 | E26: 81.036217 | F26: 84.5354 | G26: 80.7 | H26: 0.54474602
A27: ES | B27: Espanha | C27: Spain | D27: 85.559459 | E27: 89.985562 | F27: 87.842245 | G27: 83.2 | H27: 0.55558679
A28: FR | B28: França | C28: France | D28: 100.14387 | E28: 105.45301 | F28: 88.713395 | G28: 82.3 | H28: 0.50704937
A29: HR | B29: Croácia | C29: Croatia | D29: 72.870692 | E29: 79.181044 | F29: 86.03331 | G29: 77.7 | H29: 0.49100484
... A45: SE | B45: Suécia | C45: Sweden | D45: 119.51267 | E45: 111.40036 | F45: 86.469978 | G45: 83.1 | H45: 0.48922605
A47: Fontes: Eurostat, Banco Mundial, UNU-WIDER e cálculos do Banco de Portugal. | Notas: Por questões de escala, o Luxemburgo e a Irlanda foram omitidos do gráfico. Consumo (privado e público) per capita, corrigido de paridades de poder de compra. O tempo de lazer per capita é calculado como a proporção do tempo disponível (acordado) gasta em lazer e tarefas domésticas. Especificamente, o número de horas ocupadas em lazer e tarefas domésticas é calculado subtraindo ao total de horas disponíveis por pessoa (16 horas por dia vezes 365 dias por ano) o total de horas trabalhadas per capita. A proporção do lazer per capita assume valores elevados porque se divide as horas trabalhadas pela população total (e não pelo número de trabalhadores). Desigualdade do consumo medida pelo desvio-padrão (um valor mais elevado corresponde a maior desigualdade). Para mais detalhes, consultar a Caixa 1.
A48: Sources: Eurostat, World Bank, UNU-WIDER and Banco de Portugal calculations. | Notes: Luxembourg and Ireland have been omitted from the chart due to scale considerations. Consumption (private and public) per capita, adjusted for purchasing power parities. Leisure time per capita is calculated as the proportion of available time (while awake) spent on leisure and home production. Specifically, the number of hours spent on leisure and home production is calculated by subtracting the total hours worked per capita from the total hours available per person (16 hours per day multiplied by 365 days per year). The leisure per capita is high because hours worked are divided by the total population (rather than by the number of workers). Consumption inequality measured by the standard deviation (a higher value corresponds to higher inequality). For more details, see Box 1.

Sheet TED.G2
A5: Índice/Contents
A6: =+Índice!$A$5 -> Boletim Económico - março 2024 / Economic Bulletin - March 2024
A7: =Índice!$A$61 -> Parte II. Tema em Destaque: Bem-estar e PIB per capita em Portugal face à EU / Part II. Special issue: Welfare and GDP per capita in Portugal compared to the EU
A10: Gráfico 2 • Índice de Bem-estar e contributos das quatro componentes em 2022 | Logaritmo do índice de bem-estar
A11: Chart 2 • Welfare index and contributions of the four components in 2022 | Logarithm of the welfare index
A14: Unidade/Unit | D14: Logaritmo/ Logarithm | F14: Pontos de logaritmo/ Log points | G14: Pontos de logaritmo/ Log points | H14: Pontos de logaritmo/ Log points | I14: Pontos de logaritmo/ Log points
F15: Decomposição/ Decomposition
D16: Índice de bem-estar | F16: Esperança média de vida | G16: Consumo | H16: Lazer | I16: Desigualdade
D17: Welfare index | F17: Life expectancy | G17: Consumption | H17: Leisure | I17: Inequality
A18: LU | B18: Luxemburgo | C18: Luxembourg | D18: 0.53664627 | F18: 0.15288749 | G18: 0.52022808 | H18: -0.13891504 | I18: 0.0024457398
A19: BE | B19: Bélgica | C19: Belgium | D19: 0.33106681 | F19: 0.071428254 | G19: 0.1922995 | H19: 0.024891086 | I19: 0.042447967
A20: NL | B20: Países Baixos | C20: Netherlands | D20: 0.26840834 | F20: 0.064247322 | G20: 0.18827495 | H20: -0.01361997 | I20: 0.029506043
A21: IE | B21: Irlanda | C21: Ireland | D21: 0.26418363 | F21: 0.12683873 | G21: 0.13756541 | H21: -0.019720923 | I21: 0.019500411
A22: SE | B22: Suécia | C22: Sweden | D22: 0.26187434 | F22: 0.15140714 | G22: 0.10796039 | H22: -0.0079134434 | I22: 0.010420255
A23: DK | B23: Dinamarca | C23: Denmark | D23: 0.25284743 | F23: 0.038623213 | G23: 0.18826491 | H23: 0.0056280383 | I23: 0.020331266
A24: AT | B24: Áustria | C24: Austria | D24: 0.22062038 | F24: 0.025653358 | G24: 0.19283641 | H24: -0.0096483673 | I24: 0.011778978
A25: FR | B25: França | C25: France | D25: 0.18663284 | F25: 0.10045649 | G25: 0.053095294 | H25: 0.03153927 | I25: 0.0015417882
A26: FI | B26: Finlândia | C26: Finland | D26: 0.18056515 | F26: 0.031780561 | G26: 0.12178672 | H26: -0.0027713446 | I26: 0.029769211
A27: DE | B27: Alemanha | C27: Germany | D27: 0.15941206 | F27: 0 | G27: 0.14734432 | H27: 0.010224233 | I27: 0.0018435052
A28: IT | B28: Itália | C28: Italy | D28: 0.15871978 | F28: 0.14241483 | G28: 0.03943734 | H28: 0.0055066661 | I28: -0.028639054
A29: ES | B29: Espanha | C29: Spain | D29: 0.038100639 | F29: 0.15080224 | G29: -0.10552096 | H29: 0.017066376 | I29: -0.024247022
... A44: BG | B44: Bulgária | C44: Bulgaria | D44: -0.9177785 | F44: -0.34996022 | G44: -0.43720645 | H44: -0.032679507 | I44: -0.097932322
A47: Fonte: Cálculos do Banco de Portugal. | Notas: Dados corrigidos de paridades de poder de compra (PPS). O índice de bem-estar (λ) é uma medida relativa face à UE: log⁡λ positivos (negativos) implicam um nível de vida superior (inferior) ao da UE. Para detalhes sobre a decomposição do log λ nos vários contributos consultar a Caixa 1, equação 4.
A48: Source: Banco de Portugal calculations. | Notes: Data adjusted for purchasing power parities (PPS). The welfare index (λ) is a relative measure compared to the EU: a positive (negative) logλ implies that the country's welfare is higher (lower) than that of the EU. For details on the decomposition of log λ into the various contributions see Box 1, equation 4.

Sheet TED.G3
A5: Índice/Contents
A6: =+Índice!$A$5 -> Boletim Económico - março 2024 / Economic Bulletin - March 2024
A7: =Índice!$A$61 -> Parte II. Tema em Destaque: Bem-estar e PIB per capita em Portugal face à EU / Part II. Special issue: Welfare and GDP per capita in Portugal compared to the EU
A10: Gráfico 3 • Índice de bem-estar e PIB per capita, em 2022 | Em percentagem da UE
A11: Chart 3 • Welfare index and GDP per capita in 2022 | Percentage of the EU
A14: Unidade/Unit | D14: % da UE/ % of EU | E14: % da UE/ % of EU
D16: Índice de bem-estar | E16: PIB per capita
D17: Welfare index | E17: GDP per capita
A18: UE | B18: União Europeia | C18: European Union | D18: 100 | E18: 100
A19: BE | B19: Bélgica | C19: Belgium | D19: 139.24528 | E19: 119.59785
A20: BG | B20: Bulgária | C20: Bulgaria | D20: 39.940534 | E20: 62.121221
A21: CZ | B21: Chéquia | C21: Czechia | D21: 74.34145 | E21: 90.416376
A22: DK | B22: Dinamarca | C22: Denmark | D22: 128.76868 | E22: 136.45849
A23: DE | B23: Alemanha | C23: Germany | D23: 117.28211 | E23: 116.67011
A24: EE | B24: Estónia | C24: Estonia | D24: 65.856225 | E24: 85.038688
A25: IE | B25: Irlanda | C25: Ireland | D25: 130.23673 | E25: 234.94685
A26: EL | B26: Grécia | C26: Greece | D26: 75.864648 | E26: 67.247116
A27: ES | B27: Espanha | C27: Spain | D27: 103.88358 | E27: 85.559459
A28: FR | B28: França | C28: France | D28: 120.51847 | E28: 100.14387
A29: HR | B29: Croácia | C29: Croatia | D29: 65.933348 | E29: 72.870692
... A45: SE | B45: Suécia | C45: Sweden | D45: 129.93633 | E45: 119.51267
A47: Fontes: Eurostat e cálculos do Banco de Portugal. | Notas: Dados corrigidos de paridades de poder de compra. Por questões de escala, o Luxemburgo e a Irlanda foram omitidos do gráfico (os valores estão disponíveis no Quadro 1).
A48: Sources: Eurostat and Banco de Portugal calculations. | Notes: Data adjusted for purchasing power parities. Luxembourg and Ireland have been omitted from the chart due to scale considerations (their figures are available in Table 1).

Sheet TED.G4
A5: Índice/Contents
A6: =+Índice!$A$5 -> Boletim Económico - março 2024 / Economic Bulletin - March 2024
A7: =Índice!$A$61 -> Parte II. Tema em Destaque: Bem-estar e PIB per capita em Portugal face à EU / Part II. Special issue: Welfare and GDP per capita in Portugal compared to the EU
A10: Gráfico 4 • Convergência beta absoluta na UE no período 1995-2022 | Índice de bem-estar: logaritmo e taxa de variação, dados encadeados em volume, em euros
A11: Chart 4 • Absolute beta convergence in the EU over the period 1995-2022 | Welfare index: logarithm and rate of change, chain-linked volume data, in euros
A14: Unidade/Unit | D14: Logaritmo/ Logarithm | E14: %
D16: Índice de bem-estar, em 1995 | E16: Índice de bem-estar - Taxa de variação média em 1995-2022
D17: Welfare index, in 1995 | E17: Welfare index - Average growth in 1995-2022
A18: UE | B18: União Europeia | C18: European Union | D18: 0 | E18: 2.3507833
A19: BE | B19: Bélgica | C19: Belgium | D19: 0.48782058 | E19: 2.1478175
A20: BG | B20: Bulgária | C20: Bulgaria | D20: -1.8042803 | E20: 2.9588174
A21: CZ | B21: Chéquia | C21: Czechia | D21: -0.94923327 | E21: 2.9736561
A22: DK | B22: Dinamarca | C22: Denmark | D22: 0.60650287 | E22: 2.2780723
A23: DE | B23: Alemanha | C23: Germany | D23: 0.39145155 | E23: 1.9451211
A24: EE | B24: Estónia | C24: Estonia | D24: -1.7503672 | E24: 6.2692879
A25: IE | B25: Irlanda | C25: Ireland | D25: -0.060457093 | E25: 4.1467676
A26: EL | B26: Grécia | C26: Greece | D26: -0.23099409 | E26: 1.6930566
A27: ES | B27: Espanha | C27: Spain | D27: 0.04421092 | E27: 2.0964272
A28: FR | B28: França | C28: France | D28: 0.43924152 | E28: 1.9630316
A29: HR | B29: Croácia | C29: Croatia | D29: -1.2100359 | E29: 3.6537963
... A45: SE | B45: Suécia | C45: Sweden | D45: 0.69950556 | E45: 2.0671286
A47: Fonte: Cálculos do Banco de Portugal. | Nota: β ̂ denota o coeficiente beta estimado com erros robustos. *** denota significância estatística a 1%. Um coeficiente beta estimado negativo e estatisticamente significativo revela convergência absoluta. Os resultados mantêm-se quando a equação é estimada com dados corrigidos de paridade de poder de compra.
A48: Source: Banco de Portugal calculations. | Note: β ̂ denotes the beta coefficient estimated with robust errors. *** denotes statistical significance at 1% level. A negative and statistically significant estimated beta coefficient indicates absolute beta convergence. The results hold when the equation is estimated using purchasing power parity adjusted data.

Sheet TED.G5
A5: Índice/Contents
A6: =+Índice!$A$5 -> Boletim Económico - março 2024 / Economic Bulletin - March 2024
A7: =Índice!$A$61 -> Parte II. Tema em Destaque: Bem-estar e PIB per capita em Portugal face à EU / Part II. Special issue: Welfare and GDP per capita in Portugal compared to the EU
A10: Gráfico 5 • Índice de bem-estar e PIB per capita em Portugal entre 1995 e 2022| Em percentagem da EU
A11: Chart 5 • Welfare index and GDP per capita in Portugal between 1995 and 2022| Percentage of the EU
A14: Unidade/Unit | C14: % da UE/ % of EU (PPS) | D14: % da UE/ % of EU (PPS) | F14: % da UE/ % of EU (Euros) | G14: % da UE/ % of EU (Euros)
C16: Painel A – Dados nominais corrigidos de paridades de poder de compra | F16: Painel B – Dados encadeados em volume
C17: PIB per capita | D17: Índice de bem-estar | F17: PIB per capita | G17: Índice de bem-estar
C18: Panel A – Nominal data adjusted for purchasing power parities | F18: Panel B – Chain-linked volume data
C19: GDP per capita | D19: Welfare index | F19: GDP per capita | G19: Welfare index
B20: 1995 | C20: 80.968914 | D20: 76.968827 | F20: 68.335593 | G20: 63.447651
B21: 1996 | C21: 81.138481 | D21: 75.268964 | F21: 69.339246 | G21: 62.536252
B22: 1997 | C22: 82.602254 | D22: 76.582582 | F22: 70.289535 | G22: 63.651919
B23: 1998 | C23: 83.349913 | D23: 76.388294 | F23: 71.239808 | G23: 64.191874
B24: 1999 | C24: 85.160661 | D24: 78.014517 | F24: 71.592031 | G24: 64.919059
B25: 2000 | C25: 85.34424 | D25: 80.134753 | F25: 71.201995 | G25: 65.944037
B26: 2001 | C26: 84.111284 | D26: 78.416085 | F26: 70.666912 | G26: 64.909146
B27: 2002 | C27: 83.964128 | D27: 78.292154 | F27: 70.215082 | G27: 64.738928
B28: 2003 | C28: 84.205702 | D28: 79.35168 | F28: 68.963244 | G28: 64.168857
B29: 2004 | C29: 82.843087 | D29: 81.399596 | F29: 68.54861 | G29: 66.451174
B30: 2005 | C30: 84.563655 | D30: 83.066814 | F30: 67.93982 | G30: 65.704519
B31: 2006 | C31: 84.552803 | D31: 85.627283 | F31: 66.823625 | G31: 66.798007
... B47: 2022 | C47: 78.747462 | D47: 87.086445 | F47: 65.70272 | G47: 72.678708
A49: Fontes: Eurostat e cálculos do Banco de Portugal. | Nota: Para analisar pontos específicos do tempo é recomendada a utilização de dados corrigidos de paridades de poder de compra (gráfico da esquerda), que corresponde à análise feita na primeira secção de resultados do Tema em Destaque. Para avaliar a evolução ao longo do tempo, é preferível utilizar dados em volume, para expurgar efeitos de preços (gráfico da direita).
A50: Sources: Eurostat and Banco de Portugal calculations. | Notes: For analysing specific points in time, purchasing power parities adjusted data is recommended (chart on the left), corresponding to the analysis developed in the first section of this Special Issue. For assessing developments over time, it is preferable to use volume data to exclude price effects (chart on the right).

Sheet TED.Q1
A5: Índice/Contents
A6: =+Índice!$A$5 -> Boletim Económico - março 2024 / Economic Bulletin - March 2024
A7: =Índice!$A$61 -> Parte II. Tema em Destaque: Bem-estar e PIB per capita em Portugal face à EU / Part II. Special issue: Welfare and GDP per capita in Portugal compared to the EU
A10: Quadro 1 • Índice de Bem-estar e PIB per capita em 2022 e decomposição da diferença entre as duas medidas
A11: Table 1 • Welfare Index and GDP per capita in 2022 and decomposition of the difference between the two measures
A14: Unidade/Unit | D14: % da UE/ % of EU (PPS) | E14: % da UE/ % of EU (PPS) | G14: Pontos de logaritmo/ Log points | H14: Pontos de logaritmo/ Log points | I14: Pontos de logaritmo/ Log points | J14: Pontos de logaritmo/ Log points | K14: Pontos de logaritmo/ Log points
H15: Decomposição/ Decomposition
D16: Índice de bem-estar | E16: PIB per capita | G16: Diferença de logaritmos | H16: Esperança média de vida | I16: Peso do consumo no PIB | J16: Lazer | K16: Desigualdade
D17: Welfare index | E17: GDP per capita | G17: Log ratio | H17: Life expectancy | I17: Consumption share in GDP | J17: Leisure | K17: Inequality
B18: União Europeia | C18: European Union | D18: 100 | E18: 100 | G18: 0 | H18: 0 | I18: 0 | J18: 0 | K18: 0
B19: Luxemburgo | C19: Luxembourg | D19: 171.02615 | E19: 256.50475 | G19: -0.40533072 | H19: 0.15288749 | I19: -0.42174892 | J19: -0.13891504 | K19: 0.0024457398
B20: Bélgica | C20: Belgium | D20: 139.24528 | E20: 119.59785 | G20: 0.15210214 | H20: 0.071428254 | I20: 0.013334835 | J20: 0.024891086 | K20: 0.042447967
B21: Países Baixos | C21: Netherlands | D21: 130.78811 | E21: 130.53657 | G21: 0.0019250751 | H21: 0.064247322 | I21: -0.07820832 | J21: -0.01361997 | K21: 0.029506043
B22: Irlanda | C22: Ireland | D22: 130.23673 | E22: 234.94685 | G22: -0.5900055 | H22: 0.12683873 | I22: -0.71662372 | J22: -0.019720923 | K22: 0.019500411
B23: Suécia | C23: Sweden | D23: 129.93633 | E23: 119.51267 | G23: 0.083622141 | H23: 0.15140714 | I23: -0.070291811 | J23: -0.0079134434 | K23: 0.010420255
B24: Dinamarca | C24: Denmark | D24: 128.76868 | E24: 136.45849 | G24: -0.05800284 | H24: 0.038623213 | I24: -0.12258536 | J24: 0.0056280383 | K24: 0.020331266
B25: Áustria | C25: Austria | D25: 124.685 | E25: 124.15491 | G25: 0.0042604646 | H25: 0.025653358 | I25: -0.023523504 | J25: -0.0096483673 | K25: 0.011778978
B26: França | C26: France | D26: 120.51847 | E26: 100.14387 | G26: 0.18519521 | H26: 0.10045649 | I26: 0.051657661 | J26: 0.03153927 | K26: 0.0015417882
B27: Finlândia | C27: Finland | D27: 119.78942 | E27: 109.91576 | G27: 0.086021066 | H27: 0.031780561 | I27: 0.027242638 | J27: -0.0027713446 | K27: 0.029769211
B28: Alemanha | C28: Germany | D28: 117.28211 | E28: 116.67011 | G28: 0.0052318622 | H28: 0 | I28: -0.0068358759 | J28: 0.010224233 | K28: 0.0018435052
B29: Itália | C29: Italy | D29: 117.20095 | E29: 96.97998 | G29: 0.1893854 | H29: 0.14241483 | I29: 0.070102962 | J29: 0.0055066661 | K29: -0.028639054
... B45: Bulgária | C45: Bulgaria | D45: 39.940534 | E45: 62.121221 | G45: -0.44169596 | H45: -0.34996022 | I45: 0.038876082 | J45: -0.032679507 | K45: -0.097932322
A47: Fontes: Eurostat e cálculos do Banco de Portugal. | Notas: Dados corrigidos de paridades de poder de compra. Valores positivos/negativos do logaritmo do rácio correspondem a países com índice de bem-estar (λ) superior/inferior ao PIB per capita (ambos em percentagem da UE). O recurso à função logaritmo permite a aditividade dos contributos. Para detalhes sobre esta decomposição consultar a Caixa 1.
A48: Sources: Eurostat and Banco de Portugal calculations. | Notes: Data adjusted for purchasing power parities. Positive/negative values of the log ratio correspond to countries with a welfare index (λ) higher/lower than GDP per capita (both as a percentage of the EU). The use of the logarithm function allows for the additivity of contributions. For details on this decomposition, see Box 1.

Sheet TED.Q2
A5: Índice/Contents
A6: =+Índice!$A$5 -> Boletim Económico - março 2024 / Economic Bulletin - March 2024
A7: =Índice!$A$61 -> Parte II. Tema em Destaque: Bem-estar e PIB per capita em Portugal face à EU / Part II. Special issue: Welfare and GDP per capita in Portugal compared to the EU
A10: Quadro 2 • Crescimento do Índice de Bem-estar e do PIB per capita, entre 1995 e 2022, e decomposição da diferença | Em percentagem e pontos percentuais
A11: Table 2 • Welfare Index and GDP per capita growth between 1995 and 2022, and decomposition of the difference | Percentage and percentage points
A14: Unidade/Unit | D14: % | E14: % | G14: Pontos percentuais/ Percentage points | H14: Pontos percentuais/ Percentage points | I14: Pontos percentuais/ Percentage points | J14: Pontos percentuais/ Percentage points | K14: Pontos percentuais/ Percentage points
H15: Decomposição/ Decomposition
D16: Índice de bem-estar | E16: PIB per capita | G16: Diferença | H16: Esperança média de vida | I16: Peso do consumo no PIB | J16: Lazer | K16: Desigualdade
D17: Welfare index | E17: GDP per capita | G17: Difference | H17: Life expectancy | I17: Consumption share in GDP | J17: Leisure | K17: Inequality
B18: Estónia | C18: Estonia | D18: 6.2692879 | E18: 4.0981894 | G18: 2.1710985 | H18: 2.0853786 | I18: -0.033689493 | J18: -0.05788872 | K18: 0.17729813
B19: Roménia | C19: Romania | D19: 5.7381124 | E19: 3.6321865 | G19: 2.105926 | H19: 1.0512316 | I19: 0.93031306 | J19: 0.15358353 | K19: -0.029202212
B20: Letónia | C20: Latvia | D20: 5.6946962 | E20: 4.559134 | G20: 1.1355622 | H20: 1.8337832 | I20: -0.51538924 | J20: -0.090840179 | K20: -0.091991563
B21: Lituânia | C21: Lithuania | D21: 5.2210996 | E21: 4.9003886 | G21: 0.32071101 | H21: 1.323401 | I21: -0.64334721 | J21: -0.28803216 | K21: -0.071310636
B22: Polónia | C22: Poland | D22: 4.7646384 | E22: 3.9888801 | G22: 0.77575832 | H22: 1.012243 | I22: -0.38316965 | J22: -0.13569641 | K22: 0.28238134
B23: Irlanda | C23: Ireland | D23: 4.1467676 | E23: 4.5898204 | G23: -0.44305285 | H23: 1.6743019 | I23: -2.3266014 | J23: -0.1217114 | K23: 0.33095805
B24: Eslováquia | C24: Slovakia | D24: 3.8114947 | E24: 3.3603099 | G24: 0.45118485 | H24: 0.97874588 | I24: -0.60829527 | J24: 0.011930858 | K24: 0.068803378
B25: Croácia | C25: Croatia | D25: 3.6537963 | E25: 2.9921531 | G25: 0.66164321 | H25: 1.091657 | I25: -0.31688311 | J25: -0.18860692 | K25: 0.075476241
B26: Eslovénia | C26: Slovenia | D26: 3.5569403 | E26: 2.3979256 | G26: 1.1590146 | H26: 1.3876032 | I26: -0.36702106 | J26: -0.014904877 | K26: 0.15333734
B27: Hungria | C27: Hungary | D27: 3.5318712 | E27: 2.7819718 | G27: 0.7498994 | H27: 1.2259709 | I27: -0.37567871 | J27: -0.11675615 | K27: 0.016363315
B28: Chéquia | C28: Czechia | D28: 2.9736561 | E28: 2.1806179 | G28: 0.79303813 | H28: 1.1552441 | I28: -0.33031367 | J28: 0.003388717 | K28: -0.035280968
B29: Bulgária | C29: Bulgaria | D29: 2.9588174 | E29: 3.1998283 | G29: -0.24101095 | H29: 0.57060582 | I29: -0.25887879 | J29: -0.17762403 | K29: -0.37511394
... B45: Itália | C45: Italy | D45: 1.3872452 | E45: 0.47169996 | G45: 0.9155452 | H45: 1.0669452 | I45: -0.024629962 | J45: -0.036827874 | K45: -0.089942202
A47: Fontes: Eurostat e cálculos do Banco de Portugal. | Notas: Taxas de variação com dados encadeados em volume, em euros.
A48: Sources: Eurostat and Banco de Portugal calculations. | Notes: Rates of change were computed using chain-linked volume data, in euros.

Sheet PEA.G1
A5: Índice/Contents
A6: =+Índice!$A$5 -> Boletim Económico - março 2024 / Economic Bulletin - March 2024
A7: =Índice!$A$77 -> Parte III. Políticas em análise: Evidência do PISA sobre as competências dos jovens portugueses / Part III. Policy insights: Evidence from PISA on the skills of Portuguese students
A10: Gráfico 1 • Escolaridade da população adulta em Portugal e na área do euro | Em percentagem
A11: Chart 1 • Education of the adult population in Portugal and the euro area | In percentage
C13: Portugal | E13: Área do euro | H13: Portugal | J13: Área do euro
C14: Portugal | E14: Euro area | H14: Portugal | J14: Euro area
C15: 2006 | D15: 2022 | E15: 2006 | F15: 2022 | H15: 25-34 | I15: 55-64 | J15: 25-34 | K15: 55-64
A16: < 12º. ano | B16: < upper secondary education | C16: 72.5 | D16: 39.7 | E16: 34.1 | F16: 23.2 | H16: 16.7 | I16: 62.7 | J16: 15.8 | K16: 30.9
A17: 12º. ano | B17: Upper secondary education | C17: 14 | D17: 28.9 | E17: 43 | F17: 41.8 | H17: 38.8 | I17: 19 | J17: 41 | K17: 43.6
A18: Ensino superior | B18: Tertiary education | C18: 13.4 | D18: 31.5 | E18: 23 | F18: 35 | H18: 44.4 | I18: 18.3 | J18: 43.2 | K18: 25.6
A21: Fonte: Eurostat
A22: Source: Eurostat

Sheet PEA.G2
A5: Índice/Contents
A6: =+Índice!$A$5 -> Boletim Económico - março 2024 / Economic Bulletin - March 2024
A7: =Índice!$A$77 -> Parte III. Políticas em análise: Evidência do PISA sobre as competências dos jovens portugueses / Part III. Policy insights: Evidence from PISA on the skills of Portuguese students
A10: Gráfico 2 • Resultados do PISA em Portugal e na área do euro | Em pontos
A11: Chart 2 • PISA results in Portugal and the euro area | In points
D14: Matemática / Mathematics | L14: Leitura / Reading
D15: 2003 | E15: 2006 | F15: 2009 | G15: 2012 | H15: 2015 | I15: 2018 | J15: 2022 | L15: 2003 | M15: 2006 | N15: 2009 | O15: 2012 | P15: 2015 | Q15: 2018 | R15: 2022
A16: Portugal | B16: Portugal | D16: 466.01669 | E16: 466.16099 | F16: 486.88831 | G16: 487.06318 | H16: 491.62697 | I16: 492.48741 | J16: 471.91052 | L16: 477.56865 | M16: 472.30431 | N16: 489.33492 | O16: 487.75769 | P16: 498.12891 | Q16: 491.80079 | R16: 476.58861
A17: Área do euro | B17: Euro Area | D17: 498.22242 | E17: 495.50747 | F17: 493.48976 | G17: 492.5009 | H17: 489.24629 | I17: 491.1935 | J17: 473.92893 | L17: 494.08043 | M17: 487.91046 | N17: 488.80495 | O17: 492.90861 | P17: 489.52106 | Q17: 483.28247 | R17: 469.68491
A18: Percentil 25 | B18: Percentile 25 | D18: 483.37495 | E18: 479.95751 | F18: 481.95382 | G18: 482.31338 | H18: 478.51409 | I18: 482.4346 | J18: 468.63779 | L18: 477.56865 | M18: 470.07076 | N18: 481.04233 | O18: 482.12847 | P18: 478.58227 | Q18: 475.97628 | R18: 463.88946
A19: Percentil 75 | B19: Percentile 75 | D19: 510.79947 | E19: 505.4836 | F19: 512.1042 | G19: 511.52898 | H19: 506.47782 | I19: 505.48697 | J19: 485.89825 | L19: 506.98733 | M19: 500.74976 | N19: 497.30506 | O19: 508.38254 | P19: 504.08747 | Q19: 494.72532 | R19: 480.09994
A23: Fonte: OCDE e cálculos do Banco de Portugal. | Notas: A média da área do euro é uma média simples dos países considerados no relatório de 2022 da OCDE. Os países não considerados são os seguintes: o Luxemburgo em todos os anos; a Croácia, a Estónia, a Lituânia e a Eslovénia em 2003, o Chipre até 2009; Malta até 2006 e em 2012; a Áustria em 2009; e Espanha em 2018.
A24: Source: OECD and Banco de Portugal calculations. | Notes: The euro area average is a simple average of the countries considered in the 2022 OECD report. The countries not considered are the following: Luxembourg in all years; Croatia, Estonia, Lithuania and Slovenia in 2003, Cyprus until 2009; Malta until 2006 and in 2012; Austria in 2009; and Spain in 2018.

Sheet PEA.G3
A5: Índice/Contents
A6: =+Índice!$A$5 -> Boletim Económico - março 2024 / Economic Bulletin - March 2024
A7: =Índice!$A$77 -> Parte III. Políticas em análise: Evidência do PISA sobre as competências dos jovens portugueses / Part III. Policy insights: Evidence from PISA on the skills of Portuguese students
A10: Gráfico 3 • Estudantes nos extremos de competências a matemática | Em percentagem
A11: Chart 3 • Low and top performers in mathematics | In percentage
D17: Portugal | K17: Área do euro / Euro area
D18: 2006 | E18: 2009 | F18: 2012 | G18: 2015 | H18: 2018 | I18: 2022 | K18: 2006 | L18: 2009 | M18: 2012 | N18: 2015 | O18: 2018 | P18: 2022
A19: Sem competências básicas | B19: Low performers | D19: -30.716229 | E19: -23.717071 | F19: -24.906079 | G19: -23.76472 | H19: -23.281121 | I19: -29.717372 | K19: -20.987178 | L19: -22.043185 | M19: -22.582996 | N19: -23.072733 | O19: -22.522492 | P19: -29.193618
A20: Com competências de topo | B20: Top performers | D20: 5.6931666 | E20: 9.6319193 | F20: 10.633824 | G20: 11.426756 | H20: 11.608692 | I20: 6.6739 | K20: 11.978281 | L20: 11.573386 | M20: 11.544904 | N20: 10.056019 | O20: 10.559713 | P20: 7.9409939
A24: Fonte: OCDE e cálculos do Banco de Portugal. | Notas: A média da área do euro é uma média simples dos países considerados no relatório de 2022 da OCDE.
A25: Source: OECD and Banco de Portugal calculations. | Notes: The euro area average is a simple average of the countries considered in the 2022 OECD report.

Sheet PEA.G4
A5: Índice/Contents
A6: =+Índice!$A$5 -> Boletim Económico - março 2024 / Economic Bulletin - March 2024
A7: =Índice!$A$77 -> Parte III. Políticas em análise: Evidência do PISA sobre as competências dos jovens portugueses / Part III. Policy insights: Evidence from PISA on the skills of Portuguese students
A10: Gráfico 4 • Decomposição da evolução dos resultados do PISA em Portugal | Em pontos
A11: Chart 4 • Decomposition of the change in PISA results in Portugal | In points
C13: Efeito Composição | D13: Efeito Estrutural | E13: Efeito Total | G13: Efeito Composição | H13: Efeito Estrutural | I13: Efeito Total
C14: Composition effect | D14: Structural effect | E14: Total effect | G14: Composition effect | H14: Structural effect | I14: Total effect
A15: Total | B15: Total | C15: 10.722876 | D15: 16.467384 | E15: 27.19026 | G15: 0.30838833 | H15: -21.278772 | I15: -20.970383
A16: Aluno | B16: Student | C16: 0.38013382 | D16: -1.937032 | E16: -1.5568982 | G16: -0.29730593 | H16: 0.24875742 | I16: -0.048548509
A17: Família | B17: Family | C17: 9.2476647 | D17: 3.1277149 | E17: 12.37538 | G17: 0.59798705 | H17: 1.5535251 | I17: 2.1515121
A18: Escola | B18: School | C18: 1.0950776 | D18: -0.26299912 | E18: 0.83207848 | G18: 0.0077072051 | H18: -1.4714541 | I18: -1.4637469
A19: Outros | B19: Other | C19: 0 | D19: 15.5397 | E19: 15.5397 | G19: 0 | H19: -21.6096 | I19: -21.6096
A22: Fonte: OCDE e cálculos do Banco de Portugal. | Notas: A decomposição é calculada como Yt-Yt-1=(Xt-Xt-1)bt + Xt-1(bt-bt-1), onde Y é a média das pontuações, X são as médias das variáveis, b os coeficientes estimados, t é o ano final do período e t-1 o ano inicial. As regressões controlam por características do estudante (género e idade), da família (estatuto de imigrante, mãe com ensino secundário e mais de 100 livros em casa) e da escola (escola privada e contexto urbano). Para o período de 2018 a 2022, a inclusão de mais variáveis da escola (proporção de professores com mestrado e escola em que os diretores afirmaram que o ensino é muito afetado pela falta de professores) não altera de forma significativa os resultados. As regressões são ponderadas, utilizando os ponderadores finais por aluno.
A23: Sources: Statistics Portugal and Banco de Portugal calculations. | Notes: The decomposition is computed as Yt-Yt-1=(Xt-Xt-1)bt + Xt-1(bt-bt-1), where Y is the average of the scores, X are the means of the variables, b are the estimated coefficients, t is the final year of the period and t-1 the initial year.The regressions control for student characteristics (gender and age), family characteristics (immigrant status, mother with secondary education and more than 100 books at home) and school characteristics (private school and urban context). For the period from 2018 to 2022, the inclusion of more school variables (proportion of teachers with a master's degree and school in which principals stated that teaching is greatly affected by the lack of teachers) does not significantly change the results. Regressions are weighted using the final weights per student.

Sheet PEA.G5
A5: Índice/Contents
A6: =+Índice!$A$5 -> Boletim Económico - março 2024 / Economic Bulletin - March 2024
A7: =Índice!$A$77 -> Parte III. Políticas em análise: Evidência do PISA sobre as competências dos jovens portugueses / Part III. Policy insights: Evidence from PISA on the skills of Portuguese students
A10: Gráfico 5 • Variação dos resultados a matemática em 2022 nos diferentes países da área do euro | Em pontos
A11: Chart 5 • Change in mathematics results in 2022 in euro area countries | In points
B13: Variação 2018-2022 | C13: Intervalo de confiança a 95% | E13: Variação comum controlando por características observadas
B14: Change between 2018-2022 | C14: 95% confidence interval | E14: Common change controlling for observed characteristics
A15: NL | B15: -26.55534 | C15: -35.52896 | D15: -17.58172 | E15: -13.9
A16: DE | B16: -25.21733 | C16: -32.57309 | D16: -17.86157 | E16: -13.9
A17: FI | B17: -23.16214 | C17: -28.36114 | D17: -17.96313 | E17: -13.9
A18: SK | B18: -22.17024 | C18: -29.68109 | D18: -14.65938 | E18: -13.9
A19: FR | B19: -21.46316 | C19: -28.03672 | D19: -14.8896 | E19: -13.9
A20: EL | B20: -21.22402 | C20: -28.82125 | D20: -13.62679 | E20: -13.9
A21: PT | B21: -20.57688 | C21: -27.78912 | D21: -13.36464 | E21: -13.9
A22: BE | B22: -18.58349 | C22: -24.32166 | D22: -12.84532 | E22: -13.9
A23: IT | B23: -15.33038 | C23: -23.47815 | D23: -7.182612 | E23: -13.9
A24: EE | B24: -13.46763 | C24: -18.36788 | D24: -8.567369 | E24: -13.9
A25: LV | B25: -12.96688 | C25: -18.28624 | D25: -7.647511 | E25: -13.9
A26: AT | B26: -11.67481 | C26: -18.70742 | D26: -4.642208 | E26: -13.9
... A30: HR | B30: -1.099083 | C30: -7.924106 | D30: 5.725939 | E30: -13.9
A32: Fonte: OCDE e cálculos do Banco de Portugal. | Notas: A vermelho estão assinalados os intervalos de confiança a 95% das estimativas da queda média dos resultados em cada país, tendo em consideração a incerteza associada à medição das competências e à extrapolação da amostra para a população total. A variação comum controlando para as características observadas corresponde ao efeito fixo do ano calculado numa regressão dos resultados a matemática em 2018 e 2022 incluindo efeitos fixos de país e do ano e as seguintes variáveis explicativas: características do estudante (género e idade), da família (estatuto de imigrante, mãe com ensino secundário e mais de 100 livros em casa) e da escola (escola privada, contexto urbano, proporção de professores com mestrado, escola em que os diretores afirmaram que o ensino é muito afetado pela falta de professores). Inclui-se também, para todas as variáveis, a interação com o país.
A33: Source: OECD and Banco de Portugal calculations. | Notes: The 95% confidence intervals for the estimates of the average drop in results in each country are marked in red, taking into account the uncertainty associated with measuring skills and extrapolating the sample to the total population. The common change controlling for observed characteristics corresponds to the year fixed effect calculated in a regression of mathematics results in 2018 and 2022 including country and year fixed effects and the following explanatory variables: student characteristics (gender and age), family characteristics (immigrant status, mother with secondary education and more than 100 books at home) and school characteristics (private school, urban context, proportion of teachers with a master's degree, school in which principals stated that teaching is greatly affected by the lack of teachers). For all variables, an interaction term with the country is also included.

Sheet PEA.G6
A5: Índice/Contents
A6: =+Índice!$A$5 -> Boletim Económico - março 2024 / Economic Bulletin - March 2024
A7: =Índice!$A$77 -> Parte III. Políticas em análise: Evidência do PISA sobre as competências dos jovens portugueses / Part III. Policy insights: Evidence from PISA on the skills of Portuguese students
A10: Gráfico 6 • Variação entre 2018 e 2022 da diferença entre o último e o primeiro decil das pontuações a matemática | Em pontos
A11: Chart 6 • Change between 2018 and 2022 in the gap between the last and first decile of mathematics scores | In points
C13: Variação do intervalo inter-decil
C14: Inter-decile range variation
B15: PT | C15: -18.8968
B16: EL | C16: -14.6988
B17: IT | C17: -9.4348
B18: LT | C18: -9.2092
B19: MT | C19: -5.7463
B20: FR | C20: -1.8333
B21: LV | C21: -0.3292
B22: DE | C22: 0.6129
B23: AT | C23: 2.1493
B24: BE | C24: 2.3056
B25: AE | C25: 2.316114
B26: SI | C26: 4.5718
... B33: ND | C33: 38.7253
A35: Fonte: OCDE e cálculos do Banco de Portugal. | Notas: A média da área do euro é uma média simples dos países considerados no relatório de 2022 da OCDE.
A36: Source: OECD and Banco de Portugal calculations. | Notes: The euro area average is a simple average of the countries considered in the 2022 OECD report.

Sheet PEA.G7
A5: Índice/Contents
A6: =+Índice!$A$5 -> Boletim Económico - março 2024 / Economic Bulletin - March 2024
A7: =Índice!$A$77 -> Parte III. Políticas em análise: Evidência do PISA sobre as competências dos jovens portugueses / Part III. Policy insights: Evidence from PISA on the skills of Portuguese students
A10: Gráfico 7 • Variação dos resultados a matemática em 2022 nos extremos de estatuto socioeconómico ao longo da distribuição | Em pontos
A11: Chart 7 • Change in mathematics results in 2022 by socio-economic status along the distribution | In points
C14: Estatuto socioeconómico elevado | D14: Estatuto socioeconómico baixo
C15: High socio-economic status | D15: Low socio-economic status
B16: 10 | C16: -15.66307 | D16: -8.016843
B17: 20 | C17: -16.43709 | D17: -12.61797
B18: 30 | C18: -17.00236 | D18: -15.98888
B19: 40 | C19: -17.48883 | D19: -18.85557
B20: 50 | C20: -17.93908 | D20: -21.54659
B21: 60 | C21: -18.38883 | D21: -24.224
B22: 70 | C22: -18.84751 | D22: -26.96025
B23: 80 | C23: -19.36741 | D23: -30.03502
B24: 90 | C24: -20.07429 | D24: -34.2318
A28: Fonte: OCDE e cálculos do Banco de Portugal. | Notas: As regressões de quantis controlam por: características do estudante (género e idade), da família (estatuto de imigrante, mãe com ensino secundário e mais de 100 livros em casa) e da escola (escola privada, contexto urbano). As regressões são ponderadas, utilizando os ponderadores finais por aluno, e corridas separadamente para cada valor plausível.
A29: Source: OECD and Banco de Portugal calculations. | Notes: Quantile regressions control for: student characteristics (gender and age), family characteristics (immigrant status, mother with secondary education and more than 100 books at home) and school characteristics (private school, urban context). Regressions are weighted, using the final weights per student, and run separately for each plausible value.
