Workbook

Sheet Capa
A53: Nota: Neste ficheiro são disponiblizados os dados subjacentes aos gráficos e quadros do Boletim Económico – junho 2024. Note: This file contains the data used in the charts and tables of the Economic Bulletin – june 2024.

Sheet Índice
B1: Classificação de Segurança - Público
A5: Boletim Económico - junho 2024/Economic Bulletin June 2024
A6: ÍNDICE/CONTENTS
A7: Parte I. Projeções para a economia portuguesa: 2024-26/Part I. Projections for the Portuguese economy: 2024-26
A8: =HYPERLINK("#"&C8,INDIRECT(C8)) -> Quadro I.1.1 • Projeções do Banco de Portugal para 2024-26 | Taxa de variação anual, em percentagem (exceto onde indicado) | C8: QI.1.1!A$10
A9: =HYPERLINK("#"&C9,INDIRECT(C9)) -> Table I.1.1 • Projections of Banco de Portugal for 2024-26| Annual rate of change, in percentage (unless otherwise stated) | C9: QI.1.1!A$11
A10: =HYPERLINK("#"&C10,INDIRECT(C10)) -> Gráfico I.1.1 • PIB em Portugal e na área do euro | C10: GI.1.1!A$10
A11: =HYPERLINK("#"&C11,INDIRECT(C11)) -> Chart I.1.1 • GDP in Portugal and the euro area | C11: GI.1.1!A$11
A12: =HYPERLINK("#"&C12,INDIRECT(C12)) -> Gráfico I.1.2 • Projeções trimestrais para o PIB e para a inflação | C12: GI.1.2!A$10
A13: =HYPERLINK("#"&C13,INDIRECT(C13)) -> Chart I.1.2 • Quarterly GDP and inflation projections | C13: GI.1.2!A$11
A14: =HYPERLINK("#"&C14,INDIRECT(C14)) -> Gráfico I.1.3 • Taxa de variação do PIB e contributos líquidos de conteúdos importados das componentes | Percentagem e pontos percentuais | C14: GI.1.3!A$10
A15: =HYPERLINK("#"&C15,INDIRECT(C15)) -> Chart I.1.3 • GDP rate of change and import-content net contributions of components | Percentage and percentage points | C15: GI.1.3!A$11
A16: =HYPERLINK("#"&C16,INDIRECT(C16)) -> Gráfico I.1.4 • Consumo privado e rendimento disponível | Taxa de variação em percentagem e contributos para o rendimento disponível em pontos percentuais | C16: GI.1.4!A$10
A17: =HYPERLINK("#"&C17,INDIRECT(C17)) -> Chart I.1.4 • Private consumption and disposable income | Rate of change in percentage and contributions to disposable income in percentage points | C17: GI.1.4!A$11
A18: =HYPERLINK("#"&C18,INDIRECT(C18)) -> Gráfico I.1.5 • FBCF e componentes| Taxa de variação em percentagem | C18: GI.1.5!A$10
A19: =HYPERLINK("#"&C19,INDIRECT(C19)) -> Chart I.1.5 • GFCF and components| Rate of change in percentage | C19: GI.1.5!A$11
... A23: =HYPERLINK("#"&C23,INDIRECT(C23)) -> Chart I.1.7 • Observed HICP | Rate of change in percentage and contributions in percentage points | C23: GI.1.7!A$11
A25: Caixa 1- Enquadramento e políticas/Box 1-External environment, financing conditions and policies
A26: =HYPERLINK("#"&C26,INDIRECT(C26)) -> Gráfico C1.1 • IHPC e indicador PMI para o preço dos inputs na área do euro | Taxa de variação em cadeia anualizada sobre dados corrigidos de variações sazonais e em média móvel de 3 meses | C26: GC.1.1!A$10
A27: =HYPERLINK("#"&C27,INDIRECT(C27)) -> Chart B1.1 • HICP and PMI indicator for the price of inputs in the euro area | Annualized quarter-on-quarter variation rate of 3-month moving average and seasonally adjusted data | C27: GC.1.1!A$11
A28: =HYPERLINK("#"&C28,INDIRECT(C28)) -> Quadro C1.1 • Hipóteses do exercício de projeção elaboradas por especialistas do Eurosistema | C28: QC.1.1!A$10
A29: =HYPERLINK("#"&C29,INDIRECT(C29)) -> Table B1.1 • Eurosystem staff projection assumptions | C29: QC.1.1!A$11
A31: Caixa 2-Termos de troca no comércio de bens /Box 2-Terms of trade in goods
A32: =HYPERLINK("#"&C32,INDIRECT(C32)) -> Gráfico C2.1 • Termos de troca | Índice 2015 = 100 | C32: GC.2.1!A$10
A33: =HYPERLINK("#"&C33,INDIRECT(C33)) -> Chart B2.1 • Terms of trade | Index 2015 = 100 | C33: GC.2.1!A$11
A34: =HYPERLINK("#"&C34,INDIRECT(C34)) -> Gráfico C2.2 • Variação dos termos de troca de bens – contributos da componente energética e não energética | Em pontos percentuais | C34: GC.2.2!A$10
A35: =HYPERLINK("#"&C35,INDIRECT(C35)) -> Chart B2.2 • Terms of trade in goods change – contributions of energy and non-energy | In percentage points | C35: GC.2.2!A$11
A36: =HYPERLINK("#"&C36,INDIRECT(C36)) -> Gráfico C2.3 • Variação de termos de troca de bens e contributos dos efeitos estrutura e preço relativo | Em pontos percentuais | C36: GC.2.3!A$10
A37: =HYPERLINK("#"&C37,INDIRECT(C37)) -> Chart B2.3 • Terms of trade in goods change and contributions of structure and relative price effects | In percentage points | C37: GC.2.3!A$11
A38: =HYPERLINK("#"&C38,INDIRECT(C38)) -> Quadro C2.1 • Contributos dos grupos de produtos para a variação dos termos de troca de bens – 2023 vs. 2015 | Variação acumulada em percentagem e contributos em pp | C38: QC.2.1!A$10
A39: =HYPERLINK("#"&C39,INDIRECT(C39)) -> Table B2.1 • Groups of products' contribution to the terms of trade total variation – 2023 vs. 2015 | Cumulative growth as a percentage and contributions in pp | C39: QC.2.1!A$11
A41: Caixa 3 - A transmissão do preço dos bens energéticos ao IHPC / Box 3- The pass-through of energy prices to the HICP
A42: =HYPERLINK("#"&C42,INDIRECT(C42)) -> Gráfico C3.1 • IHPC total e IHPC de bens energéticos | Taxa de variação homóloga em percentagem e contributos em pontos percentuais | C42: GC.3.1!A$10
A43: =HYPERLINK("#"&C43,INDIRECT(C43)) -> Chart B3.1 • HICP headline and HICP of energy goods | Year-on-year change rate in percentage and contributions in percentage points | C43: GC.3.1!A$11
A44: =HYPERLINK("#"&C44,INDIRECT(C44)) -> Gráfico C3.2 • Resposta da inflação e dos seus componentes a um choque de 1 desvio padrão no preço dos bens energéticos | Pontos percentuais | C44: GC.3.2!A$10
A45: =HYPERLINK("#"&C45,INDIRECT(C45)) -> Chart B3.2 • Response of inflation and its components to a shock of 1 standard deviation in energy prices | Percentage points | C45: GC.3.2!A$11
A46: =HYPERLINK("#"&C46,INDIRECT(C46)) -> Gráfico C3.3 • Decomposição histórica da inflação e contributos diretos e indiretos dos choques estruturais sobre o preço dos bens energéticos | Taxa de variação homóloga em percentagem e contributos erm pontos percentuais | C46: GC.3.3!A$10
A47: =HYPERLINK("#"&C47,INDIRECT(C47)) -> Chart B3.3 • Historical decomposition of inflation and direct and indirect contributes of structural shocks to energy prices | Y-o-y rate of change in percentage and contributions in percentage points | C47: GC.3.3!A$11
A48: =HYPERLINK("#"&C48,INDIRECT(C48)) -> Quadro C3.1 • Contributo para a inflação dos choques estruturais sobre o preço da energia | Pontos percentuais | C48: QC.3.1!A$10
A49: =HYPERLINK("#"&C49,INDIRECT(C49)) -> Table B3.1 • Contribution to inflation from structural energy price shocks | Percentage points | C49: QC.3.1!A$11
A50: Parte I.2 Análise e projeções de finanças públicas/Part I.2 Analysis and projections of public finances
A51: =HYPERLINK("#"&C51,INDIRECT(C51)) -> Gráfico I.2.1 Saldo das administrações públicas observado e projetado em Portugal e na área do euro | Em percentagem do PIB | C51: GI.2.1!A$10
A52: =HYPERLINK("#"&C52,INDIRECT(C52)) -> Chart I.2.1 · General government balance outturn and projections in Portugal and the euro area | Percentage of GDP | C52: GI.2.1!A$11
A53: =HYPERLINK("#"&C53,INDIRECT(C53)) -> Gráfico I.2.2 Decomposição da variação do saldo das administrações públicas em Portugal e na área do euro| Em pontos percentuais do PIB e do PIB potencial | C53: GI.2.2!A$10
A54: =HYPERLINK("#"&C54,INDIRECT(C54)) -> Chart I.2.1 · Breakdown of the change in the general government balance in Portugal and the euro area | Percentage points of GDP and potential GDP | C54: GI.2.2!A$11
A55: =HYPERLINK("#"&C55,INDIRECT(C55)) -> Gráfico I.2.3 Impacto direto de medidas de política sobre o saldo orçamental em Portugal | Em percentagem do PIB | C55: GI.2.3!A$10
A56: =HYPERLINK("#"&C56,INDIRECT(C56)) -> Chart I.2.3 · Direct impact of policy measures on the budget balance in Portugal | Percentage of GDP | C56: GI.2.3!A$11
A57: =HYPERLINK("#"&C57,INDIRECT(C57)) -> Gráfico I.2.4 Decomposição da variação da receita fiscal e contributiva em Portugal | Em pontos percentuais do PIB | C57: GI.2.4!A$10
A58: =HYPERLINK("#"&C58,INDIRECT(C58)) -> Chart I.2.4 · Breakdown of the change in revenue from taxes and social contributions in Portugal | Percentage points of GDP | C58: GI.2.4!A$11
A59: =HYPERLINK("#"&C59,INDIRECT(C59)) -> Gráfico I.2.5 Decomposição da variação da despesa corrente primária estrutural em Portugal | Em pontos percentuais do PIB e do PIB potencial | C59: GI.2.5!A$10
A60: =HYPERLINK("#"&C60,INDIRECT(C60)) -> Chart I.2.5 · Breakdown of the change in structural primary current expenditure in Portugal | Percentage points of GDP and potencial GDP | C60: GI.2.5!A$11
A61: =HYPERLINK("#"&C61,INDIRECT(C61)) -> Gráfico I.2.6 Repartição temporal da despesa pública no âmbito do PRR em Portugal | Em percentagem do total do PRR em 2021-2026 | C61: GI.2.6!A$10
A62: =HYPERLINK("#"&C62,INDIRECT(C62)) -> Chart I.2.6 · Temporal allocation of public expenditure within the scope of the RRP in Portugal | Percentage of total RRP in 2021-2026 | C62: GI.2.6!A$11
... A68: =HYPERLINK("#"&C68,INDIRECT(C68)) -> Chart I.2.9 · Breakdown of the change in the debt ratio | In percentage points of GDP | C68: GI.2.9!A$11
A70: Caixa 5 - O referencial para a despesa pública utilizado nas regras orçamentais europeias e as medidas de política orçamental para os próximos anos/Box 5 - The expenditure benchmark used in European fiscal rules and the budgetary policy measures for the coming years
A71: =HYPERLINK("#"&C71,INDIRECT(C71)) -> Gráfico C5.1 Referencial para a despesa pública observado e PIB potencial nominal em Portugal | Taxas de variação em percentagem | C71: GC.5.1!A$10
A72: =HYPERLINK("#"&C72,INDIRECT(C72)) -> Chart B5.1 Expenditure benchmark observed and nominal potential GDP in Portugal | Percentage rates of change | C72: GC.5.1!A$11
A73: =HYPERLINK("#"&C73,INDIRECT(C73)) -> Quadro C5.1 Referencial da despesa usado nas regras orçamentais em 2025 | Em milhões de euros | C73: QC.5.1!A$10
A74: =HYPERLINK("#"&C74,INDIRECT(C74)) -> Table B5.1 · Expenditure benchmark used in the fiscal rules in 2025 | Million euros | C74: QC.5.1!A$11
A76: Caixa 6 - O efeito direto da inflação e da progressividade sobre a receita fiscal e contributiva/Box 6 - The direct effect of inflation and progressivity on tax and social contributions revenue
A77: =HYPERLINK("#"&C77,INDIRECT(C77)) -> Gráfico C6.1 Decomposição da variação da receita fiscal e contributiva em 2022–2026 | Em milhões de euros | C77: GC.6.1!A$10
A78: =HYPERLINK("#"&C78,INDIRECT(C78)) -> Chart B6.1 Breakdown of the change in tax and social contributions revenue in 2022-2026 | Million euros | C78: GC.6.1!A$11
A79: =HYPERLINK("#"&C79,INDIRECT(C79)) -> Gráfico C6.2 Impacto do aumento da inflação por imposto em 2022-2026 | Em milhões de euros | C79: GC.6.2!A$10
A80: =HYPERLINK("#"&C80,INDIRECT(C80)) -> Chart B6.2 Impact of the increase in inflation by tax 2022-2026 | In million euros | C80: GC.6.2!A$11
A81: =HYPERLINK("#"&C81,INDIRECT(C81)) -> Gráfico C6.3 Impacto da progressividade do IRS na receita| Em milhões de euros | C81: GC.6.3!A$10
A82: =HYPERLINK("#"&C82,INDIRECT(C82)) -> Chart B6.3 Impact of personal income tax progressivity on revenue | Million euros | C82: GC.6.3!A$11
A84: Caixa 7 - Trajetórias para a dívida pública portuguesa/Box 7 - Trajectories for Portuguese public debt
A85: =HYPERLINK("#"&C85,INDIRECT(C85)) -> Gráfico C7.1 Rácio da dívida pública: nível e decomposição da variação | Em percentagem e pontos percentuais do PIB | C85: GC.7.1!A$10
A86: =HYPERLINK("#"&C86,INDIRECT(C86)) -> Chart B7.1 Public debt ratio: level and breakdown of the change | In percentage and percentage points of GDP | C86: GC.7.1!A$11
A87: =HYPERLINK("#"&C87,INDIRECT(C87)) -> Gráfico C7.2 Resultados da análise determinística para as principais variáveis | Em percentagem e percentagem do PIB | C87: GC.7.2!A$10
A88: =HYPERLINK("#"&C88,INDIRECT(C88)) -> Chart B7.2 Deterministic analysis results for the main variables | In percentage and percentage of GDP | C88: GC.7.2!A$11
A89: =HYPERLINK("#"&C89,INDIRECT(C89)) -> Gráfico C7.3 Trajetórias para o rácio da dívida pública de acordo com a análise estocástica | Em percentagem do PIB | C89: GC.7.3!A$10
A90: =HYPERLINK("#"&C90,INDIRECT(C90)) -> Chart B7.3 Public debt ratio trajectories based on the stochastic analysis | In percentage of GDP | C90: GC.7.3!A$11
A91: =HYPERLINK("#"&C91,INDIRECT(C91)) -> Gráfico C7.4 Distribuição do rácio da dívida pública para 2033: probabilidade em exceder um valor | Em percentagem | C91: GC.7.4!A$10
A92: =HYPERLINK("#"&C92,INDIRECT(C92)) -> Chart B7.4 Distribution of the public debt ratio for 2033: probability of exceeding a value | In percentage | C92: GC.7.4!A$11
A95: Parte II. Tema em Destaque: Caraterização dos trabalhadores estrangeiros por conta de outrem em Portugal / Part II Special Issue: Characterization of foreign employees in Portugal
A96: =HYPERLINK("#"&C96,INDIRECT(C96)) -> Gráfico 1 • Trabalhadores com nacionalidade estrangeira | Número de indivíduos em cada mês | C96: TED.G1!A$10
A97: =HYPERLINK("#"&C97,INDIRECT(C97)) -> Chart 1 • Employees with foreign nationality | Number of individuals in each month | C97: TED.G1!A$11
A98: =HYPERLINK("#"&C98,INDIRECT(C98)) -> Gráfico 2 • Número de empresas com trabalhadores por nacionalidade| Milhares de empresas | C98: TED.G2!A$10
A99: =HYPERLINK("#"&C99,INDIRECT(C99)) -> Chart 2 • Number of firms with employees by nationality | Thousands of firms | C99: TED.G2!A$11
A100: =HYPERLINK("#"&C100,INDIRECT(C100)) -> Quadro 1 • Número de trabalhadores com nacionalidade estrangeira e respetivo peso por dimensão da empresa em 2023 | Número de indivíduos e peso em percentagem | C100: TED.Q1!A$10
A101: =HYPERLINK("#"&C101,INDIRECT(C101)) -> Table 1 • Number of employees with foreign nationality and respective weight by firm size in 2023 | Number of individuals and weight in percentage | C101: TED.Q1!A$11
A102: =HYPERLINK("#"&C102,INDIRECT(C102)) -> Gráfico 3 • Número de trabalhadores estrangeiros por principais nacionalidades | Número de indivíduos em cada mês | C102: TED.G3!A$10
A103: =HYPERLINK("#"&C103,INDIRECT(C103)) -> Chart 3 • Number of foreign employees by main nationalities | Number of individuals in each month | C103: TED.G3!A$11
A104: =HYPERLINK("#"&C104,INDIRECT(C104)) -> Gráfico 4 • Distribuição da idade dos trabalhadores por nacionalidade em 2023 | Anos | C104: TED.G4!A$10
A105: =HYPERLINK("#"&C105,INDIRECT(C105)) -> Chart 4 • Employees' age distribution by nationality in 2023 | Years | C105: TED.G4!A$11
A106: =HYPERLINK("#"&C106,INDIRECT(C106)) -> Gráfico 5 • Peso das mulheres no número total de trabalhadores por nacionalidade em 2023 | Percentagem | C106: TED.G5!A$10
A107: =HYPERLINK("#"&C107,INDIRECT(C107)) -> Chart 5 • Share of women in the total number of employees by nationality in 2023 | Percentage | C107: TED.G5!A$11
... A119: =HYPERLINK("#"&C119,INDIRECT(C119)) -> Chart 10 • Average and median of nominal gross regular wages by nationality in 2023 | Euros | C119: TED.G10!A$11
A121: Caixa 1 - Qualificações académicas da população estrangeira empregada em Portugal/Box 1 - Academic qualifications of the foreign population employed in Portugal
A122: =HYPERLINK("#"&C122,INDIRECT(C122)) -> Gráfico C1.1 • População residente empregada (20 a 64 anos) por nacionalidade e escolaridade máxima| Percentagem do total da população da respetiva nacionalidade | C122: TED.C.G1!A$10
A123: =HYPERLINK("#"&C123,INDIRECT(C123)) -> Chart C1.1 • Resident employed population (20 - 64 years) by nationality and maximum schooling attainment | As a percentage of total population of the respective nationality | C123: TED.C.G1!A$11
A124: =HYPERLINK("#"&C124,INDIRECT(C124)) -> Gráfico C1.2 • Pirâmide etária da população estrangeira empregada em Portugal, por nível máximo de ensino atingido | Número de indivíduos e percentagem com cada nível de ensino | C124: TED.C.G2!A$10
A125: =HYPERLINK("#"&C125,INDIRECT(C125)) -> Chart C1.2 • Age pyramid of foreign population employed in Portugal by maximum schooling attainment | Number of individuals and their percentage at each level of schooling attainment | C125: TED.C.G2!A$11
A126: =HYPERLINK("#"&C126,INDIRECT(C126)) -> Gráfico C1.3 • Pirâmide etária da população portuguesa empregada em Portugal, por nível máximo de ensino atingido | Número de indivíduos em cada nível de ensino | C126: TED.C.G3!A$10
A127: =HYPERLINK("#"&C127,INDIRECT(C127)) -> Chart C1.3 • Age pyramid of Portuguese population employed in Portugal by maximum schooling attainment | Number of persons at each level of schooling attainment | C127: TED.C.G3!A$11
A128: =HYPERLINK("#"&C128,INDIRECT(C128)) -> Gráfico C1.4 • População empregada (15 ou mais anos) estrangeira e portuguesa por setor de atividade e nível máximo de ensino | Percentagem do total de cada setor em cada nacionalidade | C128: TED.C.G4!A$10
A129: =HYPERLINK("#"&C129,INDIRECT(C129)) -> Chart C1.4 • Foreign and Portuguese employed population (15 and more years) by sector of activity and maximum schooling attainment | Percentage of each sector in the respective nationality | C129: TED.C.G4!A$11
A130: =HYPERLINK("#"&C130,INDIRECT(C130)) -> Quadro C1.1 • População estrangeira empregada (15 ou mais anos), por nacionalidade e nível máximo de ensino | Número de indivíduos e distribuição por nível de ensino em percentagem | C130: TED.C.Q1!A$10
A131: =HYPERLINK("#"&C131,INDIRECT(C131)) -> Table C1.1 • Foreign employed population (15 or more years) by nationality and maximum schooling attainment | Total number of individuals and breakdown as a percentage of each educational level for each nationality | C131: TED.C.Q1!A$11
...

Sheet QI.1.1
A5: Índice/Contents
A6: Boletim Económico - junho 2024/Economic Bulletin - June 2024
A7: =+Índice!$A$7 -> Parte I. Projeções para a economia portuguesa: 2024-26/Part I. Projections for the Portuguese economy: 2024-26
A10: Quadro I.1.1 • Projeções do Banco de Portugal para 2024-26 | Taxa de variação anual, em percentagem (exceto onde indicado)
A11: Table I.1.1 • Projections of Banco de Portugal for 2024-26| Annual rate of change, in percentage (unless otherwise stated)
A13: Unidade/Unit | C13: % | E13: % | F13: % | G13: % | H13: % | J13: % | K13: % | L13: % | M13: %
C14: Pesos | E14: BE Junho 2024 | J14: BE março 2023
C15: Weights | E15: EB June 2024 | J15: EB March 2023
C16: 2023 | E16: 2023 | F16: 2024(p) | G16: 2025(p) | H16: 2026(p) | J16: 2023 | K16: 2024(p) | L16: 2025(p) | M16: 2026(p)
A18: Produto interno bruto | B18: Gross domestic product | C18: 100 | E18: 2.2612549 | F18: 2.0372004 | G18: 2.2937181 | H18: 2.2337036 | J18: 2.28052 | K18: 2.0459739 | L18: 2.2967685 | M18: 2.2083861
A20: Consumo privado | B20: Private consumption | C20: 62.58191 | E20: 1.6617568 | F20: 1.9717615 | G20: 1.9311053 | H20: 1.8154847 | J20: 1.6336574 | K20: 2.0820899 | L20: 1.925106 | M20: 1.826615
A21: Consumo público | B21: Public consumption | C21: 16.996436 | E21: 1.0266231 | F21: 0.96740315 | G21: 0.87291352 | H21: 0.76134258 | J21: 1.2415149 | K21: 1.1926705 | L21: 0.877828 | M21: 0.92772281
A22: Formação bruta de capital fixo | B22: Gross fixed capital formation | C22: 19.386689 | E22: 2.549435 | F22: 3.2525603 | G22: 6.0710454 | H22: 4.9521543 | J22: 2.4401542 | K22: 3.6218192 | L22: 5.4391424 | M22: 4.119236
A23: Procura interna | B23: Domestic demand | C23: 99.167649 | E23: 1.4219138 | F23: 2.0924277 | G23: 2.5494514 | H23: 2.2508795 | J23: 1.4102447 | K23: 2.3656595 | L23: 2.4059002 | M23: 2.1184762
A24: Exportações | B24: Exports | C24: 47.441435 | E24: 4.1133954 | F24: 4.1742382 | G24: 3.7089045 | H24: 3.421961 | J24: 4.1830157 | K24: 3.5118923 | L24: 4.0090788 | M24: 3.2996928
A25: Importações | B25: Imports | C25: 46.609083 | E25: 2.2310907 | F25: 4.3102589 | G25: 4.2879151 | H25: 3.4617254 | J25: 2.2315081 | K25: 4.2144287 | L25: 4.2560516 | M25: 3.1101558
A27: Emprego (a) | B27: Employment (a) | E27: 0.8631955 | F27: 1.0084136 | G27: 0.81855017 | H27: 0.82481965 | J27: 0.8631955 | K27: 0.69846792 | L27: 0.58508385 | M27: 0.45415575
A28: Taxa de desemprego (b) | B28: Unemployment rate (b) | E28: 6.5091485 | F28: 6.5055283 | G28: 6.5640297 | H28: 6.5754342 | J28: 6.5091485 | K28: 6.5148295 | L28: 6.4592335 | M28: 6.4636811
A30: Balança corrente e de capital (% PIB) | B30: Current and capital account (% of GDP) | E30: 2.7280503 | F30: 4.3549206 | G30: 4.3898441 | H30: 4.5446319 | J30: 2.7255972 | K30: 3.595957 | L30: 3.8835519 | M30: 4.08046
A31: Balança de bens e serviços (% PIB) | B31: Trade balance (% of GDP) | E31: 1.2338337 | F31: 2.3555582 | G31: 1.8443429 | H31: 2.0570994 | J31: 1.2327243 | K31: 1.1249379 | L31: 1.2303927 | M31: 1.4790873
A33: Índice harmonizado de preços no consumidor | B33: Harmonised index of consumer prices | E33: 5.2642832 | F33: 2.4906724 | G33: 2.0875933 | H33: 1.9766928 | J33: 5.2642832 | K33: 2.3577992 | L33: 1.9997807 | M33: 1.9371263
A34: Bens energéticos | B34: Energy | E34: -8.9092019 | F34: 1.9157348 | G34: 0.36758997 | H34: -0.64928961 | J34: -8.9092019 | K34: 3.6141984 | L34: 2.1580193 | M34: 0.58776934
A35: Bens alimentares | B35: Food | E35: 9.2039871 | F35: 3.1165032 | G35: 1.8286636 | H35: 1.6695415 | J35: 9.2039871 | K35: 3.0211879 | L35: 1.2980433 | M35: 1.5113193
A36: Excluindo bens energéticos | B36: Excluding energy | E36: 6.5476591 | F36: 2.5256115 | G36: 2.1940549 | H36: 2.13566 | J36: 6.5476591 | K36: 2.2791734 | L36: 1.9902956 | M36: 2.022027
A37: Excluindo bens energéticos e alimentares | B37: Excluding energy and food | E37: 5.3698003 | F37: 2.3197031 | G37: 2.3174846 | H37: 2.2952439 | J37: 5.3698003 | K37: 2.0207849 | L37: 2.2275851 | M37: 2.1964871
A39: Saldo orçamental (% PIB) | B39: Budget Balance (% of GDP) | E39: 1.202813 | F39: 1.0381781 | G39: 0.77930605 | H39: 0.64383201 | J39: - | K39: - | L39: - | M39: -
A40: Dívida Pública (% PIB) | B40: Public Debt (% GDP) | E40: 99.089226 | F40: 92.486423 | G40: 87.220414 | H40: 82.658473 | J40: - | K40: - | L40: - | M40: -
A42: Fontes: Banco de Portugal e INE. | Notas: (p) – projetado. As atuais projeções enquadram-se no exercício de projeção do Eurosistema de junho de 2024, com fecho de dados a 21 de maio e divulgado no dia 6 de junho. A projeção corresponde ao valor mais provável condicional ao conjunto de hipóteses consideradas. Pesos a preços correntes. (a) De acordo com o conceito de Contas Nacionais. (b) Em percentagem da população ativa.
A43: Sources: Banco de Portugal and Statistics Portugal. | Notes: (p) – projected. The current projections are part of the Eurosystem projection exercise of June 2024, with cut-off date for macroeconomic projections on May 21 and released on June 6. For each aggregate, this table shows the projection corresponding to the most likely value, conditional on the set of assumptions. (a) According to the national accounts concept. (b) In percentage of the labour force.

Sheet GI.1.1
A5: Índice/Contents
A6: Boletim Económico - junho 2024/Economic Bulletin - June 2024
A7: Parte I. Projeções para a economia portuguesa: 2024-26/Part I. Projections for the Portuguese economy: 2024-26
A10: Gráfico I.1.1 • PIB em Portugal e na área do euro
A11: Chart I.1.1 • GDP in Portugal and the euro area
A13: Unidade/Unit | B13: Índice 2019=100 | C13: Índice 2019=100 | D13: Índice 2019=100 | E13: Índice 2019=100 | F13: Índice 2019=100
B14: Index 2019=100 | C14: Index 2019=100 | D14: Index 2019=100 | E14: Index 2019=100 | F14: Index 2019=100
B16: Portugal | C16: Área do euro | D16: Mediana | E16: Intervalo interquartis
B17: Portugal | C17: Euro area | D17: Median | E17: Interquartile range
A18: 2019 | B18: 100 | C18: 100 | D18: 100 | E18: 100 | F18: 100
A19: 2020 | B19: 91.699484 | C19: 93.751694 | D19: 95.780866 | E19: 91.807287 | F19: 96.913746
A20: 2021 | B20: 96.960684 | C20: 99.271803 | D20: 101.66986 | E20: 98.430375 | F20: 104.26066
A21: 2022 | B21: 103.58068 | C21: 102.72392 | D21: 105.05827 | E21: 102.4386 | F21: 107.96164
A22: 2023 | B22: 105.92291 | C22: 103.30683 | D22: 105.819 | E22: 102.72625 | F22: 108.04658
A23: 2024 (p) | B23: 108.08077 | C23: 104.21247 | D23: 107.71928 | E23: 103.79074 | F23: 110.58718
A24: 2025 (p) | B24: 110.55984 | C24: 105.71737 | D24: 110.45496 | E24: 105.8614 | F24: 113.568
A25: 2026 (p) | B25: 113.02942 | C25: 107.38992 | D25: 113.07755 | E25: 108.08874 | F25: 116.84822
A28: Fonte: Eurosistema (exercício de projeção de junho de 2024). | Notas: (p) — projetado. A mediana e o intervalo interquartis referem-se aos 20 países que compõem a área do euro.
A29: Sources: Banco de Portugal and Statistics Portugal. | Notes: (p) – projected. The median and interquartile range refer to the 20 countries that make up the euro area.

Sheet GI.1.2
A5: Índice/Contents
A6: Boletim Económico - junho 2024/Economic Bulletin - June 2024
A7: Parte I. Projeções para a economia portuguesa: 2024-26/Part I. Projections for the Portuguese economy: 2024-26
A10: Gráfico I.1.2 • Projeções trimestrais para o PIB e para a inflação
A11: Chart I.1.2 • Quarterly GDP and inflation projections
A13: Unidade/Unit | C13: % | D13: % | E13: % | F13: % | G13: % | H13: % | I13: % | J13: % | K13: % | L13: % | M13: % | N13: % | O13: % | P13: % | Q13: % | R13: %
C14: 2023 T1 | D14: 2023 T2 | E14: 2023 T3 | F14: 2023 T4 | G14: 2024 T1 | H14: 2024 T2 | I14: 2024 T3 | J14: 2024 T4 | K14: 2025 T1 | L14: 2025 T2 | M14: 2025 T3 | N14: 2025 T4 | O14: 2026 T1 | P14: 2026 T2 | Q14: 2026 T3 | R14: 2026 T4
C15: 2023 Q1 | D15: 2023 Q2 | E15: 2023 Q3 | F15: 2023 Q4 | G15: 2024 Q1 | H15: 2024 Q2 | I15: 2024 Q3 | J15: 2024 Q4 | K15: 2025 Q1 | L15: 2025 Q2 | M15: 2025 Q3 | N15: 2025 Q4 | O15: 2026 Q1 | P15: 2026 Q2 | Q15: 2026 Q3 | R15: 2026 Q4
A17: Painel A - PIB - taxa de variação em cadeia | Percentagem | B17: Panel A - GDP - quarter-on-quarter rate of change | Percentage
A18: BE de Junho | B18: June EB | C18: 1.46429 | D18: 0.10359565 | E18: -0.22753633 | F18: 0.72057319 | G18: 0.68377563 | H18: 0.60021211 | I18: 0.59382077 | J18: 0.55435084 | K18: 0.6346271 | L18: 0.50438703 | M18: 0.54991071 | N18: 0.49654165 | O18: 0.52484377 | P18: 0.61664429 | Q18: 0.60668882 | R18: 0.60211556
A19: BE de Março | B19: March EB | C19: 1.460228 | D19: 0.087780531 | E19: -0.19607811 | F19: 0.79644871 | G19: 0.66983929 | H19: 0.55876798 | I19: 0.56552396 | J19: 0.55192475 | K19: 0.59769204 | L19: 0.58541301 | M19: 0.56310902 | N19: 0.49053571 | O19: 0.52966022 | P19: 0.58876109 | Q19: 0.57612743 | R19: 0.54041728
A21: Painel B - IHPC - taxa de variação homóloga | Percentagem | B21: Panel B - HICP - Year-on-year rate of change | Percentage | C21: 8.394319 | D21: 5.6535438 | E21: 4.8143413 | F21: 2.4454348 | G21: 2.4631669 | H21: 2.7491851 | I21: 2.3332742 | J21: 2.4171617 | K21: 1.9717338 | L21: 2.0294944 | M21: 2.2006849 | N21: 2.1452244 | O21: 2.0621914 | P21: 1.9488066 | Q21: 1.913581 | R21: 1.9848899
A22: BE de Junho | B22: June EB | C22: 8.394319 | D22: 5.6535438 | E22: 4.8143413 | F22: 2.4454348 | G22: 2.3345525 | H22: 2.6090358 | I22: 2.2353349 | J22: 2.2522741 | K22: 1.9240392 | L22: 1.8929787 | M22: 2.0596441 | N22: 2.1206954 | O22: 2.0855065 | P22: 1.9645688 | Q22: 1.8761986 | R22: 1.8264064
A23: BE de Março | B23: March EB
A26: Fontes: Banco de Portugal e INE. | Nota: As linhas a tracejado correspondem aos valores projetados nos BE de março e junho de 2024.
A27: Sources: Banco de Portugal and Statistics Portugal. | Note: The dashed lines correspond to the projected values in the EB of March and June 2024.

Sheet GI.1.3
A5: Índice/Contents
A6: Boletim Económico - junho 2024/Economic Bulletin - June 2024
A7: Parte I. Projeções para a economia portuguesa: 2024-26/Part I. Projections for the Portuguese economy: 2024-26
A10: Gráfico I.1.3 • Taxa de variação do PIB e contributos líquidos de conteúdos importados das componentes | Percentagem e pontos percentuais
A11: Chart I.1.3 • GDP rate of change and import-content net contributions of components | Percentage and percentage points
A13: Unidade/Unit | C13: % e pp | D13: % e pp | E13: % e pp | F13: % e pp | G13: % e pp | H13: % e pp | I13: % e pp
C14: % and pp | D14: % and pp | E14: % and pp | F14: % and pp | G14: % and pp | H14: % and pp | I14: % and pp
C16: 2015-2019 | D16: 2020-22 | F16: 2023 | G16: 2024 (p) | H16: 2025 (p) | I16: 2026 (p)
A18: PIB (em percentagem) | B18: GDP (percentage) | C18: 2.5699926 | D18: 1.4214771 | F18: 2.2612549 | G18: 2.0372004 | H18: 2.2937181 | I18: 2.2337036
A20: Exportações | B20: Exports | C20: 1.1442875 | D20: 0.81178613 | F20: 1.4230967 | G20: 0.94537747 | H20: 0.90067595 | I20: 0.88392726
A21: Investimento | B21: Investment | C21: 0.47522375 | D21: 0.1855418 | F21: 0.040863292 | G21: 0.29549085 | H21: 0.59525225 | I21: 0.51358366
A22: Consumo | B22: Consumption | C22: 0.97506987 | D22: 0.41528234 | F22: 0.79754734 | G22: 0.79925255 | H22: 0.79095605 | I22: 0.83619265
A25: Fontes: Banco de Portugal e INE. | Notas: (p) – projetado. Para informações sobre a metodologia de cálculo dos contributos líquidos de conteúdo importado, ver Cardoso e Rua (2021), “O real contributo da procura final para o crescimento do PIB”, Revista de Estudos Económicos do Banco de Portugal, Volume VII, nº 3.
A26: Sources: Banco de Portugal and Statistics Portugal. | Notes: (p) - projected. For information on the methodology for calculating import-content net contributions, see Cardoso and Rua (2021), “Unveiling the real contribution of final demand to GDP growth”, Banco de Portugal Economic Studies, Volume VII, no. 3.

Sheet GI.1.4
A5: Índice/Contents
A6: Boletim Económico - junho 2024/Economic Bulletin - June 2024
A7: Parte I. Projeções para a economia portuguesa: 2024-26/Part I. Projections for the Portuguese economy: 2024-26
A10: Gráfico I.1.4 • Consumo privado e rendimento disponível | Taxa de variação em percentagem e contributos para o rendimento disponível em pontos percentuais
A11: Chart I.1.4 • Private consumption and disposable income | Rate of change in percentage and contributions to disposable income in percentage points
A13: Unidade/Unit | C13: % e pp | D13: % e pp | E13: % e pp | F13: % e pp
C14: % and pp | D14: % and pp | E14: % and pp | F14: % and pp
C16: 2023 | D16: 2024 (p) | E16: 2025 (p) | F16: 2026 (p)
A19: Consumo privado nominal | B19: Nominal private consumption | C19: 6.8090786 | D19: 4.8407191 | E19: 4.1960294 | F19: 3.8345096
A20: Consumo privado em termos reais | B20: Private consumption in real terms | C20: 1.6617568 | D20: 1.9717615 | E20: 1.9311053 | F20: 1.8154847
A21: Deflator do consumo privado | B21: Private consumption deflator | C21: 5.063184 | D21: 2.8134824 | E21: 2.2220146 | F21: 1.9830234
A24: Rendimento disponível nominal | B24: Nominal disposable income | C24: 6.7787215 | D24: 6.8715616 | E24: 4.4755807 | F24: 3.7971855
A25: Contributo remunerações | B25: Contribution of compensation of employees | C25: 7.2992447 | D25: 4.8457656 | E25: 3.2026148 | F25: 3.1449428
A26: Contributo transferências internas | B26: Contribution of domestic transfers | C26: 1.4778004 | D26: 2.4164908 | E26: 1.282741 | F26: 0.96175666
A27: Contributo impostos diretos | B27: Contribution of direct taxes | C27: -1.0114927 | D27: -0.081449999 | E27: -0.39470355 | F27: -0.52377138
A28: Contributo outras componentes do rend. disponível | B28: Contribution of other disposable income components | C28: -0.98683088 | D28: -0.30924475 | E28: 0.38492851 | F28: 0.2142574
A29: Por memória: rendimento disponível real | B29: Memo: real disposable income | C29: 1.6328627 | D29: 3.9470302 | E29: 2.20458 | F29: 1.7788863
A34: Fontes: Banco de Portugal e INE. | Nota: (p) – projetado.
A35: Sources: Banco de Portugal and Statistics Portugal. | Note: (p) - projected.

Sheet GI.1.5
A5: Índice/Contents
A6: Boletim Económico - junho 2024/Economic Bulletin - June 2024
A7: Parte I. Projeções para a economia portuguesa: 2024-26/Part I. Projections for the Portuguese economy: 2024-26
A10: Gráfico I.1.5 • FBCF e componentes| Taxa de variação em percentagem
A11: Chart I.1.5 • GFCF and components| Rate of change in percentage
A13: Unidade/Unit | C13: % | D13: % | E13: % | F13: %
C16: 2023 | D16: 2024 (p) | E16: 2025 (p) | F16: 2026 (p)
A19: FBCF Total | B19: Total GFCF | C19: 2.549435 | D19: 3.2525603 | E19: 6.0710454 | F19: 4.9521543
A20: FBCF Pública | B20: Public GFCF | C20: 12.52833 | D20: 20.346989 | E20: 13.262595 | F20: 8.0639918
A21: FBCF Habitação | B21: Housing GFCF | C21: -1.0551081 | D21: -0.81162725 | E21: 1.7854008 | F21: 2.3257094
A22: FBCF Empresarial | B22: Business GFCF | C22: 1.7283411 | D22: 1.0606807 | E22: 5.4394936 | F22: 4.7732565
A29: Fontes: Banco de Portugal e INE. | Nota: (p) – projetado.
A30: Sources: Banco de Portugal and Statistics Portugal. | Note: (p) - projected.

Sheet GI.1.6
A5: Índice/Contents
A6: Boletim Económico - junho 2024/Economic Bulletin - June 2024
A7: Parte I. Projeções para a economia portuguesa: 2024-26/Part I. Projections for the Portuguese economy: 2024-26
A10: Gráfico I.1.6 • Comércio de bens e serviços | Taxa de variação em percentagem e contributos em pontos percentuais
A11: Chart I.1.6 • Trade in goods and services | Rate of change in percentage and contributions in percentage points
A13: Unidade/Unit | C13: % e pp | D13: % e pp | E13: % e pp | F13: % e pp
C14: % and pp | D14: % and pp | E14: % and pp | F14: % and pp
C16: 2023 | D16: 2024 (p) | E16: 2025 (p) | F16: 2026 (p)
A17: Painel A - Exportações de bens e serviços e componentes | B17: Panel A - Exports of goods and services and components
A19: Exportações de bens e serviços | B19: Exports of goods and services | C19: 4.1133954 | D19: 4.1742382 | E19: 3.7089045 | F19: 3.421961
A20: Bens | B20: Goods | C20: -0.18948561 | D20: 2.274322 | E20: 2.1394914 | F20: 2.0219345
A21: Serviços | B21: Services | C21: 4.302881 | D21: 1.8999162 | E21: 1.5694131 | F21: 1.4000266
A23: Por memória: procura externa de bens e serviços | B23: Memo: external demand for goods and services | C23: -0.50294917 | D23: 1.1456917 | E23: 3.1877117 | F23: 3.2420058
A26: Painel B - Importações de bens e serviços e componentes | B26: Panel B - Imports of goods and services and components
A28: Importações de bens e serviços | B28: Imports of goods and services | C28: 2.2310907 | D28: 4.3102589 | E28: 4.2879151 | F28: 3.4617254
A29: Bens | B29: Goods | C29: 1.2143785 | D29: 3.8978697 | E29: 3.4036396 | F29: 2.8066901
A30: Serviços | B30: Services | C30: 1.0167123 | D30: 0.41238915 | E30: 0.8842755 | F30: 0.65503522
A34: Fontes: Banco de Portugal e INE. | Notas: (p) — projetado. O indicador de procura externa dirigida à economia portuguesa consiste numa média das importações dos parceiros comerciais, ponderadas pelo seu peso nas exportações portuguesas.
A35: Sources: Banco de Portugal and Statistics Portugal. | Notes: (p) - projected. The indicator of external demand for the Portuguese economy consists of an average of imports of trading partners, weighted by their share in Portuguese exports.

Sheet GI.1.7
A5: Índice/Contents
A6: Boletim Económico - junho 2024/Economic Bulletin - June 2024
A7: Parte I. Projeções para a economia portuguesa: 2024-26/Part I. Projections for the Portuguese economy: 2024-26
A10: Gráfico I.1.7 • IHPC observado | Taxa de variação homóloga em percentagem e contributos em pontos percentuais
A11: Chart I.1.7 • Observed HICP | Rate of change in percentage and contributions in percentage points
A13: Unidade/Unit | D13: pp | E13: pp | F13: pp | G13: pp | H13: %
D14: Energéticos | E14: Componentes voláteis associadas com o turismo | F14: Alto conteúdo importado | G14: Baixo conteúdo importado | H14: Total
D15: Energy | E15: Volatile components associated with tourism | F15: High import content | G15: Low import content | H15: Total
C17: 2021 T1 | D17: -0.11209262 | E17: -0.37285267 | F17: 0.29833102 | G17: 0.38213257 | H17: 0.1955183
C18: 2021 T2 | D18: 0.67544827 | E18: -1.6641169 | F18: 0.35712092 | G18: 0.56866183 | H18: -0.062885901
C19: 2021 T3 | D19: 0.75781326 | E19: -0.4592732 | F19: 0.3856595 | G19: 0.54777734 | H19: 1.2319769
C20: 2021 T4 | D20: 1.0244034 | E20: 0.19071791 | F20: 0.61950868 | G20: 0.58221659 | H20: 2.4168465
C21: 2022 T1 | D21: 1.2576848 | E21: 0.21202919 | F21: 1.9854147 | G21: 0.96378244 | H21: 4.4189111
C22: 2022 T2 | D22: 2.2509772 | E22: 1.0593612 | F22: 3.7851245 | G22: 1.0740176 | H22: 8.1694805
C23: 2022 T3 | D23: 2.0653286 | E23: 1.4654284 | F23: 4.8478054 | G23: 1.1495937 | H23: 9.5281561
C24: 2022 T4 | D24: 1.9624682 | E24: 0.862034 | F24: 6.0300666 | G24: 1.3502584 | H24: 10.204827
C25: 2023 T1 | D25: 0.20219231 | E25: 0.55039527 | F25: 5.9782067 | G25: 1.6685283 | H25: 8.3993225
C26: 2023 T2 | D26: -1.3296388 | E26: 1.5941982 | F26: 3.6877743 | G26: 1.6992299 | H26: 5.6515635
C27: 2023 T3 | D27: -0.72155623 | E27: 1.487275 | F27: 2.2554361 | G27: 1.792628 | H27: 4.8137828
C28: 2023 T4 | D28: -0.97902871 | E28: 0.69338929 | F28: 1.1005282 | G28: 1.6330589 | H28: 2.4479476
C29: 2024 T1 | D29: 0.17771255 | E29: 0.40964432 | F29: 0.10677144 | G29: 1.7673255 | H29: 2.4614538
A35: Fontes: Banco de Portugal e INE. | Notas: O conteúdo importado inclui o conteúdo direto e indireto do consumo privado em 2017. As rubricas do IHPC de elevado conteúdo importado correspondem às que se caraterizam por um conteúdo importado estimado superior a 20% na despesa de consumo. Para mais pormenores sobre o cálculo do IHPC por nível de conteúdo importado, ver o Boletim Económico de junho de 2022.
A36: Sources: Banco de Portugal and Statistics Portugal. | Notes: Import content includes the direct and indirect content of private consumption in 2017. HICP items with a high import content correspond to those with an estimated import content of more than 20% of consumption expenditure. For more details on calculating the HICP by level of import content, see the June 2022 Economic Bulletin.

Sheet GC.1.1
A5: Índice/Contents
A6: Boletim Económico - junho 2024/Economic Bulletin - June 2024
A10: Gráfico C1.1 • IHPC e indicador PMI para o preço dos inputs na área do euro | Taxa de variação em cadeia anualizada sobre dados corrigidos de variações sazonais e em média móvel de 3 meses
A11: Chart B1.1 • HICP and PMI indicator for the price of inputs in the euro area | Annualized quarter-on-quarter variation rate of 3-month moving average and seasonally adjusted data
A13: Unidade/Unit | C13: Taxa de variação em cadeia anualizada sobre dados corrigidos de variações sazonais e em média móvel de 3 meses /Annualized quarter-on-quarter variation rate of 3-month moving average and seasonally adjusted data
C15: Painel A - Bens excluindo alimentares e energéticos | F15: Painel B - Serviços
C16: Panel A - Goods excluding food and energy | F16: Panel B - Services
C18: IHPC - bens exc. alim. e energ. | D18: Média 2014-19 | E18: PMI - preço dos inputs na indústria (t-10) | F18: IHPC - serviços | G18: Média 2014-19 | H18: PMI - preço dos inputs nos serviços (t-6)
C19: HICP - goods exc. food and energy | D19: Average 2014-19 | E19: PMI - input prices in manufacturing (t-10) | F19: HICP - services | G19: Average 2014-20 | H19: PMI - input prices in services (t-6)
A20: 43831 | B20: 43831 | C20: 0.45658261 | D20: 0.29589648 | E20: 1.3233447 | F20: 0.94476582 | G20: 1.411748 | H20: 1.3654098
A21: 43862 | B21: 43862 | C21: 0.034011531 | D21: 0.29589648 | E21: 1.3880214 | F21: 0.80616159 | G21: 1.411748 | H21: 1.3989188
A22: 43891 | B22: 43891 | C22: -0.15914057 | D22: 0.29589648 | E22: 1.1680564 | F22: 0.35890392 | G22: 1.411748 | H22: 1.1968411
A23: 43922 | B23: 43922 | C23: 0.46843921 | D23: 0.29589648 | E23: 0.69689858 | F23: 0.68855991 | G23: 1.411748 | H23: 1.5055281
A24: 43952 | B24: 43952 | C24: 0.75936614 | D24: 0.29589648 | E24: 0.44543534 | F24: 0.58370302 | G24: 1.411748 | H24: 1.3991711
A25: 43983 | B25: 43983 | C25: 0.35109787 | D25: 0.29589648 | E25: 0.50051721 | F25: 1.1460347 | G25: 1.411748 | H25: 1.361361
A26: 44013 | B26: 44013 | C26: 1.4459925 | D26: 0.29589648 | E26: 0.44923701 | F26: 0.63313724 | G26: 1.411748 | H26: 1.5604505
A27: 44044 | B27: 44044 | C27: 0.55311533 | D27: 0.29589648 | E27: 0.061821181 | F27: 0.43647103 | G27: 1.411748 | H27: 1.3890758
A28: 44075 | B28: 44075 | C28: 0.43315059 | D28: 0.29589648 | E28: 0.097314466 | F28: -0.43886947 | G28: 1.411748 | H28: -0.1345115
A29: 44105 | B29: 44105 | C29: -3.0418966 | D29: 0.29589648 | E29: 0.25870921 | F29: -0.22243993 | G29: 1.411748 | H29: -1.2518741
A30: 44136 | B30: 44136 | C30: -1.997955 | D30: 0.29589648 | E30: 0.34767548 | F30: 0.14474396 | G30: 1.411748 | H30: -0.56436952
A31: 44166 | B31: 44166 | C31: -1.6091008 | D31: 0.29589648 | E31: 0.57243627 | F31: 1.1338766 | G31: 1.411748 | H31: 0.40067825
... A71: 45383 | B71: 45383 | C71: 0.82524938 | D71: 0.29589648 | E71: -0.54710758 | F71: 5.3012967 | G71: 1.411748 | H71: 2.5153871
A72: 45413 | B72: 45413 | D72: 0.29589648 | E72: -1.0901594 | G72: 1.411748 | H72: 2.6259844
A73: 45444 | B73: 45444 | D73: 0.29589648 | E73: -0.5142925 | G73: 1.411748 | H73: 2.4225253
A74: 45474 | B74: 45474 | D74: 0.29589648 | E74: -0.20106058 | G74: 1.411748 | H74: 2.6345504
A75: 45505 | B75: 45505 | D75: 0.29589648 | E75: -0.10524747 | G75: 1.411748 | H75: 2.7057783
A76: 45536 | B76: 45536 | D76: 0.29589648 | E76: -0.082660827 | G76: 1.411748 | H76: 2.3964694
A77: 45566 | B77: 45566 | D77: 0.29589648 | E77: -0.015605472 | G77: 1.411748 | H77: 2.4411968
A78: 45597 | B78: 45597 | D78: 0.29589648 | E78: -0.057620984 | G78: 1.411748
A79: 45627 | B79: 45627 | D79: 0.29589648 | E79: 0.33297148 | G79: 1.411748
A83: Fontes: Eurostat e S&P Global (cálculos do Banco de Portugal).| Notas: A taxa de variação em cadeia da média móvel a 3 meses considera informação do IHPC corrigido de variações sazonais num período de 6 meses, correspondendo à variação da média dos últimos 3 meses sobre a média do período de 3 meses imediatamente anterior. Os indicadores PMI para os preços dos inputs da indústria e dos serviços sofreram uma alteração de escala de maneira a apresentarem a mesma média e desvio-padrão do indicador de inflação subjacente correspondente, e foram desfasados 10 e 6 meses, respetivamente.
A84: Sources: Eurostat and S&P Global (Banco de Portugal calculations).| Notes: The quarter-on-quarter variation rate of the 3-month moving average considers information from the seasonally adjusted HIPC over a period of six months, corresponding to the variation of the average of the last 3 months over the average of the immediately preceding 3-month period. The scale of PMI indicators for input prices in manufacturing and services was changed so that they present the mean and standard deviation of the corresponding underlying inflation indicator, and were lagged by 10 and 6 months, respectively.

Sheet GC.1.2
A5: Índice/Contents
A6: Boletim Económico - junho 2024/Economic Bulletin - June 2024
A7: Caixa 1- Enquadramento e políticas/Box 1-External environment, financing conditions and policies
A10: Gráfico C1.2 • Hipóteses do exercício de projeção para o preço da energia e das outras matérias-primas e para a taxa de juro de curto prazo
A11: Chart B1.2 • Projection assumptions for the prices of energy and other commodities, and the short-term interest rate
A13: Unidade/Unit | C13: EUR/MWh | F13: 2005=100 | I13: Percentagem/Percentage
C14: Painel A - Indicador sintético do preço da energia (petróleo e gás) | F14: Painel B - Preço das matérias-primas exceto energia | I14: Painel C - Taxa de juro EURIBOR a 3 meses
C15: Panel A - Synthetic energy price index (oil and gas) | F15: Panel B - Non-oil commodity prices | I15: Panel C - Short-term interest rate (3-month EURIBOR)
C17: Observado | D17: 45444 | E17: 45352 | F17: Observado | G17: 45444 | H17: 45352 | I17: Observado | J17: 45444 | K17: 45352
C18: Observed | D18: 45444 | E18: 45352 | F18: Observed | G18: 45444 | H18: 45352 | I18: Observed | J18: 45444 | K18: 45352
A19: 2019Q1 | B19: 2019T1 | C19: 27.841998 | F19: -0.30856132 | I19: 152.84668
A20: 2019Q2 | B20: 2019T2 | C20: 28.467829 | F20: -0.31706087 | I20: 152.06765
A21: 2019Q3 | B21: 2019T3 | C21: 25.124432 | F21: -0.3967076 | I21: 149.86049
A22: 2019Q4 | B22: 2019T4 | C22: 26.87872 | F22: -0.40305176 | I22: 152.23398
A23: 2020Q1 | B23: 2020T1 | C23: 21.206444 | F23: -0.40542299 | I23: 151.28747
A24: 2020Q2 | B24: 2020T2 | C24: 11.608262 | F24: -0.29965152 | I24: 140.98916
A25: 2020Q3 | B25: 2020T3 | C25: 17.059312 | F25: -0.47173612 | I25: 151.24808
A26: 2020Q4 | B26: 2020T4 | C26: 19.310684 | F26: -0.52275146 | I26: 164.61918
A27: 2021Q1 | B27: 2021T1 | C27: 25.987589 | F27: -0.54241153 | I27: 189.86087
A28: 2021Q2 | B28: 2021T2 | C28: 30.773076 | F28: -0.54038023 | I28: 211.90862
A29: 2021Q3 | B29: 2021T3 | C29: 40.882759 | F29: -0.54581818 | I29: 208.12883
A30: 2021Q4 | B30: 2021T4 | C30: 59.304426 | F30: -0.56637656 | I30: 223.83696
... A37: 2023Q3 | B37: 2023T3 | C37: 42.346609 | F37: 3.7773872 | I37: 204.97402
A38: 2023Q4 | B38: 2023T4 | C38: 44.994272 | E38: 44.994272 | F38: 3.957456 | H38: 3.9574559 | I38: 206.60089 | K38: 206.60089
A39: 2024Q1 | B39: 2024T1 | C39: 39.674179 | D39: 39.674179 | E39: 39.587113 | F39: 3.9233789 | G39: 3.9233789 | H39: 3.8882558 | I39: 213.7639 | J39: 213.7639 | K39: 210.39182
A40: 2024Q2 | B40: 2024T2 | D40: 41.24095 | E40: 38.587038 | G40: 3.7860828 | H40: 3.6533334 | J40: 244.38704 | K40: 213.19501
A41: 2024Q3 | B41: 2024T3 | D41: 40.404486 | E41: 38.325443 | G41: 3.5433333 | H41: 3.2650001 | J41: 244.87525 | K41: 215.02333
A42: 2024Q4 | B42: 2024T4 | D42: 41.124661 | E42: 38.972014 | G42: 3.3 | H42: 2.905 | J42: 245.63615 | K42: 216.0122
A43: 2025Q1 | B43: 2025T1 | D43: 41.293964 | E43: 39.156598 | G43: 3.0716667 | H43: 2.635 | J43: 246.32097 | K43: 217.16582
A44: 2025Q2 | B44: 2025T2 | D44: 40.014927 | E44: 37.594223 | G44: 2.8833333 | H44: 2.4583333 | J44: 246.98356 | K44: 218.14476
A45: 2025Q3 | B45: 2025T3 | D45: 39.589631 | E45: 37.228874 | G45: 2.735 | H45: 2.3633332 | J45: 247.13657 | K45: 218.62221
A46: 2025Q4 | B46: 2025T4 | D46: 39.72359 | E46: 37.554342 | G46: 2.6233333 | H46: 2.3266666 | J46: 246.96319 | K46: 218.61891
A47: 2026Q1 | B47: 2026T1 | D47: 39.484 | E47: 37.50952 | G47: 2.5466667 | H47: 2.3266666 | J47: 248.3282 | K47: 219.21739
A48: 2026Q2 | B48: 2026T2 | D48: 36.425942 | E48: 35.684802 | G48: 2.4916667 | H48: 2.3399999 | J48: 249.76848 | K48: 219.38578
A49: 2026Q3 | B49: 2026T3 | D49: 35.856528 | E49: 35.289878 | G49: 2.455 | H49: 2.3616667 | J49: 249.52932 | K49: 218.26943
A50: 2026Q4 | B50: 2026T4 | D50: 36.308355 | E50: 35.69152 | G50: 2.4283333 | H50: 2.3833334 | J50: 248.5453 | K50: 216.28695
A53: Fontes: Eurosistema e Refinitiv (cálculos do Banco de Portugal).| Notas: As linhas a tracejado englobam o período posterior ao último trimestre completo aquando da data de fecho das hipóteses técnicas do exercício de projeção. As hipóteses técnicas para o preço do petróleo, do gás e das outras matérias-primas assentam nos mercados de futuros. O indicador sintético do preço da energia é uma média ponderada dos preços do petróleo e gás, ambos expressos em EUR/MWh (com ponderadores para Portugal baseados nas importações líquidas respetivas).
A54: Sources: Eurosystem and Refinitiv (Banco de Portugal calculations)| Notes: The dashed lines encompass the period after the last complete quarter at the closing date of the technical assumptions of the projection exercise. Technical assumptions for the price of oil, gas and other raw materials are based on futures markets. The synthetic energy price indicator is a weighted average of oil and gas prices, both expressed in EUR/MWh (with weights for Portugal based on the respective net imports).

Sheet QC.1.1
A5: Índice/Contents
A6: Boletim Económico - junho 2024/Economic Bulletin - June 2024
A7: =+Índice!$A$25 -> Caixa 1- Enquadramento e políticas/Box 1-External environment, financing conditions and policies
A10: Quadro C1.1 • Hipóteses do exercício de projeção elaboradas por especialistas do Eurosistema
A11: Table B1.1 • Eurosystem staff projection assumptions
C13: Unidade | D13: Unit | E13: BE junho 2024 | H13: 0 | I13: Revisões face ao BE março 2024 | L13: 0
E14: EB june 2024 | H14: 0 | I14: Revisions from EB march 2024 | L14: 0
E15: 2023 | F15: 2024 | G15: 2025 | H15: 2026 | I15: 2023 | J15: 2024 | K15: 2025 | L15: 2026
A17: Enquadramento internacional | B17: International environment
A18: PIB mundial | B18: World GDP | C18: tva | D18: yoy | E18: 3.1256537 | F18: 3.0287717 | G18: 3.0497791 | H18: 3.0264887 | I18: 0.012372409 | J18: -0.0018379022 | K18: 0.011736794 | L18: -0.01079721
A19: PIB Área do euro | B19: Euro area GDP | C19: tva | D19: yoy | E19: 0.6 | F19: 0.9 | G19: 1.4 | H19: 1.6 | I19: 0.1 | J19: 0.3 | K19: -0.1 | L19: 0
A20: Comércio mundial | B20: World trade | C20: tva | D20: yoy | E20: 0.42176308 | F20: 2.1087043 | G20: 3.2602987 | H20: 3.2444834 | I20: -0.13572421 | J20: -0.2171852 | K20: 0.12956244 | L20: 0.011620999
A21: Procura externa | B21: External demand | C21: tva | D21: yoy | E21: -0.50294917 | F21: 1.1456917 | G21: 3.1877117 | H21: 3.2420058 | I21: -0.041222018 | J21: -0.36993393 | K21: 0.10085887 | L21: 0.088708076
A23: Preços internacionais | B23: International prices
A24: Preço do petróleo | B24: Oil prices | C24: vma | D24: aav | E24: 77.451136 | F24: 77.655042 | G24: 72.43214 | H24: 69.159677 | I24: -1.358346e-08 | J24: 3.9057143 | K24: 3.0998379 | L24: 2.3192418
A25: Preço do gás (MWh) | B25: Gas prices (MWh) | C25: vma | D25: aav | E25: 40.613095 | F25: 30.819706 | G25: 35.41265 | H25: 29.93865 | I25: 0 | J25: 0.83352532 | K25: 3.325775 | L25: 0.39695833
A26: Matérias-primas não energéticas | B26: Non-oil commodity prices | C26: tva | D26: yoy | E26: -14.529652 | F26: 11.693508 | G26: 4.0838508 | H26: 0.88788605 | I26: 2.3293694e-05 | J26: 11.072042 | K26: 1.9859244 | L26: 0.8182233
A27: Preço de importação dos concorrentes | B27: Competitors' import prices | C27: tva | D27: yoy | E27: -1.5580303 | F27: 0.81989546 | G27: 2.6404624 | H27: 2.345748 | I27: -0.23227639 | J27: -0.18616241 | K27: -0.0029001823 | L27: -0.069877414
A29: Condições monetárias e financeiras | B29: Monetary and financial conditions
A30: Taxa de juro de curto prazo (EURIBOR a 3 meses) | B30: Short-term interest rate (3-month EURIBOR) | C30: % | D30: % | E30: 3.4307381 | F30: 3.6381988 | G30: 2.8283333 | H30: 2.4804167 | I30: -6.2496405e-05 | J30: 0.21030143 | K30: 0.38250007 | L30: 0.12750001
A31: Taxa de juro implícita da dívida pública | B31: Implicit interest rate in public debt | C31: % | D31: % | E31: 2.1480831 | F31: 2.4484075 | G31: 2.5102048 | H31: 2.5600957 | I31: 0.031099205 | J31: 0.11306572 | K31: 0.15573787 | L31: 0.15847761
A32: Índice de taxa de câmbio efetiva | B32: Effective exchange rate index | C32: tva | D32: yoy | E32: 4.8827669 | F32: 1.8102117 | G32: 0.10293139 | H32: 0 | I32: 2.1411594e-08 | J32: 0.74442455 | K32: 0.13682444 | L32: 0
A33: Taxa de câmbio euro-dólar | B33: Euro-dollar exchange rate | C33: vma | D33: aav | E33: 1.0813067 | F33: 1.0785848 | G33: 1.07661 | H33: 1.07661 | I33: 1.8853985e-10 | J33: -0.0022587525 | K33: -0.00337 | L33: -0.00337
A35: Fontes: Banco de Portugal e Eurosistema (cálculos do Banco de Portugal). | Notas: tva – taxa de variação anual, % – em percentagem, vma – valor médio anual, MWh – megawatt-hora. As hipóteses técnicas e de enquadramento externo e as projeções para o PIB e inflação da área do euro coincidem com as do exercício de projeção do Eurosistema divulgado a 6 de junho (ver “Projeções macroeconómicas para a área do euro elaboradas por especialistas do Eurosistema”, junho de 2024), incluindo a informação disponível até 21 de maio. Os preços internacionais são medidos em euros. A hipótese técnica para o preço do petróleo, gás e matérias-primas não energéticas assenta nos mercados de futuros. O preço de importação dos concorrentes corresponde a uma média ponderada dos deflatores de exportação dos países dos quais Portugal importa, ponderada pelo peso relativo nas importações portuguesas (para mais informação, ver “Trade consistency in the context of the Eurosystem projection exercises: an overview”, ECB Ocasional Paper 108, março de 2010). A evolução da taxa EURIBOR a 3 meses tem por base as expetativas implícitas nos contratos de futuros. A taxa de juro implícita da dívida pública é calculada como o rácio entre a despesa em juros do ano e a média simples do stock da dívida no final do ano e no final do ano anterior. Um aumento da taxa de câmbio corresponde a uma apreciação. O índice de taxa de câmbio efetiva do euro é calculado face a um grupo de 42 países parceiros. A revisão da taxa de câmbio euro-dólar é apresentada em percentagem. A hipótese técnica para as taxas de câmbio bilaterais pressupõe a manutenção ao longo do horizonte de projeção dos níveis médios observados nas duas semanas anteriores à data de fecho da informação.
A36: Sources: Banco de Portugal and Eurosystem (Banco de Portugal calculations). | Notes: yoy – year-on-year rate of change, % – in percentage, aav – annual average value, MWh – megawatt-hour. Technical and external environment assumptions, as well as projections for euro area GDP and inflation, coincide with those in the ECB projection exercise released on June 6 (see "Eurosystem staff macroeconomic projections for the euro area", june 2024), which include information up to May 21. International prices are in euros. The technical assumptions for the price of oil, gas and non-energy commodities is based on futures markets. The import price of competitors corresponds to a weighted average of the export deflators of the countries from which Portugal imports, weighted by their share on total Portuguese imports (for more information, see "Trade consistency in the context of the Eurosystem projection exercises: an overview", ECB Occasional Paper 108, March 2010). The evolution of the 3-month EURIBOR is based on expectations implied in futures contracts. The implicit interest rate on public debt is computed as the ratio of interest expenditure for the year to the simple average of the stock of debt at the end of the same year and at the end of the preceding year. An increase in the exchange rate corresponds to an appreciation of the euro. The effective exchange rate of the euro is computed against 41 trading partner countries. The technical assumption for bilateral exchange rates assumes that the average levels observed in the 10 business days prior to the cut-off date are maintained over the projection horizon.

Sheet GC.2.1
A5: Índice/Contents
A6: Boletim Económico - junho 2024/Economic Bulletin - June 2024
A7: =+Índice!A31 -> Caixa 2-Termos de troca no comércio de bens /Box 2-Terms of trade in goods
A10: Gráfico C2.1 • Termos de troca | Índice 2015 = 100
A11: Chart B2.1 • Terms of trade | Index 2015 = 100
D13: Unidade/Unit
E14: 2015 | F14: =+E14+1 -> 2016 | G14: =+F14+1 -> 2017 | H14: =+G14+1 -> 2018 | I14: =+H14+1 -> 2019 | J14: =+I14+1 -> 2020 | K14: =+J14+1 -> 2021 | L14: =+K14+1 -> 2022 | M14: =+L14+1 -> 2023
B16: Total de bens | C16: Total of goods | D16: Índice 2015 = 100/Index 2015 = 100 | E16: 100 | F16: 100.54058 | G16: 99.7452 | H16: 99.345425 | I16: 99.802379 | J16: 101.64847 | K16: 100.34898 | L16: 95.022477 | M16: 97.284704
B17: Bens excluindo energéticos | C17: Goods excluding energy | D17: Índice 2015 = 100/Index 2015 = 100 | E17: 100 | F17: 99.940043 | G17: 99.800487 | H17: 100.53175 | I17: 100.86826 | J17: 101.4886 | K17: 102.69789 | L17: 101.94459 | M17: 102.32361
B19: Fonte: INE – Estatísticas de Comércio Internacional de Bens (cálculos do Banco de Portugal).
B20: Nota: Sobre a decomposição da variação dos termos de troca ver nota ao gráfico C2.3.
B22: Source: Statistics Portugal - Goods International Trade Statistics (Banco de Portugal calculations).
B23: Notes: Regarding the terms of trade variation clause, see note to chart B2.3.

Sheet GC.2.2
A5: Índice/Contents
A6: Boletim Económico - junho 2024/Economic Bulletin - June 2024
A7: =+Índice!A31 -> Caixa 2-Termos de troca no comércio de bens /Box 2-Terms of trade in goods
A10: Gráfico C2.2 • Variação dos termos de troca de bens – contributos da componente energética e não energética | Em pontos percentuais
A11: Chart B2.2 • Terms of trade in goods change – contributions of energy and non-energy | In percentage points
D13: Unidade/Unit | E13: 2016 | F13: 2017 | G13: 2018 | H13: 2019 | I13: 2020 | J13: 2021 | K13: 2022 | L13: 2023
B15: Variação dos termos de troca de bens (pp) | C15: Change on goods terms of trade | D15: pp | E15: 0.54057934 | F15: -0.79537926 | G15: -0.39977491 | H15: 0.45695355 | I15: 1.846091 | J15: -1.2994933 | K15: -5.3264992 | L15: 2.262227
B16: Energéticos | C16: Energy | D16: pp | E16: 0.67268875 | F16: -0.76362484 | G16: -1.1054527 | H16: 0.14473525 | I16: 1.3442266 | J16: -2.6344755 | K16: -5.3602214 | L16: 1.8327708
B17: Não energéticos | C17: Non-energy | D17: pp | E17: -0.13210941 | F17: -0.031754417 | G17: 0.70567782 | H17: 0.3122183 | I17: 0.50186434 | J17: 1.3349822 | K17: 0.033722163 | L17: 0.42945622
B19: Fonte: INE – Estatísticas de Comércio Internacional de Bens (cálculos do Banco de Portugal).
B20: Nota: Sobre a decomposição da variação dos termos de troca ver nota ao gráfico C2.3.
B22: Source: Statistics Portugal - Goods International Trade Statistics (Banco de Portugal calculations).
B23: Notes: Regarding the terms of trade breakdown, see note to chart B2.3.

Sheet GC.2.3
A5: Índice/Contents
A6: Boletim Económico - junho 2024/Economic Bulletin - June 2024
A7: =+Índice!A31 -> Caixa 2-Termos de troca no comércio de bens /Box 2-Terms of trade in goods
A10: Gráfico C2.3 • Variação de termos de troca de bens e contributos dos efeitos estrutura e preço relativo | Em pontos percentuais
A11: Chart B2.3 • Terms of trade in goods change and contributions of structure and relative price effects | In percentage points
F13: Unidade/Unit | H13: 2016 | I13: 2017 | J13: 2018 | K13: 2019 | L13: 2020 | M13: 2021 | N13: 2022 | O13: 2023
B15: Painel A - Total de bens | C15: Panel A - Total goods | D15: Termos de troca total de bens | E15: Goods Terms of trade | F15: % | H15: 0.54057934 | I15: -0.79537926 | J15: -0.39977491 | K15: 0.45695355 | L15: 1.846091 | M15: -1.2994933 | N15: -5.3264992 | O15: 2.262227
D16: Contributo do efeito estrutura | E16: Structural effect | F16: pp | H16: 0.70533731 | I16: -0.89356044 | J16: -0.59510516 | K16: 0.17140696 | L16: 1.182021 | M16: -2.3437472 | N16: -3.6745579 | O16: 1.9447287
D17: Contributo do efeito preço relativo | E17: Relative price effect | F17: pp | H17: -0.16475797 | I17: 0.098181178 | J17: 0.19533025 | K17: 0.28554659 | L17: 0.66406994 | M17: 1.0442539 | N17: -1.6519413 | O17: 0.31749835
B19: Painel B - Bens excluindo energéticos | C19: Panel B - Goods excluding energy | D19: Termos de troca excluindo bens energéticos | E19: Goods excluding energy terms of trade | F19: % | H19: -0.059956681 | I19: -0.13955639 | J19: 0.731262 | K19: 0.33651308 | L19: 0.62033665 | M19: 1.2092919 | N19: -0.75329908 | O19: 0.37901796
D20: Contributo do efeito estrutura | E20: Structural effect | F20: pp | H20: -0.14949632 | I20: -0.059385274 | J20: 0.21106423 | K20: 0.0066118018 | L20: -0.027251744 | M20: -0.40511837 | N20: -0.13962487 | O20: -0.18989652
D21: Contributo do efeito preço relativo | E21: Relative price effect | F21: ppp | H21: 0.089539636 | I21: -0.080171113 | J21: 0.52019778 | K21: 0.32990128 | L21: 0.64758839 | M21: 1.6144103 | N21: -0.61367422 | O21: 0.56891448
B23: Fonte: INE – Estatísticas de Comércio Internacional de Bens (cálculos do Banco de Portugal).
B24: Source: Statistics Portugal - Goods International Trade Statistics (Banco de Portugal calculations).
B26: Notas: A variação dos termos de troca pode ser decomposta na soma dos contributos dos diferentes tipos de produtos i da seguinte forma:
B28: Sendo tvaXi,t e wXi,t (tvaMi,t e wMi,t) a taxa de variação anual do preço e o peso nas exportações totais (importações) de cada componente i em t. O efeito estrutura mede o impacto sobre os termos de troca da especialização setorial da economia. O efeito preço relativo mede o efeito da evolução diferenciada dos preços de exportação e importação em cada setor. Para mais detalhes, ver Cardoso, F. e Esteves, P. (2008), “Globalização, alterações estruturais das exportações e termos de troca de Portugal”, Boletim Económico Primavera 2008, Banco de Portugal.
B30: Notes: The terms of trade change may be broken down into the sum of contributions of different types of products i in the following way:
B32: Being yrcXi,t and wXi,t (yrcMi,t and wMi,t) the annual rate of change of prices and the weight in total exports (imports) of each component i in t. The structural effect measures the impact on the terms of trade of the sectoral specialization of the economy. The relative price effect measures the effect of the different export and import price evolution within each sector. For further details, see Cardoso, F. and Esteves, P. (2008), “Globalisation, Structural Changes in Exports and the Portuguese Terms of Trade”, Economic Bulletin Spring 2008, Banco de Portugal.

Sheet QC.2.1
A5: Índice/Contents
A6: Boletim Económico - junho 2024/Economic Bulletin - June 2024
A7: =+Índice!A31 -> Caixa 2-Termos de troca no comércio de bens /Box 2-Terms of trade in goods
A10: Quadro C2.1 • Contributos dos grupos de produtos para a variação dos termos de troca de bens – 2023 vs. 2015 | Variação acumulada em percentagem e contributos em pp
A11: Table B2.1 • Groups of products' contribution to the terms of trade total variation – 2023 vs. 2015 | Cumulative growth as a percentage and contributions in pp
A13: Unidade/Unit | H13: % | I13: % | J13: % | K13: % | L13: % | M13: pp | N13: pp | O13: pp
J14: 2023 vs 2015
H15: Peso médio no período | J15: Crescimento acumulado | M15: Contributos
H16: Average weight | J16: Cumulative growth | M16: Contributions
H17: Exportações | I17: Importações | J17: Preço de exportação | K17: Preço de importação | L17: Termos de troca | M17: Efeito estrutura | N17: Efeito preço relativo | O17: Efeito total
H18: Exports | I18: Imports | J18: Export prices | K18: Import prices | L18: Terms of trade | M18: Structural effect | N18: Relative price effect | O18: Total effect
B19: Agric. silv. e pescas | E19: Agriculture, hunting and fishing | H19: 3.0953758 | I19: 5.7006411 | J19: 14.636668 | K19: 27.685051 | L19: -13.048383 | M19: -0.48504941 | N19: -0.59709603 | O19: -1.0821454
B20: Indústrias extrativas | E20: Mining and quarrying | H20: 1.1325866 | I20: 0.19787074 | J20: 35.768955 | K20: 11.577051 | L20: 24.191904 | M20: 0.18586517 | N20: 0.13133757 | O20: 0.31720274
B21: Bens manufaturados | E21: Manufacturing | H21: 89.370233 | I21: 82.128083 | J21: 21.614432 | K21: 18.568549 | L21: 3.0458827 | M21: 1.2678366 | N21: 2.6511633 | O21: 3.9189999
C22: Alimentares e bebidas | F22: Food and beverages | H22: 8.9117863 | I22: 9.4212126 | J22: 30.277196 | K22: 29.441917 | L22: 0.83527898 | M22: -0.1108243 | N22: 0.068526668 | O22: -0.042297636
C23: Artigos de borracha e de matérias plásticas | F23: Rubber and plastic produtes | H23: 5.562144 | I23: 3.2125036 | J23: 21.15375 | K23: 4.9617905 | L23: 16.191959 | M23: 0.25205078 | N23: 0.72786356 | O23: 0.97991434
C24: Setor têxtil e do calçado | F24: Textiles, clothing and footwear | H24: 11.92763 | I24: 6.9616623 | J24: 20.676468 | K24: 1.3872488 | L24: 19.289219 | M24: 0.47846038 | N24: 1.7881023 | O24: 2.2665627
D25: Têxteis | G25: Textiles | H25: 3.2651836 | I25: 2.2610582 | J25: 13.863734 | K25: -1.350479 | L25: 15.214213 | M25: 0.080592215 | N25: 0.39015047 | O25: 0.47074269
D26: Vestuário | G26: Clothing | H26: 5.6756905 | I26: 3.7713126 | J26: 28.081941 | K26: -1.2342332 | L26: 29.316174 | M26: 0.19413066 | N26: 1.389205 | O26: 1.5833356
D27: Calçado e produtos de couro | G27: Footwear and leather products | H27: 2.9867557 | I27: 0.92929157 | J27: 14.823015 | K27: 18.756064 | L27: -3.9330494 | M27: 0.31035696 | N27: -0.097872586 | O27: 0.21248438
C28: Madeira, cortiça e papel | F28: Wood, cork, pulp and paper products | H28: 7.211789 | I28: 2.817951 | J28: 31.246561 | K28: 18.899209 | L28: 12.347352 | M28: 1.0008026 | N28: 0.61169985 | O28: 1.6125024
C29: Máquinas e equipamentos | F29: Machinery and equipment | H29: 15.26764 | I29: 17.984798 | J29: 19.822895 | K29: 23.663392 | L29: -3.8404966 | M29: -0.35034299 | N29: -0.52160043 | O29: -0.87194342
C30: Material de transporte | F30: Transport equipment | H30: 13.994166 | I30: 13.715569 | J30: 18.608608 | K30: 16.881432 | L30: 1.727176 | M30: 0.11179791 | N30: 0.21902983 | O30: 0.33082774
C31: Minerais e produtos metálicos | F31: Mineral and metal products | H31: 12.261525 | I31: 9.2827235 | J31: 22.725915 | K31: 26.93186 | L31: -4.205945 | M31: 0.56919502 | N31: -0.44192194 | O31: 0.12727307
C32: Produtos químicos | F32: Chemical products | H32: 8.0810237 | I32: 14.423955 | J32: 24.838644 | K32: 16.662877 | L32: 8.175767 | M32: -1.6341351 | N32: 1.0087632 | O32: -0.62537187
C33: Outros | F33: Other | H33: 6.1525287 | I33: 4.3077073 | J33: 11.356308 | K33: 11.595532 | L33: -0.23922447 | M33: 0.18470514 | N33: -0.043172597 | O33: 0.14153255
B35: Bens não energéticos | E35: Non-energy | H35: 93.598195 | I35: 88.026595 | J35: 21.441273 | K35: 19.117663 | L35: 2.3236095 | M35: 0.30914466 | N35: 2.8449125 | O35: 3.1540572
B36: Bens energéticos | E36: Energy | H36: 6.4018048 | I36: 11.973405 | J36: 87.523518 | K36: 113.58995 | L36: -26.06643 | M36: -3.8126214 | N36: -2.0567316 | O36: -5.869353
B38: TOTAL | E38: TOTAL | H38: 100 | I38: 100 | J38: 22.873316 | K38: 25.588612 | L38: -2.7152958 | M38: -3.5034768 | N38: 0.78818095 | O38: -2.7152958
B40: Fonte: INE – Estatísticas de Comércio Internacional de Bens (cálculos do Banco de Portugal).
B41: Nota: Sobre a decomposição da variação dos termos de troca ver nota ao gráfico C2.3.
B43: Source: Statistics Portugal - Goods International Trade Statistics (Banco de Portugal calculations).
B44: Notes: Regarding the terms of trade breakdown, see note to Chart B2.3.

Sheet GC.3.1
A5: Índice/Contents
A6: Boletim Económico - junho 2024/Economic Bulletin - June 2024
A7: =+Índice!$A$41 -> Caixa 3 - A transmissão do preço dos bens energéticos ao IHPC / Box 3- The pass-through of energy prices to the HICP
A10: Gráfico C3.1 • IHPC total e IHPC de bens energéticos | Taxa de variação homóloga em percentagem e contributos em pontos percentuais
A11: Chart B3.1 • HICP headline and HICP of energy goods | Year-on-year change rate in percentage and contributions in percentage points
C13: Painel A – IHPC total | G13: Painel B – IHPC de bens energéticos
C14: Panel A – HICP headline | G14: Panel B – HICP of energy goods
A15: Unidade/Unit | C15: % | D15: pp | E15: pp | G15: % | H15: pp | I15: pp | J15: pp | K15: pp
C16: IHPC total (tvh, %) | D16: Energéticos | E16: Componente não energética | G16: Energéticos (%) | H16: Eletricidade | I16: Gás | J16: Gasóleo+ Gasolina | K16: Outros
C17: HICP headline (%) | D17: Energy | E17: Non-energy component | G17: Energy goods (%) | H17: Electricity | I17: Gas | J17: Diesel+ Gasoline | K17: Other
A18: 2021T1 | B18: 2021Q1 | C18: 0.19465983 | D18: -0.1181629 | E18: 0.30414705 | G18: -1.7781758 | H18: -0.36087318 | I18: -0.63396667 | J18: -0.65117341 | K18: -0.070778714
A19: 2021T2 | B19: 2021Q2 | C19: -0.060478737 | D19: 0.67556556 | E19: -0.73896652 | G19: 9.3519193 | H19: -0.092023851 | I19: 0.06806711 | J19: 9.0539382 | K19: 0.32209581
A20: 2021T3 | B20: 2021Q3 | C20: 1.2273694 | D20: 0.75768955 | E20: 0.4706718 | G20: 9.7944581 | H20: 0.63973293 | I20: 0.33260398 | J20: 8.4850842 | K20: 0.33788125
A21: 2021T4 | B21: 2021Q4 | C21: 2.411814 | D21: 1.0236634 | E21: 1.3878774 | G21: 13.236637 | H21: 1.0528085 | I21: 1.1214061 | J21: 10.527432 | K21: 0.54578825
A22: 2022T1 | B22: 2022Q1 | C22: 4.4199074 | D22: 1.2587494 | E22: 3.1578129 | G22: 15.941651 | H22: 2.0482422 | I22: 1.8307119 | J22: 11.425264 | K22: 0.60913749
A23: 2022T2 | B23: 2022Q2 | C23: 8.1663853 | D23: 2.2522634 | E23: 5.9172338 | G23: 28.88445 | H23: 7.6590392 | I23: 4.3853504 | J23: 15.822469 | K23: 0.99920766
A24: 2022T3 | B24: 2022Q3 | C24: 9.5312351 | D24: 2.0647473 | E24: 7.4614111 | G24: 25.889152 | H24: 11.490878 | I24: 3.7003622 | J24: 9.7866459 | K24: 0.92787996
A25: 2022T4 | B25: 2022Q4 | C25: 10.207166 | D25: 1.9626659 | E25: 8.2433214 | G25: 24.331184 | H25: 9.5804664 | I25: 8.9746688 | J25: 5.1436658 | K25: 0.63420505
A26: 2023T1 | B26: 2023Q1 | C26: 8.394319 | D26: 0.19234509 | E26: 8.1952695 | G26: 1.3985621 | H26: -1.8124827 | I26: 6.6876946 | J26: -3.5180692 | K26: 0.22065746
A27: 2023T2 | B27: 2023Q2 | C27: 5.6535438 | D27: -1.3342156 | E27: 6.977075 | G27: -15.775618 | H27: -6.6893257 | I27: 1.7022828 | J27: -10.385326 | K27: -0.33828269
A28: 2023T3 | B28: 2023Q3 | C28: 4.8143413 | D28: -0.73525871 | E28: 5.5366335 | G28: -8.4951041 | H28: -6.4598752 | I28: 1.5460972 | J28: -3.2470055 | K28: -0.20252416
A29: 2023T4 | B29: 2023Q4 | C29: 2.4454348 | D29: -0.98114581 | E29: 3.4247086 | G29: -11.42864 | H29: -5.6657818 | I29: -3.9073115 | J29: -1.7668884 | K29: -0.073541413
A30: 2024T1 | B30: 2024Q1 | C30: 2.4631669 | D30: 0.17500238 | E30: 2.2839654 | G30: 3.0133496 | H30: 5.431499 | I30: -3.3682944 | J30: 0.9322441 | K30: 0.043773707
A32: Fonte: Eurostat (cálculos do Banco de Portugal).
A33: Source: Eurostat (Banco de Portugal calculations).

Sheet GC.3.2
A5: Índice/Contents
A6: Boletim Económico - junho 2024/Economic Bulletin - June 2024
A7: =+Índice!$A$41 -> Caixa 3 - A transmissão do preço dos bens energéticos ao IHPC / Box 3- The pass-through of energy prices to the HICP
A10: Gráfico C3.2 • Resposta da inflação e dos seus componentes a um choque de 1 desvio padrão no preço dos bens energéticos | Pontos percentuais
A11: Chart B3.2 • Response of inflation and its components to a shock of 1 standard deviation in energy prices | Percentage points
A13: unidade/unit: pp | C13: meses após o choque
C14: months after shock
C15: t | D15: t +6 | E15: t +12 | F15: t +18 | G15: t +24
A16: IHPC total | B16: HICP headline | C16: 0.2141088 | D16: 0.2359512 | E16: 0.18714926 | F16: 0.095243145 | G16: 0.01788294
A17: IHPC subjacente | B17: HICP core | C17: 0.0076224203 | D17: 0.049846428 | E17: 0.061007224 | F17: 0.040515612 | G17: 0.011421839
A18: IHPC alimentares | B18: HICP food | C18: 0.026486205 | D18: 0.081709921 | E18: 0.084860231 | F18: 0.051328225 | G18: 0.015299722
A19: IHPC energia | B19: HICP energy | C19: 0.18000017 | D19: 0.10439485 | E19: 0.041281804 | F19: 0.0033993078 | G19: -0.0088386212
A21: Fontes: Eurostat e INE (cálculos do Banco de Portugal). | Notas: Resposta a um choque positivo de um desvio padrão na taxa de variação homóloga do IHPC dos bens energéticos, que corresponde a um aumento de 2,2%. Foi estimado um modelo BVAR com volatilidade estocástica e inércia aleatória, usando dados mensais. As variáveis foram transformadas em taxas de variação homóloga. O período de estimação considerado foi jan/04-mar/24. Foram incluídos no modelo 12 desfasamentos de cada variável. As variáveis PIB real e remunerações por trabalhador foram convertidas em frequência mensal usando o método de Litterman. A identificação dos choques foi obtida com recurso à decomposição de Cholesky da matriz de variância-covariância dos resíduos, seguindo a ordem das variáveis pela qual são apresentadas no texto principal. O IHPC total é obtido através da agregação das subcomponentes com recurso aos respetivos pesos anuais.
A22: Sources: Eurostat and Statistics Portugal (Banco de Portugal calculations). | Notes: response to a positive one standard deviation shock in the year-on-year growth rate of the HICP for energy goods, which corresponds to an increase of 2.2%. A BVAR model with stochastic volatility and random inertia was estimated using monthly data. The variables were transformed into year-on-year growth rates. The estimation sample was Jan/04-Mar/24. The model included 12 lags of each variable. The variables real GDP and wages per worker were converted to a monthly frequency using the Litterman method. The identification of shocks was obtained using the Cholesky decomposition of the variance-covariance matrix of the residuals, following the order of the variables as presented in the main text. The total HICP is obtained through the aggregation of the subcomponents using their respective annual weights.

Sheet GC.3.3
A5: Índice/Contents
A6: Boletim Económico - junho 2024/Economic Bulletin - June 2024
A7: =+Índice!$A$41 -> Caixa 3 - A transmissão do preço dos bens energéticos ao IHPC / Box 3- The pass-through of energy prices to the HICP
A10: Gráfico C3.3 • Decomposição histórica da inflação e contributos diretos e indiretos dos choques estruturais sobre o preço dos bens energéticos | Taxa de variação homóloga em percentagem e contributos erm pontos percentuais
A11: Chart B3.3 • Historical decomposition of inflation and direct and indirect contributes of structural shocks to energy prices | Y-o-y rate of change in percentage and contributions in percentage points
A13: Unidade/Unit | C13: pp | D13: pp | E13: pp | F13: pp | G13: %
C14: Efeito direto | D14: Efeito indireto via IHPC alimentares | E14: Efeito indireto via IHPC subjacente | F14: Outros efeitos não relacionados com os bens energéticos | G14: Inflação total (%)
C15: Direct effect | D15: Indirect effect via HICP food | E15: Indirect effect via HICP core | F15: Other effects unrelated with energy goods | G15: Headline inflation (%)
A16: jan/21 | B16: Jan/21 | C16: -0.090237697 | D16: -0.45989774 | E16: -0.29020765 | F16: 1.0255824 | G16: 0.18523935
A17: fev /21 | B17: Feb/21 | C17: 0.0025972759 | D17: -0.40774538 | E17: -0.26494427 | F17: 0.94462909 | G17: 0.27453672
A18: mar/21 | B18: Mar/21 | C18: 0.39266981 | D18: -0.30312813 | E18: -0.22575533 | F18: 0.26161154 | G18: 0.1253979
A19: abr/21 | B19: Apr/21 | C19: 0.7870277 | D19: -0.17663808 | E19: -0.16280777 | F19: -0.54331228 | G19: -0.095730423
A20: mai/21 | B20: May/21 | C20: 0.8192084 | D20: -0.06133723 | E20: -0.090329772 | F20: -0.18769495 | G20: 0.47984645
A21: jun/21 | B21: Jun/21 | C21: 0.64175072 | D21: 0.021339374 | E21: -0.026117796 | F21: -1.196214 | G21: -0.55924171
A22: jul/21 | B22: Jul/21 | C22: 0.5761605 | D22: 0.10978408 | E22: 0.032439731 | F22: 0.39401653 | G22: 1.1124009
A23: ago/21 | B23: Aug/21 | C23: 0.62014074 | D23: 0.19865509 | E23: 0.089617461 | F23: 0.34255646 | G23: 1.2509697
A24: set/21 | B24: Sep/21 | C24: 0.68832143 | D24: 0.28761132 | E24: 0.14607453 | F24: 0.1963145 | G24: 1.3183218
A25: out/21 | B25: Oct/21 | C25: 0.84187059 | D25: 0.39016229 | E25: 0.20505111 | F25: 0.38372525 | G25: 1.8208092
A26: nov/21 | B26: Nov/21 | C26: 0.81880031 | D26: 0.46414629 | E26: 0.26633461 | F26: 1.0853565 | G26: 2.6346377
A27: dez/21 | B27: Dec/21 | C27: 0.50395051 | D27: 0.48596916 | E27: 0.3093105 | F27: 1.484475 | G27: 2.7837051
... A54: mar/24 | B54: Mar/24 | C54: 0.066910865 | D54: -0.36642771 | E54: -0.28766631 | F54: 3.1586601 | G54: 2.5714769
A56: Fonte: Eurostat (cálculos do Banco de Portugal). | Notas: os contributos têm origem na decomposição histórica do modelo BVAR estimado, condicionados pelo método de identificação dos choques estruturais que foi assumido (método de Cholesky). O efeito direto da energia na dinâmica da inflação corresponde ao contributo dos choques estruturais no IHPC dos bens energéticos para a dinâmica do IHPC total. Os efeitos indiretos dizem respeito ao contributo dos choques estruturais no IHPC dos bens energéticos para a dinâmica das restantes componentes do IHPC.
A57: Sources: Eurostat (Banco de Portugal calculations). | Notes: the source of the contributes is the historical decomposition of the estimated BVAR model, which is conditioned by the assumed method of identification of structural shocks (Cholesky method). The direct effect of energy on inflation dynamics corresponds to the contribution of structural shocks in the HICP of energy goods to the dynamics of total HICP. The indirect effects refer to the contribution of structural shocks in the HICP of energy goods to the dynamics of the remaining components of the HICP.

Sheet QC.3.1
A5: Índice/Contents
A6: Boletim Económico - junho 2024/Economic Bulletin - June 2024
A7: =+Índice!$A$41 -> Caixa 3 - A transmissão do preço dos bens energéticos ao IHPC / Box 3- The pass-through of energy prices to the HICP
A10: Quadro C3.1 • Contributo para a inflação dos choques estruturais sobre o preço da energia | Pontos percentuais
A11: Table B3.1 • Contribution to inflation from structural energy price shocks | Percentage points
A13: Unidade/Unit | C13: pp | D13: pp | E13: pp | F13: pp | G13: %
C14: Efeito direto | D14: Efeito indireto via IHPC alimentares | E14: Efeito indireto via IHPC subjacente | F14: Efeito total na inflação | G14: por memória: inflação observada
C15: Direct effect | D15: Indirect effect via HICP food | E15: Indirect effect via HICP core | F15: Total effect on inflation | G15: Headline inflation
A16: 2021 | B16: 2021 | C16: 0.55018836 | D16: 0.045743421 | E16: -0.00094455212 | F16: 0.59498723 | G16: 0.94130898
A17: 2022 | B17: 2022 | C17: 1.4476282 | D17: 1.0982756 | E17: 0.70619566 | F17: 3.2520994 | G17: 8.1026581
A18: 2023 | B18: 2023 | C18: -0.70794422 | D18: 0.50858854 | E18: 0.49314906 | F18: 0.29379338 | G18: 5.2642832
A19: 2024 T1 | B19: 2024 Q1 | C19: -0.033547757 | D19: -0.34709206 | E19: -0.2525535 | F19: -0.63319332 | G19: 2.4631669
A21: Fonte: Eurostat (cálculos do Banco de Portugal).
A22: Source: Eurostat (Banco de Portugal calculations).
B56: Fonte: Eurostat (cálculos do Banco de Portugal). | Notas: os contributos têm origem na decomposição histórica do modelo BVAR estimado, condicionados pelo método de identificação dos choques estruturais que foi assumido (método de Cholesky). O efeito direto da energia na dinâmica da inflação corresponde ao contributo dos choques estruturais no IHPC dos bens energéticos para a dinâmica do IHPC total. Os efeitos indiretos dizem respeito ao contributo dos choques estruturais no IHPC dos bens energéticos para a dinâmica das restantes componentes do IHPC.
B57: Sources: Eurostat (Banco de Portugal calculations). | Notes: .

Sheet GI.2.1
A5: Índice/Contents
A6: Boletim Económico - Junho 2024/Economic Bulletin - June 2024
A7: =+Índice!$A$50 -> Parte I.2 Análise e projeções de finanças públicas/Part I.2 Analysis and projections of public finances
A10: Gráfico I.2.1 Saldo das administrações públicas observado e projetado em Portugal e na área do euro | Em percentagem do PIB
A11: Chart I.2.1 · General government balance outturn and projections in Portugal and the euro area | Percentage of GDP
A15: Unidade/Unit | C15: % PIB | D15: % PIB | E15: % PIB
C16: % GDP | D16: % GDP | E16: % GDP
C18: 2019 | D18: 2023 | E18: 2025(p)
A20: CY | B20: CY | C20: 0.9 | D20: 3.1 | E20: 2.9
A21: IE | B21: IE | C21: 0.5 | D21: 1.7 | E21: 1.2
A22: PT | B22: PT | C22: 0.1 | D22: 1.2 | E22: 0.77930605
A23: NL | B23: NL | C23: 1.8 | D23: -0.3 | E23: -2.1
A24: HR | B24: HR | C24: 0.2 | D24: -0.7 | E24: -2.6
A25: LT | B25: LT | C25: 0.5 | D25: -0.8 | E25: -2.2
A26: LU | B26: LU | C26: 2.2 | D26: -1.3 | E26: -1.9
A27: EL | B27: EL | C27: 0.8 | D27: -1.6 | E27: -0.8
A28: LV | B28: LV | C28: -0.5 | D28: -2.2 | E28: -2.9
A29: DE | B29: DE | C29: 1.5 | D29: -2.5 | E29: -1.2
A30: SI | B30: SI | C30: 0.7 | D30: -2.5 | E30: -2.2
A31: AT | B31: AT | C31: 0.6 | D31: -2.7 | E31: -2.9
... A40: IT | B40: IT | C40: -1.5 | D40: -7.4 | E40: -4.7
A42: Fontes: INE e Banco de Portugal (Portugal) e Comissão Europeia (restantes países e agregado da área do euro). | Notas: Os países estão ordenados pelo saldo orçamental de 2023. Os valores projetados pela Comissão Europeia para Portugal são 0,4% e 0,5% do PIB em 2024 e 2025.
A43: Sources: Statistics Portugal and Banco de Portugal (Portugal) and European Commission (remaining countries and euro area aggregate). | Notes: Countries are ordered by the 2023 budget balance. The values ​​projected by the European Commission for Portugal are 0.4% and 0.5% of GDP in 2024 and 2025.

Sheet GI.2.2
A5: Índice/Contents
A6: Boletim Económico - Junho 2024/Economic Bulletin - June 2024
A7: =+Índice!$A$50 -> Parte I.2 Análise e projeções de finanças públicas/Part I.2 Analysis and projections of public finances
A10: Gráfico I.2.2 Decomposição da variação do saldo das administrações públicas em Portugal e na área do euro| Em pontos percentuais do PIB e do PIB potencial
A11: Chart I.2.1 · Breakdown of the change in the general government balance in Portugal and the euro area | Percentage points of GDP and potential GDP
A15: Unidade/Unit | C15: pp do PIB | D15: pp do PIB | E15: pp do PIB | F15: pp do PIB | G15: pp do PIB
C16: pp of GDP | D16: pp of GDP | E16: pp of GDP | F16: pp of GDP | G16: pp of GDP
C18: AE | D18: PT | E18: PT
C19: EA | D19: PT | F19: PT
C20: Acumulado: 20-23 | E20: 2024(p) | F20: 2025(p) | G20: 2026(p)
C21: Cumulative: 20-23
A23: Componente cíclica | B23: Cyclical component | C23: -0.7 | D23: 0.085143682 | E23: -0.3299923 | F23: -0.094547547 | G23: -0.015477217
A24: Medidas temporárias | B24: Temporary measures | C24: 0.2 | D24: 0.054718198 | E24: 0.34698417 | F24: 0.083896159 | G24: 0
A25: Despesa em juros (simétrico) | B25: Interest expenditure (symmetric) | C25: -0.1 | D25: 0.78374117 | E25: -0.11084204 | F25: 0.077963029 | G25: 0.074815298
A26: Saldo primário estrutural | B26: Structural primary balance | C26: -2.5 | D26: 0.16365617 | E26: -0.071160326 | F26: -0.32623135 | G26: -0.19481212
A27: Saldo total | B27: Overall balance | C27: -3.1 | D27: 1.0874836 | E27: -0.16463486 | F27: -0.25887208 | G27: -0.13547404
A29: Fontes: INE, Comissão Europeia (área do euro) e Banco de Portugal. | Nota: A correção pelos efeitos cíclicos e de medidas temporárias é apurada pelo Banco de Portugal de acordo com a metodologia e as definições utilizadas no SEBC. Para mais detalhes, ver Braz et al. (2019), “A nova metodologia do SEBC para o cálculo dos saldos orçamentais ajustados do ciclo: uma aplicação ao caso português”, Revista de Estudos Económicos, Volume V, nº. 2, Abril, Banco de Portugal.
A30: Sources: Statistics Portugal, European Commission (euro area) and Banco de Portugal. | Note: Correction for cyclical effects and temporary measures is calculated by Banco de Portugal in accordance with the methodology and definitions used in the ESCB. For more details, see Braz et al. (2019), “The new ESCB methodology for calculating cyclically adjusted budget balances: an application to the Portuguese case”, Review of Economic Studies, Volume V, no. 2, April, Banco de Portugal.

Sheet GI.2.3
A5: Índice/Contents
A6: Boletim Económico - Junho 2024/Economic Bulletin - June 2024
A7: =+Índice!$A$50 -> Parte I.2 Análise e projeções de finanças públicas/Part I.2 Analysis and projections of public finances
A10: Gráfico I.2.3 Impacto direto de medidas de política sobre o saldo orçamental em Portugal | Em percentagem do PIB
A11: Chart I.2.3 · Direct impact of policy measures on the budget balance in Portugal | Percentage of GDP
A15: Unidade/Unit | C15: % do PIB | D15: % do PIB | E15: % do PIB | F15: % do PIB
C16: % of GDP | D16: % of GDP | E16: % of GDP | F16: % of GDP
C18: 2023 | D18: 2024 | E18: 2025 | F18: 2026
A19: OE 2024 | B19: Budget 2024 | C19: 0 | D19: -0.90092388 | E19: -0.92283807 | F19: -0.87212158
A20: Compensação pelo aumento dos preços | B20: Compensation for price increases | C20: -1.0342602 | D20: -0.4398157 | E20: -0.10445054 | F20: -0.099758416
A21: PRR empréstimos | B21: RRF loans | C21: -0.019783291 | D21: -0.1111002 | E21: -0.50770875 | F21: -0.796779
A22: Outras medidas (exc. temporárias) | B22: Other measures (exc. temporary) | C22: -1.036215 | D22: -0.9655813 | E22: -0.94444574 | F22: -0.88586682
A23: Pós - OE 2024 | B23: Post-Budget 2024 | C23: 0 | D23: -0.017419118 | E23: -0.13471684 | F23: -0.1286651
A24: Total | B24: Total | C24: -2.0902585 | D24: -2.4348402 | E24: -2.6141599 | F24: -2.7831909
A26: Fonte: Banco de Portugal. | Nota: A componente ‘Pós-OE2024’ refere-se às medidas adotadas recentemente, incluindo a abolição das portagens nas ex-SCUT e as alterações ao Complemento Solidário para Idosos.
A27: Source: Banco de Portugal. | Note: The ‘Post-Budget2024’ component refers to recently adopted measures, including the abolition of tolls on former SCUT roads and changes to the solidaritysupplement for the elderly.

Sheet GI.2.4
A5: Índice/Contents
A6: Boletim Económico - Junho 2024/Economic Bulletin - June 2024
A7: =+Índice!$A$50 -> Parte I.2 Análise e projeções de finanças públicas/Part I.2 Analysis and projections of public finances
A10: Gráfico I.2.4 Decomposição da variação da receita fiscal e contributiva em Portugal | Em pontos percentuais do PIB
A11: Chart I.2.4 · Breakdown of the change in revenue from taxes and social contributions in Portugal | Percentage points of GDP
A15: Unidade/Unit | C15: pp do PIB | D15: pp do PIB | E15: pp do PIB | F15: pp do PIB | G15: pp do PIB | H15: pp do PIB | I15: pp do PIB
C16: pp of GDP | D16: pp of GDP | E16: pp of GDP | F16: pp of GDP | G16: pp of GDP | H16: pp of GDP | I16: pp of GDP
C18: 2020 | D18: 2021 | E18: 2022 | F18: 2023 | G18: 2024(p) | H18: 2025(p) | I18: 2026(p)
A19: Efeito da progressividade fiscal | B19: Fiscal drag | C19: 0.071451547 | D19: 0.23988707 | E19: 0.27149891 | F19: 0.37714936 | G19: 0.2276869 | H19: 0.16352196 | I19: 0.16028732
A20: Efeito da composição do crescimento | B20: Growth composition effect | C20: -0.082818272 | D20: 0.0043697857 | E20: 0.057653419 | F20: -0.41268115 | G20: -0.19519609 | H20: -0.20587987 | I20: -0.12684127
A21: Impacto de medidas | B21: Impact of measures | C21: -0.37466329 | D21: -0.30017901 | E21: -0.16179318 | F21: -0.65196043 | G21: -0.18944557 | H21: 0.012515835 | I21: 0
A22: Resíduo | B22: Residual | C22: 1.1540244 | D22: -0.002539896 | E22: 0.39338537 | F22: 0.38137337 | G22: 0.00057043736 | H22: -0.10377482 | I22: -0.084408568
A23: Total | B23: Total | C23: 0.76799443 | D23: -0.058462053 | E23: 0.56074453 | F23: -0.30611886 | G23: -0.15638433 | H23: -0.13361689 | I23: -0.050962523
A25: Fontes: INE e Banco de Portugal. | Nota: Para mais detalhes, ver Braz et al. (2019).
A26: Source: Statistics Portugal and Banco de Portugal. | Note: For more details, see Braz et al. (2019).

Sheet GI.2.5
A5: Índice/Contents
A6: Boletim Económico - Junho 2024/Economic Bulletin - June 2024
A7: =+Índice!$A$50 -> Parte I.2 Análise e projeções de finanças públicas/Part I.2 Analysis and projections of public finances
A10: Gráfico I.2.5 Decomposição da variação da despesa corrente primária estrutural em Portugal | Em pontos percentuais do PIB e do PIB potencial
A11: Chart I.2.5 · Breakdown of the change in structural primary current expenditure in Portugal | Percentage points of GDP and potencial GDP
A15: Unidade/Unit | C15: pp do PIB | D15: pp do PIB | E15: pp do PIB | F15: pp do PIB | G15: pp do PIB | H15: pp do PIB | I15: pp do PIB
C16: pp of GDP | D16: pp of GDP | E16: pp of GDP | F16: pp of GDP | G16: pp of GDP | H16: pp of GDP | I16: pp of GDP
C18: 2020 | D18: 2021 | E18: 2022 | F18: 2023 | G18: 2024(p) | H18: 2025(p) | I18: 2026(p)
A19: Remunerações | B19: Compensation of employees | C19: 0.19096683 | D19: 0.053434041 | E19: -0.32057276 | F19: -0.092357268 | G19: -0.025079007 | H19: -0.09908151 | I19: -0.040705942
A20: Consumo intermédio | B20: Intermediate consumption | C20: -0.084545116 | D20: 0.32492559 | E20: 0.13018587 | F20: -0.21667851 | G20: 0.061058282 | H20: 0.0078125794 | I20: 0.056295226
A21: Prestações sociais | B21: Social payments | C21: -0.10464228 | D21: -0.0018465775 | E21: 0.37356538 | F21: -0.89548341 | G21: 0.1358822 | H21: -0.12416403 | I21: -0.20013376
A22: Outra | B22: Other | C22: 1.3806388 | D22: 0.5115969 | E22: -0.87747507 | F22: -0.65693169 | G22: -0.013317339 | H22: -0.13855653 | I22: -0.037670276
A23: Total | B23: Total | C23: 1.3824182 | D23: 0.88810996 | E23: -0.69429658 | F23: -1.8614509 | G23: 0.15854414 | H23: -0.35398949 | I23: -0.22221475
A25: Fontes: INE e Banco de Portugal.
A26: Sources: Statistics Portugal and Banco de Portugal.

Sheet GI.2.6
A5: Índice/Contents
A6: Boletim Económico - Junho 2024/Economic Bulletin - June 2024
A7: =+Índice!$A$50 -> Parte I.2 Análise e projeções de finanças públicas/Part I.2 Analysis and projections of public finances
A10: Gráfico I.2.6 Repartição temporal da despesa pública no âmbito do PRR em Portugal | Em percentagem do total do PRR em 2021-2026
A11: Chart I.2.6 · Temporal allocation of public expenditure within the scope of the RRP in Portugal | Percentage of total RRP in 2021-2026
A15: Unidade/Unit | C15: % do total | D15: % do total | E15: % do total | F15: % do total | G15: % do total | H15: % do total
C16: % of total | D16: % of total | E16: % of total | F16: % of total | G16: % of total | H16: % of total
C18: 2021 | D18: 2022 | E18: 2023 | F18: 2024(p) | G18: 2025(p) | H18: 2026(p)
A19: Despesa financiada por subvenções | B19: Expenditure financed by grants | C19: 0.4368579 | D19: 3.8258573 | E19: 7.5405187 | F19: 17.627647 | G19: 24.990997 | H19: 24.592365
A20: Despesa financiada por empréstimos | B20: Expenditure financed by loans | C20: 0 | D20: 0.020952879 | E20: 0.25416966 | F20: 1.5123091 | G20: 7.2633518 | H20: 11.934973
A22: Fontes: INE, Ministério das Finanças e Banco de Portugal.
A23: Sources: Statistics Portugal, Ministry of Finance and Banco de Portugal.

Sheet GI.2.7
A5: Índice/Contents
A6: Boletim Económico - Junho 2024/Economic Bulletin - June 2024
A7: =+Índice!$A$50 -> Parte I.2 Análise e projeções de finanças públicas/Part I.2 Analysis and projections of public finances
A10: Gráfico I.2.7 Investimento público em Portugal | Em percentagem do PIB
A11: Chart I.2.7 · Public investment in Portugal | Percentage of GDP
A15: Unidade/Unit | C15: % do PIB | D15: % do PIB | E15: % do PIB | F15: % do PIB | G15: % do PIB | H15: % do PIB | I15: % do PIB | J15: % do PIB | K15: % do PIB | L15: % do PIB | M15: % do PIB
C16: % of GDP | D16: % of GDP | E16: % of GDP | F16: % of GDP | G16: % of GDP | H16: % of GDP | I16: % of GDP | J16: % of GDP | K16: % of GDP | L16: % of GDP | M16: % of GDP
C18: 2016 | D18: 2017 | E18: 2018 | F18: 2019 | G18: 2020 | H18: 2021 | I18: 2022 | J18: 2023 | K18: 2024(p) | L18: 2025(p) | M18: 2026(p)
A19: Excluindo PRR | B19: Excluding RRP | C19: 1.5417277 | D19: 1.7843908 | E19: 1.8472014 | F19: 1.8213052 | G19: 2.3149359 | H19: 2.5740582 | I19: 2.2618954 | J19: 2.4024687 | K19: 2.2533564 | L19: 2.3819829 | M19: 2.41624
A20: Excl. PRR e outros fundos da UE | B20: Excl. RRP and other EU funds | C20: 1.005807 | D20: 1.2505946 | E20: 1.2770734 | F20: 1.2842608 | G20: 1.656471 | H20: 1.7977733 | I20: 1.6513485 | J20: 1.773785 | K20: 1.773785 | L20: 1.773785 | M20: 1.773785
A21: Total | B21: Total | C21: 1.5417277 | D21: 1.7843908 | E21: 1.8472014 | F21: 1.8213052 | G21: 2.3149359 | H21: 2.5844064 | I21: 2.3822269 | J21: 2.5396369 | K21: 2.964621 | L21: 3.2601541 | M21: 3.4316056
A23: Fontes: INE e Banco de Portugal. | Nota: Os valores entre parêntesis correspondem às taxas de variação do investimento público total, em termos nominais.
A24: Sources: Statistics Portugal and Banco de Portugal. | Note: The values in parentheses correspond to the rates of change in total public investment, in nominal terms.

Sheet GI.2.8
A5: Índice/Contents
A6: Boletim Económico - Junho 2024/Economic Bulletin - June 2024
A7: =+Índice!$A$50 -> Parte I.2 Análise e projeções de finanças públicas/Part I.2 Analysis and projections of public finances
A10: Gráfico I.2.8 Dívida pública observada e projetada em Portugal e na área do euro | Em percentagem do PIB
A11: Chart I.2.8 · Public debt observed and projected in Portugal and the euro area | Percentage of GDP
A15: Unidade/Unit | C15: % PIB | D15: % PIB | E15: % PIB
C16: % GDP | D16: % GDP | E16: % GDP
C18: 2019 | D18: 2023 | E18: 2025(p)
A20: EE | B20: EE | C20: 8.5 | D20: 19.6 | E20: 24.6
A21: LU | B21: LU | C21: 22.4 | D21: 25.7 | E21: 28.5
A22: LT | B22: LT | C22: 35.8 | D22: 38.3 | E22: 41.6
A23: LV | B23: LV | C23: 36.7 | D23: 43.6 | E23: 46.3
A24: IE | B24: IE | C24: 57.1 | D24: 43.7 | E24: 41.3
A25: NL | B25: NL | C25: 48.6 | D25: 46.5 | E25: 48.4
A26: MT | B26: MT | C26: 40 | D26: 50.4 | E26: 52.6
A27: SK | B27: SK | C27: 48 | D27: 56 | E27: 59.9
A28: HR | B28: HR | C28: 70.4 | D28: 63 | E28: 59.1
A29: DE | B29: DE | C29: 59.6 | D29: 63.6 | E29: 62.2
A30: SI | B30: SI | C30: 65.4 | D30: 69.2 | E30: 66.4
A31: FI | B31: FI | C31: 64.9 | D31: 75.8 | E31: 82.4
... A40: EL | B40: EL | C40: 180.6 | D40: 161.9 | E40: 149.3
A42: Fontes: Banco de Portugal (Portugal) e Comissão Europeia (restantes países e agregado da área do euro). | Notas: Os países estão ordenados pelo rácio da dívida de 2023. Os valores projetados pela Comissão Europeia para Portugal são 95,6% do PIB em 2024 e 91,5% em 2025.
A43: Sources: Banco de Portugal (Portugal) and European Commission (remaining countries and euro area aggregate). | Notes: Countries are ordered by the 2023 debt ratio. The values ​​projected by the European Commission for Portugal are 95,4% in 2024 and 91.5% of GDP in 2025.

Sheet GI.2.9
A5: Índice/Contents
A6: Boletim Económico - Junho 2024/Economic Bulletin - June 2024
A7: =+Índice!$A$50 -> Parte I.2 Análise e projeções de finanças públicas/Part I.2 Analysis and projections of public finances
A10: Gráfico I.2.9 Contributos para a variação do rácio da dívida pública | Em pontos percentuais do PIB
A11: Chart I.2.9 · Breakdown of the change in the debt ratio | In percentage points of GDP
A15: Unidade/Unit | C15: pp do PIB | D15: pp do PIB | E15: pp do PIB | F15: pp do PIB
C16: pp of GDP | D16: pp of GDP | E16: pp of GDP | F16: pp of GDP
C18: 2023 | D18: 2024(p) | E18: 2025(p) | F18: 2026(p)
A19: Despesa em juros | B19: Interest expenditure | C19: 2.1663119 | D19: 2.2771539 | E19: 2.1991909 | F19: 2.1243756
A20: Efeito do saldo primário | B20: Effect of primary balance | C20: -3.3691249 | D20: -3.315332 | E20: -2.9784969 | F20: -2.7682076
A21: Ajustamentos défice-dívida | B21: Deficit-debt adjustments | C21: -2.315946 | D21: 0 | E21: 0 | F21: 0
A22: Efeito denominador: deflator | B22: Denominator effect: deflator | C22: -7.3211579 | D22: -3.5862811 | E22: -2.4128927 | F22: -2.0124314
A23: Efeito denominador: volume | B23: Denominator effect: volume | C23: -2.4857781 | D23: -1.9783433 | E23: -2.0738104 | F23: -1.9056783
A24: Variação da dívida | B24: Change in debt | C24: -13.325695 | D24: -6.6028025 | E24: -5.2660092 | F24: -4.5619417
A27: Fontes: INE e Banco de Portugal. | Notas: Na projeção, assume-se a hipótese técnica de ajustamentos défice-dívida nulos. A diferença entre as despesas em juros e o efeito denominador total corresponde ao ‘efeito bola de neve’.
A28: Sources: Statistics Portugal and Banco de Portugal. | Notes:The projection considers a technical assumption of zero deficit-debt adjustments. The difference between interest expenditure and the total denominator effect corresponds to the ‘snowball effect’.

Sheet GC.5.1
A4: Índice/Contents
A5: Boletim Económico - Junho 2024/Economic Bulletin - June 2024
A6: =+Índice!A70 -> Caixa 5 - O referencial para a despesa pública utilizado nas regras orçamentais europeias e as medidas de política orçamental para os próximos anos/Box 5 - The expenditure benchmark used in European fiscal rules and the budgetary policy measures for the coming years
A10: Gráfico C5.1 Referencial para a despesa pública observado e PIB potencial nominal em Portugal | Taxas de variação em percentagem
A11: Chart B5.1 Expenditure benchmark observed and nominal potential GDP in Portugal | Percentage rates of change
A14: Unidade/Unit | C14: Taxa de var. % | D14: Taxa de var. % | E14: Taxa de var. % | F14: Taxa de var. % | G14: Taxa de var. % | H14: Taxa de var. % | I14: Taxa de var. % | J14: Taxa de var. % | K14: Taxa de var. %
C15: Rate of change % | D15: Rate of change % | E15: Rate of change % | F15: Rate of change % | G15: Rate of change % | H15: Rate of change % | I15: Rate of change % | J15: Rate of change % | K15: Rate of change %
C17: 2015 | D17: 2016 | E17: 2017 | F17: 2018 | G17: 2019 | H17: 2020 | I17: 2021 | J17: 2022 | K17: 2023
A18: Referencial para a despesa pública | B18: Expenditure benchmark | C18: 0.080630012 | D18: 1.4683299 | E18: 2.5115155 | F18: 4.9700201 | G18: 4.0451291 | H18: 9.7028419 | I18: 4.4142959 | J18: 7.292317 | K18: 4.1492823
A19: PIB potencial nominal | B19: Nominal potencial GDP | C19: 2.4666854 | D19: 2.6589965 | E19: 3.0466481 | F19: 3.5459841 | G19: 3.5055878 | H19: 3.3145737 | I19: 4.0730944 | J19: 6.9814819 | K19: 9.4345607
A21: Fontes: Comissão Europeia e cálculos do Banco de Portugal. | Notas: O referencial para a despesa pública é definido como a despesa primária líquida de medidas discricionárias do lado da receita, de programas de despesa financiados por fundos europeus, da componente cíclica dos subsídios de desemprego e de medidas temporárias, classificadas de acordo com a definição da Comissão Europeia. O investimento público financiado nacionalmente é alisado com uma média de quatro anos: o ano corrente e os três anteriores. O PIB potencial nominal é o calculado pela Comissão Europeia.
A22: Sources: European Commission and Banco de Portugal calculations. | Notes: The expenditure benchmark is defined as primary expenditure net of discretionary revenue measures, expenditure programmes financed by European funds, the cyclical component of unemployment benefits, and temporary measures, classified according to the definition of the European Commission. Nationally financed public investment is smoothed with a four-year average: the current year and the three previous years. Nominal potential GDP is calculated by the European Commission.

Sheet QC.5.1
A5: Índice/Contents
A6: Boletim Económico - Junho 2024/Economic Bulletin - June 2024
A7: =+Índice!$A$70 -> Caixa 5 - O referencial para a despesa pública utilizado nas regras orçamentais europeias e as medidas de política orçamental para os próximos anos/Box 5 - The expenditure benchmark used in European fiscal rules and the budgetary policy measures for the coming years
A10: Quadro C5.1 Referencial da despesa usado nas regras orçamentais em 2025 | Em milhões de euros
A11: Table B5.1 · Expenditure benchmark used in the fiscal rules in 2025 | Million euros
A15: Unidade/Unit | C15: Milhões de euros
C16: Million euros
A18: (1) Margem para a variação do referencial da despesa | B18: (1) Margin for the change of the expenditure benchmark | C18: 5385
A19: (função da despesa relevante e definida com a taxa de crescimento do PIB potencial nominal) | B19: (function of the relevant expenditure and defined with the growth rate of nominal potential GDP)
A22: (2) Variação das componentes da despesa | B22: (2) Change in expenditure components | C22: =C29+C34 -> 5635
A23: Variação resultante da dinâmica regular da despesa e de compromissos anteriores | B23: Change resulting from the regular dynamics of expenditure and previous commitments
A24: Despesas com pessoal | B24: Compensation of employees | C24: 1050
A25: Pensões e outras prestações sociais em dinheiro | B25: Pensions and other social payments in cash | C25: 1900
A26: Consumo intermédio e prestações sociais em espécie | B26: Intermediate consumption and social payments in kind | C26: 1100
A27: Média do investimento com financiamento nacional(a) | B27: Average of investment with national financing(a) | C27: 470
A28: Outra despesa corrente e de capital(a) | B28: Other current and capital expenditure(a) | C28: 650
A29: Sub-total | B29: Sub-total | C29: =SUM(C24:C28) -> 5170
A30: Novas medidas com quantificação oficial, fora do Orçamento, com efeitos em 2025 | B30: New measures with official quantification, outside the Budget, with effects in 2025
A31: Expansão do CSI(b) | B31: Expansion of the solidarity supplement for the elderly(b) | C31: 220
A32: Apoio aos jovens(b) | B32: Support for the young(b) | C32: 85
A33: Revisão das carreiras: Professores(b) | B33: Career revision: Teachers(b) | C33: 160
A34: Sub-total | B34: Sub-total | C34: =SUM(C31:C33) -> 465
A36: (3) Variação discricionária da receita | B36: (3) Discretionary revenue change | C36: =C40+C43+C49 -> -1820
A37: Medidas orçamentadas em 2024, já implementadas, mas com efeitos em 2025 | B37: Budgeted measures in 2024, already implemented, but with effects in 2025
A38: Redução do IRS (efeito desfasado) | B38: Reduction of personal income tax (lagged effect) | C38: -575
A39: IRC: fim dos créditos fiscais | B39: Corporate income tax: end of tax credits | C39: 75
A40: Sub-total | B40: Sub-total | C40: =SUM(C38:C39) -> -500
A41: Medidas orçamentadas em 2024, não implementadas, com potenciais efeitos em 2025 | B41: Budgeted measures in 2024, not implemented, with potential effects in 2025
A42: Aumento do ISP (requer Portaria a atualizar o valor) | B42: Increase in the tax on oil products (requires a Ministerial Order to update the value) | C42: 445
A43: Sub-total | B43: Sub-total | C43: =SUM(C41:C42) -> 445
A44: Novas medidas com quantificação oficial, fora do Orçamento, com efeitos em 2025 | B44: New measures with official quantification, outside the Budget, with effects in 2025
A45: Redução do IRS Jovem + Isenção de IMT e Imposto do Selo(b) | B45: Reduction of personal income tax for the young + Exemption from property transfer tax and stamp duty(b) | C45: -1100
A46: Redução geral do IRS(b) | B46: General reduction of personal income tax(b) | C46: -465
A47: Redução do IVA da electricidade | B47: Reduction of VAT on electricity | C47: -90
A48: Redução das portagens nas ex-SCUTS | B48: Reduction of tolls on former SCUT roads | C48: -110
A49: Sub-total | B49: Sub-total | C49: =SUM(C45:C48) -> -1765
A51: (4) Variação do referencial da despesa (2) - (3) | B51: (4) Change in the expenditure benchmark (2) - (3) | C51: =+C22-C36 -> 7455
A54: (5) Hiato entre a margem e a variação do referencial da despesa (1) - (4) | B54: (5) Gap between the margin and the change in the expenditure benchmark (1) - (4) | C54: =C18-C51 -> -2070
A55: Em percentagem do PIB | B55: In percentage of GDP | C55: -0.70017037
A58: Memo: Novas medidas sem quantificação oficial não incluídas nos cálculos | B58: Memo: New measures without official quantification, not included in the calculations
A59: Revisão das carreiras: | B59: Career revisions:
A60: Forças de segurança, guardas prisionais e militares | B60: Security forces, prison guards and military personnel
A61: Saúde | B61: Health
A62: Justiça | B62: Justice
A63: Plano de emergência da saúde | B63: Health emergency plan
A64: Apoios à habitação | B64: Housing support
A67: Fonte: Cálculos do Banco de Portugal. | Notas: a) Os empréstimos do PRR não são corrigidos, implicando um aumento dos contributos da outra despesa de capital e do investimento público, embora em menor medida no último caso pelo alisamento com a média de 4 anos. b) Medidas em que poderá observar-se algum impacto orçamental já em 2024.
A68: Source: Banco de Portugal calculations. | Notes: The loans from the Recovery and Resilience Plan (RRP) are not corrected, implying an increase in contributions from other capital expenditure and public investment, albeit to a lesser extent in the latter case due to smoothing with a 4-year average. (b) Measures where some budgetary impact may be observed as early as 2024.
A83: Fontes: INE e Banco de Portugal. | Notas: Na projeção, assume-se a hipótese técnica de ajustamentos défice-dívida nulos. A diferença entre as despesas em juros e o efeito denominador total corresponde ao ‘efeito bola de neve’.
A84: Sources: Statistics Portugal and Banco de Portugal. | Notes:The projection considers a technical assumption of zero deficit-debt adjustments. The difference between interest expenditure and the total denominator effect corresponds to the ‘snowball effect’.

Sheet GC.6.1
A4: Índice/Contents
A5: Boletim Económico - Junho 2024/Economic Bulletin - June 2024
A6: =+Índice!A76 -> Caixa 6 - O efeito direto da inflação e da progressividade sobre a receita fiscal e contributiva/Box 6 - The direct effect of inflation and progressivity on tax and social contributions revenue
A10: Gráfico C6.1 Decomposição da variação da receita fiscal e contributiva em 2022–2026 | Em milhões de euros
A11: Chart B6.1 Breakdown of the change in tax and social contributions revenue in 2022-2026 | Million euros
A13: Unidade/Unit | C13: Milhões de euros | D13: Milhões de euros | E13: Milhões de euros | F13: Milhões de euros | G13: Milhões de euros
C14: Million euros | D14: Million euros | E14: Million euros | F14: Million euros | G14: Million euros
C17: 2022 | D17: 2023 | E17: 2024 | F17: 2025 | G17: 2026
A19: Variação total da receita | B19: Change in total revenue | C19: 11154.29 | D19: 7947.884 | E19: 5486.7114 | F19: 4963.3047 | G19: 5018.8382
A20: Efeito das alterações legislativas | B20: Impact of legislation changes | C20: -427.83471 | D20: -2610.2915 | E20: -1529.0016 | F20: -597.83732 | G20: -189.34911
A21: Impacto do aumento da inflação | B21: Impact of the increase in inflation | C21: 2635.0701 | D21: 3651.1626 | E21: 824.28417 | F21: -311.40864 | G21: -503.83298
A22: Receita esperada sem aumento da inflação | B22: Expected revenue without the increase in inflation | C22: 7645.9528 | D22: 6184.7102 | E22: 6502.32 | F22: 6515.5725 | G22: 6334.5169
A23: Por explicar (resíduo/julgamento) | B23: To be explained (residual/judgement) | C23: 1301.1018 | D23: 722.30266 | E23: -310.8912 | F23: -643.02178 | G23: -622.4966
A26: Fonte: Cálculos do Banco de Portugal.
A27: Source: Banco de Portugal calculations.

Sheet GC.6.2
A4: Índice/Contents
A5: Boletim Económico - Junho 2024/Economic Bulletin - June 2024
A6: =+Índice!A76 -> Caixa 6 - O efeito direto da inflação e da progressividade sobre a receita fiscal e contributiva/Box 6 - The direct effect of inflation and progressivity on tax and social contributions revenue
A10: Gráfico C6.2 Impacto do aumento da inflação por imposto em 2022-2026 | Em milhões de euros
A11: Chart B6.2 Impact of the increase in inflation by tax 2022-2026 | In million euros
A13: Unidade/Unit | C13: Milhões de euros | D13: Milhões de euros | E13: Milhões de euros | F13: Milhões de euros | G13: Milhões de euros
C14: Million euros | D14: Million euros | E14: Million euros | F14: Million euros | G14: Million euros
C17: 2022 | D17: 2023 | E17: 2024 | F17: 2025 | G17: 2026
A19: IRS | B19: Personal income tax | C19: 424.76104 | D19: 830.84076 | E19: 83.591182 | F19: -310.4377 | G19: -375.46709
A20: IRC | B20: Corporate income tax | C20: 359.62493 | D20: 860.39522 | E20: 363.38375 | F20: 169.81369 | G20: 106.36624
A21: IVA | B21: VAT | C21: 1642.8586 | D21: 1126.1861 | E21: 341.72289 | F21: 223.86969 | G21: 215.63457
A22: Outros dir. e ind. | B22: Other dir. and ind. | C22: 60.580212 | D22: 104.47338 | E22: 39.82488 | F22: 18.167388 | G22: 11.585463
A23: CSS | B23: Social contributions | C23: 147.24533 | D23: 729.26709 | E23: -4.238524 | F23: -412.82171 | G23: -461.95216
A24: Total | B24: Total | C24: 2635.0701 | D24: 3651.1626 | E24: 824.28417 | F24: -311.40864 | G24: -503.83298
A26: Fonte: Cálculos do Banco de Portugal.
A27: Source: Banco de Portugal calculations.

Sheet GC.6.3
A4: Índice/Contents
A5: Boletim Económico - Junho 2024/Economic Bulletin - June 2024
A6: =+Índice!A76 -> Caixa 6 - O efeito direto da inflação e da progressividade sobre a receita fiscal e contributiva/Box 6 - The direct effect of inflation and progressivity on tax and social contributions revenue
A10: Gráfico C6.3 Impacto da progressividade do IRS na receita| Em milhões de euros
A11: Chart B6.3 Impact of personal income tax progressivity on revenue | Million euros
A13: Unidade/Unit | C13: Milhões de euros | D13: Milhões de euros | E13: Milhões de euros | F13: Milhões de euros | G13: Milhões de euros
C14: Million euros | D14: Million euros | E14: Million euros | F14: Million euros | G14: Million euros
C17: 2022 | D17: 2023 | E17: 2024 | F17: 2025 | G17: 2026
A20: Impacto total | B20: Total impact | C20: 702.38274 | D20: 1012.7262 | E20: 764.67548 | F20: 492.57524 | G20: 501.69237
A21: Limites dos escalões | B21: Brackets limits | C21: 436.33154 | D21: 629.12193 | E21: 475.0288 | F21: 305.99572 | G21: 311.65943
A22: Outros parâmetros | B22: Other parameters | C22: 266.0512 | D22: 383.60427 | E22: 289.64668 | F22: 186.57952 | G22: 190.03294
A24: Total após atualização efetiva de parâmetros | B24: Total after actual update of parameters | C24: 702.38274 | D24: 712.7262 | E24: 497.67548 | F24: 492.57524 | G24: 501.69237
A29: Fonte: Cálculos do Banco de Portugal baseados em simulações do EUROMOD e nos dados do EU-SILC. | Nota: Em 2022, não se apresenta o impacto após a atualização efetiva de parâmetros, dado que as alterações aos limites dos escalões decorreram essencialmente da reestruturação da tabela, com a introdução de novos escalões. O impacto da progressividade foi calculado usando o sistema de impostos e benefícios de 2022 para Portugal, usando o modelo EUROMOD, disponível em https://euromod-web.jrc.ec.europa.eu/. Para mais detalhes relativos à modelização do IRS para Portugal ver EUROMOD Country report — Portugal 2020–2023.
A30: Source: Banco de Portugal calculations based on EUROMOD simulations and EU-SILC data. | Note: In 2022, the impact after the actual update of parameters is not shown given that the changes in bracket limits were mainly driven by a restructuring of the PIT table, with the introduction of new brackets. The impact of tax progressivity was calculated using the EUROMOD tax and benefit system for Portugal in 2022 available in https://euromod-web.jrc.ec.europa.eu/. For more details regarding PIT modelling in EUROMOD for Portugal see EUROMOD Country report — Portugal 2020–2023.

Sheet GC.7.1
A4: Índice/Contents
A5: Boletim Económico - Junho 2024/Economic Bulletin - June 2024
A6: =+Índice!A84 -> Caixa 7 - Trajetórias para a dívida pública portuguesa/Box 7 - Trajectories for Portuguese public debt
A10: Gráfico C7.1 Rácio da dívida pública: nível e decomposição da variação | Em percentagem e pontos percentuais do PIB
A11: Chart B7.1 Public debt ratio: level and breakdown of the change | In percentage and percentage points of GDP
C13: Unidade/Unit
D18: 2001 | E18: 2002 | F18: 2003 | G18: 2004 | H18: 2005 | I18: 2006 | J18: 2007 | K18: 2008 | L18: 2009 | M18: 2010 | N18: 2011 | O18: 2012 | P18: 2013 | Q18: 2014 | R18: 2015 | S18: 2016 | T18: 2017 | U18: 2018 | V18: 2019 | W18: 2020 | X18: 2021 | Y18: 2022 | Z18: 2023 | AA18: 2024 | AB18: 2025 | AC18: 2026 | AD18: 2027 | AE18: 2028 | AF18: 2029 | AG18: 2030 | AH18: 2031 | AI18: 2032 | AJ18: 2033
A19: Rácio da dívida (esc. dir.) | B19: Debt ratio (rhs) | C19: % do PIB / % of GDP
D20: 57.380219 | E20: 60.043717 | F20: 63.897284 | G20: 67.099504 | H20: 72.249078 | I20: 73.679394 | J20: 72.727965 | K20: 75.642544 | L20: 87.79906 | M20: 100.21448 | N20: 114.40307 | O20: 129.03504 | P20: 131.42974 | Q20: 132.94068 | R20: 131.17912 | S20: 131.50573 | T20: 126.14343 | U20: 121.48136 | V20: 116.60778 | W20: 134.89747 | X20: 124.54758 | Y20: 112.41492 | Z20: 99.089226 | AA20: 92.491105 | AB20: 87.171177 | AC20: 82.559618 | AD20: 79.193522 | AE20: 76.514745 | AF20: 74.380962 | AG20: 72.61984 | AH20: 70.953506 | AI20: 69.593116 | AJ20: 68.526253
A21: Var. total | B21: Total change | C21: pp | D21: 3.1871077 | E21: 2.6634985 | F21: 3.8535663 | G21: 3.2022204 | H21: 5.1495744 | I21: 1.4303158 | J21: -0.95142925 | K21: 2.9145789 | L21: 12.156516 | M21: 12.415425 | N21: 14.188588 | O21: 14.631971 | P21: 2.3947008 | Q21: 1.5109353 | R21: -1.761556 | S21: 0.3266072 | T21: -5.3622986 | U21: -4.6620718 | V21: -4.8735801 | W21: 18.289686 | X21: -10.349887 | Y21: -12.13266 | Z21: -13.325695 | AA21: -6.598121 | AB21: -5.3199277 | AC21: -4.6115594 | AD21: -3.3660957 | AE21: -2.6787775 | AF21: -2.1337822 | AG21: -1.7611222 | AH21: -1.6663339 | AI21: -1.36039 | AJ21: -1.066863
A22: (-) Saldo primário | B22: (-) Primary balance | C22: pp | D22: 1.7993633 | E22: 0.49661763 | F22: 2.9963686 | G22: 3.6159031 | H22: 3.5624967 | I22: 1.3978434 | J22: -0.067703411 | K22: 0.57981912 | L22: 6.8856471 | M22: 8.4572701 | N22: 3.3421196 | O22: 1.3055823 | P22: 0.27378895 | Q22: 2.4762847 | R22: -0.13591882 | S22: -2.2147576 | T22: -0.81993969 | U22: -3.0150861 | V22: -3.0653825 | W22: 2.9334348 | X22: 0.47412242 | Y22: -1.603145 | Z22: -3.3691249 | AA22: -3.3154524 | AB22: -2.9821837 | AC22: -2.7837497 | AD22: -2.5655034 | AE22: -2.3200034 | AF22: -2.0745034 | AG22: -1.8290034 | AH22: -1.6127412 | AI22: -1.4121022 | AJ22: -1.2121022
A23: Juros | B23: Interest | C23: pp | D23: 2.9905025 | E23: 2.8377643 | F23: 2.6596741 | G23: 2.5676538 | H23: 2.5678197 | I23: 2.7826489 | J23: 2.9669267 | K23: 3.1197636 | L23: 2.986918 | M23: 2.9411236 | N23: 4.321101 | O23: 4.8741815 | P23: 4.8307199 | Q23: 4.879737 | R23: 4.5847021 | S23: 4.1497806 | T23: 3.7759548 | U23: 3.3640707 | V23: 2.950053 | W23: 2.8859704 | X23: 2.4026128 | Y23: 1.9246465 | Z23: 2.1663119 | AA23: 2.277268 | AB23: 2.1980806 | AC23: 2.1222702 | AD23: 2.0791612 | AE23: 2.0581843 | AF23: 2.055695 | AG23: 2.0605608 | AH23: 2.0617074 | AI23: 2.1066318 | AJ23: 2.15623
A24: Efeito do crescimento nominal | B24: Nominal growth effect | C24: pp | D24: -2.9378887 | E24: -2.7287509 | F24: -1.4443239 | G24: -2.593913 | H24: -2.6679865 | I24: -3.3494367 | J24: -3.8723893 | K24: -1.4697155 | L24: 1.5896141 | M24: -2.0503184 | N24: 2.0001266 | O24: 5.302652 | P24: -1.6625462 | Q24: -1.9453329 | R24: -4.9262626 | S24: -4.7667766 | T24: -6.3471288 | U24: -5.6786852 | V24: -5.208051 | W24: 8.0575441 | X24: -9.6992055 | Y24: -13.510135 | Z24: -9.806936 | AA24: -5.5599367 | AB24: -4.5358245 | AC24: -3.9500799 | AD24: -2.8797534 | AE24: -2.4169584 | AF24: -2.1149738 | AG24: -1.9926796 | AH24: -2.1153001 | AI24: -2.0549196 | AJ24: -2.0109908
A25: Ajustamentos défice-dívida | B25: Deficit-debt adjustments | C25: pp | D25: 1.3351307 | E25: 2.0578675 | F25: -0.35815248 | G25: -0.38742354 | H25: 1.6872445 | I25: 0.59926025 | J25: 0.021736746 | K25: 0.68471169 | L25: 0.69433706 | M25: 3.0673496 | N25: 4.525241 | O25: 3.1495551 | P25: -1.0472619 | Q25: -3.8997534 | R25: -1.2840767 | S25: 3.1583609 | T25: -1.9711849 | U25: 0.66762874 | V25: 0.44980036 | W25: 4.4127368 | X25: -3.5274163 | Y25: 1.0559742 | Z25: -2.315946 | AA25: 0 | AB25: 0 | AC25: 0 | AD25: 6.2172489e-15 | AE25: 8.437695e-15 | AF25: -1.8207658e-14 | AG25: 6.6613381e-15 | AH25: -7.1054274e-15 | AI25: 0 | AJ25: 1.7763568e-15
A27: Fonte: Cálculos do Banco de Portugal.
A28: Source: Banco de Portugal calculations.

Sheet GC.7.2
A4: Índice/Contents
A5: Boletim Económico - Junho 2024/Economic Bulletin - June 2024
A6: =+Índice!A84 -> Caixa 7 - Trajetórias para a dívida pública portuguesa/Box 7 - Trajectories for Portuguese public debt
A10: Gráfico C7.2 Resultados da análise determinística para as principais variáveis | Em percentagem e percentagem do PIB
A11: Chart B7.2 Deterministic analysis results for the main variables | In percentage and percentage of GDP
C13: Unidade/Unit
D16: 2015 | E16: 2016 | F16: 2017 | G16: 2018 | H16: 2019 | I16: 2020 | J16: 2021 | K16: 2022 | L16: 2023 | M16: 2024 | N16: 2025 | O16: 2026 | P16: 2027 | Q16: 2028 | R16: 2029 | S16: 2030 | T16: 2031 | U16: 2032 | V16: 2033
A17: Saldo orçamental | B17: Budget balance
A18: Cenário base | B18: Baseline scenario | C18: % do PIB / % of GDP | D18: -4.4487833 | E18: -1.935023 | F18: -2.9560151 | G18: -0.3489846 | H18: 0.11532942 | I18: -5.8194052 | J18: -2.8767352 | K18: -0.32150149 | L18: 1.202813 | M18: 1.0381843 | N18: 0.78410314 | O18: 0.66147947 | P18: 0.48634229 | Q18: 0.26181912 | R18: 0.018808403 | S18: -0.23155739 | T18: -0.44896619 | U18: -0.69452961 | V18: -0.94412783
A19: Choque 'saldo primário' | B19: 'Primary balance' shock | C19: % do PIB / % of GDP | L19: 1.202813 | M19: 0.24308735 | N19: -1.1117983 | O19: -2.2276336 | P19: -2.5150724 | Q19: -2.8404606 | R19: -2.9824808 | S19: -3.0164292 | T19: -2.9963723 | U19: -2.992371 | V19: -2.9708569
A20: Choque 'PIB' | B20: 'GDP' shock | C20: % do PIB / % of GDP | L20: 1.202813 | M20: 1.062038 | N20: -0.31525973 | O20: -1.6262633 | P20: -1.6848428 | Q20: -1.6381457 | R20: -1.5932634 | S20: -1.5379736 | T20: -1.4335403 | U20: -1.3399124 | V20: -1.2293623
A21: Choque 'taxa de juro' | B21: 'Interest rate' shock | C21: % do PIB / % of GDP | L21: 1.202813 | M21: 0.78118783 | N21: 0.34524695 | O21: 0.17664078 | P21: 0.012918631 | Q21: -0.18135754 | R21: -0.39380174 | S21: -0.61333695 | T21: -0.7986063 | U21: -1.0227466 | V21: -1.2516456
A23: Taxa de juro implícita | B23: Implicit interest rate
A24: Cenário base | B24: Baseline scenario | C24: % | D24: 3.5813951 | E24: 3.2827336 | F24: 3.0169359 | G24: 2.7925769 | H24: 2.5371713 | I24: 2.3149745 | J24: 1.9190464 | K24: 1.7333311 | L24: 2.1112508 | M24: 2.4348181 | N24: 2.4990888 | O24: 2.5501589 | P24: 2.6093934 | Q24: 2.6807456 | R24: 2.7630395 | S24: 2.8465392 | T24: 2.9242194 | U24: 3.0575835 | V24: 3.190533
A25: Choque 'saldo primário' | B25: 'Primary balance' shock | C25: % | L25: 2.1112508 | M25: 2.4803967 | N25: 2.6988744 | O25: 2.8575653 | P25: 2.9447039 | Q25: 3.0442788 | R25: 3.1426163 | S25: 3.2229718 | T25: 3.280774 | U25: 3.3752255 | V25: 3.4497946
A26: Choque 'PIB' | B26: 'GDP' shock | C26: % | L26: 2.1112508 | M26: 2.4348181 | N26: 2.6241806 | O26: 2.7630676 | P26: 2.8213465 | Q26: 2.8781755 | R26: 2.9319814 | S26: 2.9731781 | T26: 2.9972182 | U26: 3.0587386 | V26: 3.1052125
A27: Choque 'taxa de juro' | B27: 'Interest rate' shock | C27: % | L27: 2.1112508 | M27: 2.7349247 | N27: 3.0128021 | O27: 3.1313254 | P27: 3.1600263 | Q27: 3.1946063 | R27: 3.2345108 | S27: 3.2717045 | T27: 3.2999872 | U27: 3.3944333 | V27: 3.4872049
A29: Hiato do produto | B29: Output-gap
A30: Cenário base | B30: Baseline scenario | C30: % | D30: -2.7360602 | E30: -2.0364976 | F30: -0.33003027 | G30: 0.77784735 | H30: 1.5711347 | I30: -6.730348 | J30: -2.866665 | K30: 1.4814533 | L30: 1.6425428 | M30: 0.92410023 | N30: 0.83061483 | O30: 0.81278007 | P30: 0.61278007 | Q30: 0.41278007 | R30: 0.21278007 | S30: 0.012780066 | T30: 0 | U30: 0 | V30: 0
A31: Choque 'PIB' | B31: 'GDP' shock | C31: % | L31: 1.6425428 | M31: 0.92410023 | N31: -1.1355504 | O31: -3.0823343 | P31: -2.7317029 | Q31: -2.3777265 | R31: -2.0212197 | S31: -1.6633186 | T31: -1.1207177 | U31: -0.56232025 | V31: -0.00073175335
A33: Dívida pública | B33: Public debt
A34: Cenário base | B34: Baseline scenario | C34: % do PIB / % of GDP | D34: 131.17912 | E34: 131.50573 | F34: 126.14343 | G34: 121.48136 | H34: 116.60778 | I34: 134.89747 | J34: 124.54758 | K34: 112.41492 | L34: 99.089226 | M34: 92.491105 | N34: 87.171177 | O34: 82.559618 | P34: 79.193522 | Q34: 76.514745 | R34: 74.380962 | S34: 72.61984 | T34: 70.953506 | U34: 69.593116 | V34: 68.526253
A35: Choque 'saldo primário' | B35: 'Primary balance' shock | C35: % do PIB / % of GDP | L35: 99.089226 | M35: 93.286202 | N35: 89.823184 | O35: 87.980564 | P35: 87.426796 | Q35: 87.599021 | R35: 88.160143 | S35: 88.814746 | T35: 89.224087 | U35: 89.632395 | V35: 90.013198
A36: Choque 'PIB' | B36: 'GDP' shock | C36: % do PIB / % of GDP | L36: 99.089226 | M36: 92.467251 | N36: 89.996614 | O36: 89.255107 | P36: 87.345851 | Q36: 85.843465 | R36: 84.594529 | S36: 83.402853 | T36: 81.952368 | U36: 80.471938 | V36: 78.937085
A37: Choque 'taxa de juro' | B37: 'Interest rate' shock | C37: % do PIB / % of GDP | L37: 99.089226 | M37: 92.748101 | N37: 87.854427 | O37: 83.696745 | P37: 80.764409 | Q37: 78.480865 | R37: 76.705347 | S37: 75.263734 | T37: 73.870027 | U37: 72.753388 | V37: 71.902722
A39: Fonte: Cálculos do Banco de Portugal. | Nota: Nos cenários choque ‘saldo primário’ e choque ‘taxa de juro’ assume-se que não existe reação do PIB.
A40: Source: Banco de Portugal calculations. | Note: In the 'primary balance' and 'interest rate' shock scenarios, it is assumed that there is no reaction of GDP.

Sheet GC.7.3
A4: Índice/Contents
A5: Boletim Económico - Junho 2024/Economic Bulletin - June 2024
A6: =+Índice!A84 -> Caixa 7 - Trajetórias para a dívida pública portuguesa/Box 7 - Trajectories for Portuguese public debt
A10: Gráfico C7.3 Trajetórias para o rácio da dívida pública de acordo com a análise estocástica | Em percentagem do PIB
A11: Chart B7.3 Public debt ratio trajectories based on the stochastic analysis | In percentage of GDP
C13: Unidade/Unit
D16: 2015 | E16: 2016 | F16: 2017 | G16: 2018 | H16: 2019 | I16: 2020 | J16: 2021 | K16: 2022 | L16: 2023 | M16: 2024 | N16: 2025 | O16: 2026 | P16: 2027 | Q16: 2028 | R16: 2029 | S16: 2030 | T16: 2031 | U16: 2032 | V16: 2033
A17: Dívida pública | B17: Public debt | C17: % do PIB / % of GDP | D17: 131.17912 | E17: 131.50573 | F17: 126.14343 | G17: 121.48136 | H17: 116.60778 | I17: 134.89747 | J17: 124.54758 | K17: 112.41492 | L17: 99.089226
A18: Cenário base | B18: Baseline scenario | C18: % do PIB / % of GDP | L18: 99.089226 | M18: 92.491105 | N18: 87.171177 | O18: 82.559618 | P18: 79.193522 | Q18: 76.514745 | R18: 74.380962 | S18: 72.61984 | T18: 70.953506 | U18: 69.593116 | V18: 68.526253
A19: Mediana | B19: Median | C19: % do PIB / % of GDP | L19: 99.089226 | M19: 92.76098 | N19: 85.606655 | O19: 79.982295 | P19: 75.787495 | Q19: 72.720225 | R19: 70.324785 | S19: 68.714895 | T19: 67.00249 | U19: 65.458895 | V19: 63.579845
A20: P05 | B20: P05 | C20: % do PIB / % of GDP | L20: 99.089226 | M20: 88.732713 | N20: 78.883062 | O20: 70.367103 | P20: 62.892417 | Q20: 56.919479 | R20: 51.0757 | S20: 46.419594 | T20: 42.10689 | U20: 37.503877 | V20: 31.797483
A21: P10 | B21: P10 | C21: % do PIB / % of GDP | M21: 0.846601 | N21: 1.4490055 | O21: 1.93223 | P21: 2.862561 | Q21: 3.2675505 | R21: 4.473427 | S21: 5.006964 | T21: 5.4699415 | U21: 6.268377 | V21: 8.225201
A22: P20 | B22: P20 | C22: % do PIB / % of GDP | M22: 1.101142 | N22: 1.785982 | O22: 2.670419 | P22: 3.31008 | Q22: 4.135191 | R22: 4.867269 | S22: 5.64726 | T22: 6.8981 | U22: 7.946034 | V22: 8.436992
A23: P40 | B23: P40 | C23: % do PIB / % of GDP | M23: 1.465224 | N23: 2.421942 | O23: 3.513762 | P23: 4.696734 | Q23: 5.898456 | R23: 6.963374 | S23: 8.262088 | T23: 8.757868 | U23: 9.589852 | V23: 10.529712
A24: P60 | B24: P60 | C24: % do PIB / % of GDP | M24: 1.2507 | N24: 2.189432 | O24: 3.048208 | P24: 4.008828 | Q24: 4.920566 | R24: 5.959184 | S24: 6.473382 | T24: 7.520808 | U24: 8.248274 | V24: 9.148944
A25: P80 | B25: P80 | C25: % do PIB / % of GDP | M25: 1.403184 | N25: 2.532238 | O25: 3.782856 | P25: 4.903344 | Q25: 5.77138 | R25: 6.612892 | S25: 7.92859 | T25: 9.10012 | U25: 10.52049 | V25: 11.853352
A26: P90 | B26: P90 | C26: % do PIB / % of GDP | M26: 1.184962 | N26: 1.938456 | O26: 2.833945 | P26: 3.573364 | Q26: 4.831546 | R26: 5.74486 | S26: 6.763692 | T26: 7.67467 | U26: 8.789357 | V26: 10.422789
A27: P95 | B27: P95 | C27: % do PIB / % of GDP | M27: 1.007909 | N27: 1.783804 | O27: 2.271397 | P27: 3.2016185 | Q27: 3.8319305 | R27: 4.4158965 | S27: 5.9444865 | T27: 7.080477 | U27: 8.548843 | V27: 10.588262
A30: Fontes: INE, BCE e cálculos do Banco de Portugal. | Notas: Foi estimado um modelo BVAR com uma prior Independent Normal-Wishart, usando dados trimestrais. A taxa de juro de curto prazo corresponde à Euribor a 3 meses e a de longo prazo à taxa de juro das obrigações soberanas a 10 anos. Foi usado o deflator do PIB no cálculo das taxas de juro reais. A procura externa, hipótese do exercício de projeção deste Boletim, é utilizada como variável exógena. O período de estimação considerado foi 1999T1-2023T4 e as observações referentes ao período da pandemia foram tratadas com recurso a variáveis binárias. Foram incluídos no modelo 2 desfasamentos de cada variável endógena. Para as simulações, a componente cíclica do saldo considera uma semi-elasticidade de 0,54 face ao hiato do produto, este estimado com recurso a um filtro de Hodrick-Prescott para cada PIB simulado. Esta técnica de análise estocástica não capta a probabilidade de ocorrência de eventos extremos.
A31: Sources: Statistics Portugal, ECB and Banco de Portugal calculations. | Notes: A BVAR model was estimated with an Independent Normal-Wishart prior, using quarterly data. The short-term interest rate corresponds to the 3-month Euribor, and the long-term interest rate corresponds to the 10-year sovereign bond yield. The GDP deflator was used in the calculation of real interest rates. External demand, as assumed in the projection exercise of this Bulletin, is used as an exogenous variable. The estimation period considered was from Q1 1999 to Q4 2023, and observations relating to the pandemic period were treated using dummy variables. The model included 2 lags of each endogenous variable. For the simulations, the cyclical component of the balance considers a semi-elasticity of 0.54 with respect to the output gap, which is estimated using a Hodrick-Prescott filter for each simulated GDP. This stochastic analysis technique does not capture the probability of extreme events occurring.

Sheet GC.7.4
A4: Índice/Contents
A5: Boletim Económico - Junho 2024/Economic Bulletin - June 2024
A6: =+Índice!A84 -> Caixa 7 - Trajetórias para a dívida pública portuguesa/Box 7 - Trajectories for Portuguese public debt
A10: Gráfico C7.4 Distribuição do rácio da dívida pública para 2033: probabilidade em exceder um valor | Em percentagem
A11: Chart B7.4 Distribution of the public debt ratio for 2033: probability of exceeding a value | In percentage
A13: Unidade/Unit | B13: % do PIB | C13: % | D13: % | E13: % | F13: %
B14: % of GDP | C14: % | D14: % | E14: % | F14: %
B16: Rácio da dívida pública em 2033 | C16: Probabilidade da dívida exceder um rácio x em 2033 | D16: Cenário base | E16: Observado em 2023 | F16: Referência das regras orçamentais (60%)
B17: Debt ratio in 2033 | C17: Probability of debt exceeding a ratio of x in 2033 | D17: Baseline scenario | E17: Observed in 2023 | F17: Reference for fiscal rules (60%)
B19: 10 | C19: 99.9
B20: 10.5 | C20: 99.8
B21: 11 | C21: 99.8
B22: 11.5 | C22: 99.8
B23: 12 | C23: 99.8
B24: 12.5 | C24: 99.7
B25: 13 | C25: 99.7
B26: 13.5 | C26: 99.7
B27: 14 | C27: 99.6
B28: 14.5 | C28: 99.6
B29: 15 | C29: 99.5
B30: 15.5 | C30: 99.4
... B118: 59.5 | C118: 58.9
B119: 60 | C119: 58 | F119: 58
B120: 60.5 | C120: 57.1
B121: 61 | C121: 56
B122: 61.5 | C122: 55
B123: 62 | C123: 53.9
B124: 62.5 | C124: 52.7
B125: 63 | C125: 51.5
B126: 63.5 | C126: 50.3
B127: 64 | C127: 48.9
B128: 64.5 | C128: 47.7
B129: 65 | C129: 46.7
B130: 65.5 | C130: 45.8
B131: 66 | C131: 44.8
... B135: 68 | C135: 40.5
B136: 68.5 | C136: 39.3 | D136: 39.3
B137: 69 | C137: 38.3
B138: 69.5 | C138: 37.6
B139: 70 | C139: 36.5
B140: 70.5 | C140: 35.3
B141: 71 | C141: 34.4
B142: 71.5 | C142: 33.7
B143: 72 | C143: 32.8
B144: 72.5 | C144: 31.7
B145: 73 | C145: 31
B146: 73.5 | C146: 30.3
B147: 74 | C147: 29.4
B148: 74.5 | C148: 28.6
... B196: 98.5 | C196: 5.8
B197: 99 | C197: 5.6 | E197: 5.6
B198: 99.5 | C198: 5.5
B199: 100 | C199: 5.4
B200: 100.5 | C200: 5.2
B201: 101 | C201: 5.1
B202: 101.5 | C202: 4.8
B203: 102 | C203: 4.7
B204: 102.5 | C204: 4.6
B205: 103 | C205: 4.5
B206: 103.5 | C206: 4.2
B207: 104 | C207: 4.1
B208: 104.5 | C208: 4
B209: 105 | C209: 3.8
... B279: 140 | C279: 0.6
A282: Fontes: INE, BCE e cálculos do Banco de Portugal. | Notas: Foi estimado um modelo BVAR com uma prior Independent Normal-Wishart, usando dados trimestrais. A taxa de juro de curto prazo corresponde à Euribor a 3 meses e a de longo prazo à taxa de juro das obrigações soberanas a 10 anos. Foi usado o deflator do PIB no cálculo das taxas de juro reais. A procura externa, hipótese do exercício de projeção deste Boletim, é utilizada como variável exógena. O período de estimação considerado foi 1999T1-2023T4 e as observações referentes ao período da pandemia foram tratadas com recurso a variáveis binárias. Foram incluídos no modelo 2 desfasamentos de cada variável endógena. Para as simulações, a componente cíclica do saldo considera uma semi-elasticidade de 0,54 face ao hiato do produto, este estimado com recurso a um filtro de Hodrick-Prescott para cada PIB simulado. Esta técnica de análise estocástica não capta a probabilidade de ocorrência de eventos extremos. A distribuição do rácio da dívida em 2033 é calculada com base nas simulações estocásticas.
A283: Sources: Statistics Portugal, ECB and Banco de Portugal calculations. | Notes: A BVAR model was estimated with an Independent Normal-Wishart prior, using quarterly data. The short-term interest rate corresponds to the 3-month Euribor, and the long-term interest rate corresponds to the 10-year sovereign bond yield. The GDP deflator was used in the calculation of real interest rates. External demand, as assumed in the projection exercise of this Bulletin, is used as an exogenous variable. The estimation period considered was from Q1 1999 to Q4 2023, and observations relating to the pandemic period were treated using dummy variables. The model included 2 lags of each endogenous variable. For the simulations, the cyclical component of the balance considers a semi-elasticity of 0.54 with respect to the output gap, which is estimated using a Hodrick-Prescott filter for each simulated GDP. This stochastic analysis technique does not capture the probability of extreme events occurring. The distribution of the debt ratio in 2033 is calculated based on the stochastic simulations.

Sheet TED.G1
A5: Índice/Contents
A6: Boletim Económico - junho 2024/Economic Bulletin - June 2024
A7: =+Índice!A95 -> Parte II. Tema em Destaque: Caraterização dos trabalhadores estrangeiros por conta de outrem em Portugal / Part II Special Issue: Characterization of foreign employees in Portugal
A10: Gráfico 1 • Trabalhadores com nacionalidade estrangeira | Número de indivíduos em cada mês
A11: Chart 1 • Employees with foreign nationality | Number of individuals in each month
A13: Unidade/Unit | B13: número de trabalhadores/number of employees
A15: ano | B15: year | C15: 2014 | O15: 2015 | AA15: 2016 | AM15: 2017 | AY15: 2018 | BK15: 2019 | BW15: 2020 | CI15: 2021 | CU15: 2022 | DG15: 2023
A16: mês | B16: month | C16: 1 | D16: 2 | E16: 3 | F16: 4 | G16: 5 | H16: 6 | I16: 7 | J16: 8 | K16: 9 | L16: 10 | M16: 11 | N16: 12 | O16: 1 | P16: 2 | Q16: 3 | R16: 4 | S16: 5 | T16: 6 | U16: 7 | V16: 8 | W16: 9 | X16: 10 | Y16: 11 | Z16: 12 | AA16: 1 | AB16: 2 | AC16: 3 | AD16: 4 | AE16: 5 | AF16: 6 | AG16: 7 | AH16: 8 | AI16: 9 | AJ16: 10 | AK16: 11 | AL16: 12 | AM16: 1 | AN16: 2 | AO16: 3 | AP16: 4 | AQ16: 5 | AR16: 6 | AS16: 7 | AT16: 8 | AU16: 9 | AV16: 10 | AW16: 11 | AX16: 12 | AY16: 1 | AZ16: 2 | BA16: 3 | BB16: 4 | BC16: 5 | BD16: 6 | BE16: 7 | BF16: 8 | BG16: 9 | BH16: 10 | BI16: 11 | BJ16: 12 | BK16: 1 | BL16: 2 | BM16: 3 | BN16: 4 | BO16: 5 | BP16: 6 | BQ16: 7 | BR16: 8 | BS16: 9 | BT16: 10 | BU16: 11 | BV16: 12 | BW16: 1 | BX16: 2 | BY16: 3 | BZ16: 4 | CA16: 5 | CB16: 6 | CC16: 7 | CD16: 8 | CE16: 9 | CF16: 10 | CG16: 11 | CH16: 12 | CI16: 1 | CJ16: 2 | CK16: 3 | CL16: 4 | CM16: 5 | CN16: 6 | CO16: 7 | CP16: 8 | CQ16: 9 | CR16: 10 | CS16: 11 | CT16: 12 | CU16: 1 | CV16: 2 | CW16: 3 | CX16: 4 | CY16: 5 | CZ16: 6 | DA16: 7 | DB16: 8 | DC16: 9 | DD16: 10 | DE16: 11 | DF16: 12 | DG16: 1 | DH16: 2 | DI16: 3 | DJ16: 4 | DK16: 5 | DL16: 6 | DM16: 7 | DN16: 8 | DO16: 9 | DP16: 10 | DQ16: 11 | DR16: 12
A17: número de trabalhadores | B17: number of employees | C17: 51637 | D17: 51500 | E17: 52741 | F17: 54283 | G17: 55518 | H17: 56281 | I17: 57146 | J17: 57249 | K17: 57800 | L17: 58464 | M17: 57896 | N17: 56367 | O17: 55537 | P17: 55869 | Q17: 57757 | R17: 60311 | S17: 62312 | T17: 64100 | U17: 65530 | V17: 66527 | W17: 67651 | X17: 68555 | Y17: 68685 | Z17: 68180 | AA17: 67711 | AB17: 68934 | AC17: 72026 | AD17: 74222 | AE17: 75932 | AF17: 77214 | AG17: 78527 | AH17: 78960 | AI17: 79820 | AJ17: 80993 | AK17: 81136 | AL17: 80336 | AM17: 80127 | AN17: 81351 | AO17: 84907 | AP17: 88438 | AQ17: 91973 | AR17: 94729 | AS17: 97012 | AT17: 98597 | AU17: 100650 | AV17: 102815 | AW17: 104020 | AX17: 103433 | AY17: 104837 | AZ17: 107361 | BA17: 112991 | BB17: 118489 | BC17: 124318 | BD17: 130074 | BE17: 135711 | BF17: 139342 | BG17: 143368 | BH17: 147551 | BI17: 149560 | BJ17: 149020 | BK17: 151648 | BL17: 157055 | BM17: 165720 | BN17: 176046 | BO17: 186280 | BP17: 194096 | BQ17: 202714 | BR17: 208012 | BS17: 214569 | BT17: 218269 | BU17: 219115 | BV17: 217585 | BW17: 220831 | BX17: 228848 | BY17: 233112 | BZ17: 214462 | CA17: 217297 | CB17: 224479 | CC17: 230481 | CD17: 235539 | CE17: 239837 | CF17: 240249 | CG17: 239120 | CH17: 233678 | CI17: 231682 | CJ17: 231250 | CK17: 234777 | CL17: 240376 | CM17: 250678 | CN17: 260374 | CO17: 266521 | CP17: 271077 | CQ17: 276643 | CR17: 280744 | CS17: 284886 | CT17: 282899 | CU17: 285603 | CV17: 294469 | CW17: 309547 | CX17: 327079 | CY17: 350626 | CZ17: 369999 | DA17: 385678 | DB17: 397826 | DC17: 410909 | DD17: 416684 | DE17: 422140 | DF17: 416519 | DG17: 420690 | DH17: 431520 | DI17: 450469 | DJ17: 469621 | DK17: 492536 | DL17: 509605 | DM17: 523218 | DN17: 532614 | DO17: 539273 | DP17: 538368 | DQ17: 530624 | DR17: 503786
A20: Fonte: Microdados da Segurança Social (cálculos do Banco de Portugal). | Nota: Foram considerados os trabalhadores por conta de outrem, em idade ativa (16-74 anos), com morada em Portugal e com, pelo menos, o equivalente a um dia de remuneração na empresa em cada mês.
A21: Source: Social Security microdata (Banco de Portugal calculations). | Note: Employees of working age (16-74 years old), living in Portugal and with, at least, the equivalent of a day of remuneration at the firm each month were considered.

Sheet TED.G2
A5: Índice/Contents
A6: Boletim Económico - junho 2024/Economic Bulletin - June 2024
A7: =+Índice!A95 -> Parte II. Tema em Destaque: Caraterização dos trabalhadores estrangeiros por conta de outrem em Portugal / Part II Special Issue: Characterization of foreign employees in Portugal
A10: Gráfico 2 • Número de empresas com trabalhadores por nacionalidade| Milhares de empresas
A11: Chart 2 • Number of firms with employees by nationality | Thousands of firms
A13: Unidade/Unit | C13: Milhares de empresas/ Thousands of firms
C15: Nacionalidade portuguesa | D15: Nacionalidade estrangeira
C16: Portuguese nationality | D16: Foreign nationality
B17: 2014 | C17: 285.32842 | D17: 24.481667
B18: 2015 | C18: 291.07092 | D18: 26.957083
B19: 2016 | C19: 295.42467 | D19: 30.43975
B20: 2017 | C20: 300.98792 | D20: 34.8175
B21: 2018 | C21: 305.72667 | D21: 42.9465
B22: 2019 | C22: 309.78192 | D22: 54.252667
B23: 2020 | C23: 304.39875 | D23: 59.705583
B24: 2021 | C24: 306.86708 | D24: 62.567167
B25: 2022 | C25: 315.7225 | D25: 74.64575
B26: 2023 | C26: 317.83767 | D26: 90.63875
A28: Fonte: Microdados da Segurança Social (cálculos do Banco de Portugal). | Notas: Foram consideradas as empresas com trabalhadores por conta de outrem, em idade ativa (16-74 anos) e com, pelo menos, o equivalente a um dia de remuneração na empresa em cada mês. Médias mensais.
A29: Source: Social Security microdata (Banco de Portugal calculations). | Notes: Firms with employees of working age (16-74 years) and with, at least, the equivalent of a day of remuneration at the firm each month were considered. Monthly averages.

Sheet TED.Q1
A5: Índice/Contents
A6: Boletim Económico - junho 2024/Economic Bulletin - June 2024
A7: =+Índice!A95 -> Parte II. Tema em Destaque: Caraterização dos trabalhadores estrangeiros por conta de outrem em Portugal / Part II Special Issue: Characterization of foreign employees in Portugal
A10: Quadro 1 • Número de trabalhadores com nacionalidade estrangeira e respetivo peso por dimensão da empresa em 2023 | Número de indivíduos e peso em percentagem
A11: Table 1 • Number of employees with foreign nationality and respective weight by firm size in 2023 | Number of individuals and weight in percentage
A13: Unidade/Unit | B13: Número de indivíduos/ Number of individuals | C13: Número de indivíduos/ Number of individuals | D13: %
B15: Number of employees in the firm | C15: Total number of foreign employees | D15: Weight of foreign employees
B16: Número de trabalhadores na empresa | C16: Total de trabalhadores estrangeiros | D16: Peso dos trabalhadores estrangeiros
A17: Up to 10 | B17: Até 10 | C17: 110692.42 | D17: 13.805923
A18: 11-25 | B18: 11-25 | C18: 75721.5 | D18: 16.222331
A19: 26-50 | B19: 26-50 | C19: 62609.25 | D19: 15.56825
A20: 51-100 | B20: 51-100 | C20: 60308.25 | D20: 14.76395
A21: 101-150 | B21: 101-150 | C21: 31481 | D21: 14.321437
A22: More than 150 | B22: Mais de 150 | C22: 189436.83 | D22: 12.479724
A25: Fonte: Microdados da Segurança Social (cálculos do Banco de Portugal). | Notas: A dimensão da empresa foi calculada com base no número de trabalhadores por conta de outrem, em idade ativa (16-74 anos) e com, pelo menos, o equivalente a um dia de remuneração na empresa em cada mês em 2023. O peso é face ao número médio de trabalhadores nacionais e estrangeiros por dimensão da empresa em cada mês em 2023. De notar que a soma do número de trabalhadores por dimensão é superior ao apresentado no Gráfico 1, uma vez que o mesmo trabalhador pode trabalhar em diferentes empresas, com diferentes dimensões, em cada mês.
A26: Source: Social Security microdata (Banco de Portugal calculations). | Notes: The size of the firm was calculated based on the number of employees of working age (16-74 years old) and with, at least, the equivalent of a day of remuneration in the firm each month in 2023. The weight is relative to the average number of national and foreign employees by firm size in each month in 2023. It should be noted that the sum of the number of employees by size is higher than in Chart 1, since the same employee can work in different firms, with different sizes, each month.

Sheet TED.G3
A5: Índice/Contents
A6: Boletim Económico - junho 2024/Economic Bulletin - June 2024
A7: =+Índice!A95 -> Parte II. Tema em Destaque: Caraterização dos trabalhadores estrangeiros por conta de outrem em Portugal / Part II Special Issue: Characterization of foreign employees in Portugal
A10: Gráfico 3 • Número de trabalhadores estrangeiros por principais nacionalidades | Número de indivíduos em cada mês
A11: Chart 3 • Number of foreign employees by main nationalities | Number of individuals in each month
C13: Unidade/Unit
A15: year | B15: ano | D15: 2014 | P15: 2015 | AB15: 2016 | AN15: 2017 | AZ15: 2018 | BL15: 2019 | BX15: 2020 | CJ15: 2021 | CV15: 2022 | DH15: 2023
A16: month | B16: mês | C16: Número de indivíduos/ Number of individuals | D16: 1 | E16: 2 | F16: 3 | G16: 4 | H16: 5 | I16: 6 | J16: 7 | K16: 8 | L16: 9 | M16: 10 | N16: 11 | O16: 12 | P16: 1 | Q16: 2 | R16: 3 | S16: 4 | T16: 5 | U16: 6 | V16: 7 | W16: 8 | X16: 9 | Y16: 10 | Z16: 11 | AA16: 12 | AB16: 1 | AC16: 2 | AD16: 3 | AE16: 4 | AF16: 5 | AG16: 6 | AH16: 7 | AI16: 8 | AJ16: 9 | AK16: 10 | AL16: 11 | AM16: 12 | AN16: 1 | AO16: 2 | AP16: 3 | AQ16: 4 | AR16: 5 | AS16: 6 | AT16: 7 | AU16: 8 | AV16: 9 | AW16: 10 | AX16: 11 | AY16: 12 | AZ16: 1 | BA16: 2 | BB16: 3 | BC16: 4 | BD16: 5 | BE16: 6 | BF16: 7 | BG16: 8 | BH16: 9 | BI16: 10 | BJ16: 11 | BK16: 12 | BL16: 1 | BM16: 2 | BN16: 3 | BO16: 4 | BP16: 5 | BQ16: 6 | BR16: 7 | BS16: 8 | BT16: 9 | BU16: 10 | BV16: 11 | BW16: 12 | BX16: 1 | BY16: 2 | BZ16: 3 | CA16: 4 | CB16: 5 | CC16: 6 | CD16: 7 | CE16: 8 | CF16: 9 | CG16: 10 | CH16: 11 | CI16: 12 | CJ16: 1 | CK16: 2 | CL16: 3 | CM16: 4 | CN16: 5 | CO16: 6 | CP16: 7 | CQ16: 8 | CR16: 9 | CS16: 10 | CT16: 11 | CU16: 12 | CV16: 1 | CW16: 2 | CX16: 3 | CY16: 4 | CZ16: 5 | DA16: 6 | DB16: 7 | DC16: 8 | DD16: 9 | DE16: 10 | DF16: 11 | DG16: 12 | DH16: 1 | DI16: 2 | DJ16: 3 | DK16: 4 | DL16: 5 | DM16: 6 | DN16: 7 | DO16: 8 | DP16: 9 | DQ16: 10 | DR16: 11 | DS16: 12
A17: Bangladesh | B17: Bangladesh | C17: Número de indivíduos/ Number of individuals | D17: 87 | E17: 89 | F17: 93 | G17: 108 | H17: 138 | I17: 164 | J17: 190 | K17: 204 | L17: 236 | M17: 286 | N17: 316 | O17: 335 | P17: 391 | Q17: 443 | R17: 495 | S17: 699 | T17: 893 | U17: 1070 | V17: 1209 | W17: 1374 | X17: 1585 | Y17: 1769 | Z17: 2038 | AA17: 2269 | AB17: 2455 | AC17: 2702 | AD17: 2838 | AE17: 2899 | AF17: 2867 | AG17: 2784 | AH17: 2815 | AI17: 2735 | AJ17: 2667 | AK17: 2601 | AL17: 2600 | AM17: 2537 | AN17: 2386 | AO17: 2367 | AP17: 2348 | AQ17: 2335 | AR17: 2356 | AS17: 2342 | AT17: 2318 | AU17: 2358 | AV17: 2380 | AW17: 2425 | AX17: 2406 | AY17: 2408 | AZ17: 2463 | BA17: 2504 | BB17: 2592 | BC17: 2707 | BD17: 2784 | BE17: 2856 | BF17: 2947 | BG17: 3046 | BH17: 3170 | BI17: 3228 | BJ17: 3272 | BK17: 3280 | BL17: 3232 | BM17: 3218 | BN17: 3362 | BO17: 3746 | BP17: 3966 | BQ17: 4109 | BR17: 4329 | BS17: 4495 | BT17: 4643 | BU17: 4800 | BV17: 4888 | BW17: 4875 | BX17: 5136 | BY17: 5471 | BZ17: 5669 | CA17: 5192 | CB17: 5484 | CC17: 5956 | CD17: 6185 | CE17: 6751 | CF17: 7206 | CG17: 7474 | CH17: 7644 | CI17: 7390 | CJ17: 7401 | CK17: 7370 | CL17: 7635 | CM17: 7828 | CN17: 8220 | CO17: 8580 | CP17: 9037 | CQ17: 9339 | CR17: 9829 | CS17: 10212 | CT17: 10833 | CU17: 11189 | CV17: 11271 | CW17: 11520 | CX17: 11996 | CY17: 12474 | CZ17: 13898 | DA17: 14358 | DB17: 14680 | DC17: 15096 | DD17: 15564 | DE17: 15608 | DF17: 15898 | DG17: 15742 | DH17: 15252 | DI17: 15391 | DJ17: 15958 | DK17: 16872 | DL17: 18028 | DM17: 19062 | DN17: 20016 | DO17: 21024 | DP17: 21562 | DQ17: 21614 | DR17: 21205 | DS17: 19296
A18: Brazil | B18: Brasil | C18: Número de indivíduos/ Number of individuals | D18: 9553 | E18: 9495 | F18: 9594 | G18: 9709 | H18: 9865 | I18: 9944 | J18: 10175 | K18: 10261 | L18: 10319 | M18: 10219 | N18: 9959 | O18: 9692 | P18: 9634 | Q18: 9665 | R18: 9915 | S18: 10192 | T18: 10467 | U18: 10796 | V18: 11097 | W18: 11387 | X18: 11570 | Y18: 11596 | Z18: 11484 | AA18: 11355 | AB18: 11455 | AC18: 11750 | AD18: 12149 | AE18: 12542 | AF18: 12965 | AG18: 13400 | AH18: 13954 | AI18: 14166 | AJ18: 14491 | AK18: 14712 | AL18: 14891 | AM18: 14995 | AN18: 15393 | AO18: 15842 | AP18: 16715 | AQ18: 17768 | AR18: 18865 | AS18: 19908 | AT18: 20959 | AU18: 21840 | AV18: 22833 | AW18: 23654 | AX18: 24499 | AY18: 24771 | AZ18: 25793 | BA18: 27049 | BB18: 29076 | BC18: 31075 | BD18: 33416 | BE18: 36080 | BF18: 38941 | BG18: 41255 | BH18: 43348 | BI18: 45424 | BJ18: 46822 | BK18: 47321 | BL18: 49575 | BM18: 52672 | BN18: 56342 | BO18: 60694 | BP18: 65267 | BQ18: 69420 | BR18: 73763 | BS18: 76180 | BT18: 79387 | BU18: 81252 | BV18: 81993 | BW18: 81825 | BX18: 84190 | BY18: 88297 | BZ18: 90348 | CA18: 81485 | CB18: 81403 | CC18: 84504 | CD18: 87401 | CE18: 88453 | CF18: 89713 | CG18: 89016 | CH18: 88108 | CI18: 85701 | CJ18: 85085 | CK18: 84500 | CL18: 84714 | CM18: 85702 | CN18: 89049 | CO18: 92272 | CP18: 93881 | CQ18: 94886 | CR18: 96682 | CS18: 98547 | CT18: 101408 | CU18: 101878 | CV18: 104948 | CW18: 110200 | CX18: 117589 | CY18: 125284 | CZ18: 136663 | DA18: 147223 | DB18: 156458 | DC18: 163050 | DD18: 169894 | DE18: 173064 | DF18: 176971 | DG18: 176219 | DH18: 180377 | DI18: 186311 | DJ18: 194367 | DK18: 200400 | DL18: 209159 | DM18: 215683 | DN18: 220784 | DO18: 222628 | DP18: 225043 | DQ18: 224348 | DR18: 222123 | DS18: 212054
A19: Cape Verde | B19: Cabo Verde | C19: Número de indivíduos/ Number of individuals | D19: 2712 | E19: 2734 | F19: 2801 | G19: 2856 | H19: 2936 | I19: 3011 | J19: 3162 | K19: 3203 | L19: 3262 | M19: 3234 | N19: 3151 | O19: 3141 | P19: 3083 | Q19: 3164 | R19: 3269 | S19: 3337 | T19: 3456 | U19: 3628 | V19: 3771 | W19: 3869 | X19: 3886 | Y19: 3904 | Z19: 3854 | AA19: 3835 | AB19: 3821 | AC19: 3912 | AD19: 4062 | AE19: 4115 | AF19: 4225 | AG19: 4322 | AH19: 4480 | AI19: 4555 | AJ19: 4608 | AK19: 4625 | AL19: 4651 | AM19: 4609 | AN19: 4638 | AO19: 4736 | AP19: 4902 | AQ19: 5043 | AR19: 5203 | AS19: 5357 | AT19: 5503 | AU19: 5593 | AV19: 5704 | AW19: 5787 | AX19: 5836 | AY19: 5829 | AZ19: 5909 | BA19: 6071 | BB19: 6269 | BC19: 6438 | BD19: 6760 | BE19: 6995 | BF19: 7242 | BG19: 7355 | BH19: 7441 | BI19: 7569 | BJ19: 7630 | BK19: 7612 | BL19: 7758 | BM19: 7955 | BN19: 8293 | BO19: 8663 | BP19: 8929 | BQ19: 9195 | BR19: 9600 | BS19: 9794 | BT19: 9991 | BU19: 10063 | BV19: 10130 | BW19: 10122 | BX19: 10369 | BY19: 10679 | BZ19: 10824 | CA19: 9888 | CB19: 9917 | CC19: 10148 | CD19: 10349 | CE19: 10585 | CF19: 10713 | CG19: 10685 | CH19: 10720 | CI19: 10561 | CJ19: 10600 | CK19: 10661 | CL19: 10879 | CM19: 11105 | CN19: 11628 | CO19: 12090 | CP19: 12631 | CQ19: 12948 | CR19: 13221 | CS19: 13437 | CT19: 13612 | CU19: 13489 | CV19: 13609 | CW19: 14094 | CX19: 14648 | CY19: 15028 | CZ19: 15603 | DA19: 16234 | DB19: 16930 | DC19: 17355 | DD19: 17780 | DE19: 18029 | DF19: 18287 | DG19: 18299 | DH19: 18663 | DI19: 19202 | DJ19: 20016 | DK19: 20755 | DL19: 21818 | DM19: 22597 | DN19: 23689 | DO19: 24399 | DP19: 25256 | DQ19: 25634 | DR19: 25652 | DS19: 24791
A20: India | B20: Índia | C20: Número de indivíduos/ Number of individuals | D20: 319 | E20: 330 | F20: 336 | G20: 387 | H20: 414 | I20: 445 | J20: 489 | K20: 525 | L20: 569 | M20: 620 | N20: 634 | O20: 662 | P20: 710 | Q20: 749 | R20: 836 | S20: 970 | T20: 1124 | U20: 1263 | V20: 1333 | W20: 1466 | X20: 1627 | Y20: 1746 | Z20: 1896 | AA20: 1941 | AB20: 2035 | AC20: 2128 | AD20: 2311 | AE20: 2490 | AF20: 2605 | AG20: 2613 | AH20: 2711 | AI20: 2712 | AJ20: 2745 | AK20: 2853 | AL20: 2919 | AM20: 2932 | AN20: 2876 | AO20: 2921 | AP20: 3098 | AQ20: 3349 | AR20: 3529 | AS20: 3672 | AT20: 3744 | AU20: 3824 | AV20: 3906 | AW20: 4027 | AX20: 4094 | AY20: 4082 | AZ20: 4099 | BA20: 4052 | BB20: 4378 | BC20: 4816 | BD20: 5205 | BE20: 5801 | BF20: 6301 | BG20: 6724 | BH20: 7136 | BI20: 7593 | BJ20: 7922 | BK20: 7907 | BL20: 7782 | BM20: 7982 | BN20: 8880 | BO20: 10390 | BP20: 11929 | BQ20: 13150 | BR20: 13994 | BS20: 15219 | BT20: 15992 | BU20: 16750 | BV20: 16841 | BW20: 16515 | BX20: 16034 | BY20: 16596 | BZ20: 17245 | CA20: 16448 | CB20: 18135 | CC20: 19255 | CD20: 19679 | CE20: 20990 | CF20: 21335 | CG20: 21562 | CH20: 21293 | CI20: 20472 | CJ20: 19618 | CK20: 19314 | CL20: 19964 | CM20: 21039 | CN20: 22531 | CO20: 23566 | CP20: 24091 | CQ20: 24387 | CR20: 24633 | CS20: 24470 | CT20: 23725 | CU20: 22517 | CV20: 21635 | CW20: 21729 | CX20: 22911 | CY20: 25152 | CZ20: 27952 | DA20: 30013 | DB20: 31201 | DC20: 32279 | DD20: 33425 | DE20: 33571 | DF20: 33651 | DG20: 32097 | DH20: 31417 | DI20: 32292 | DJ20: 34792 | DK20: 38739 | DL20: 42279 | DM20: 44693 | DN20: 45751 | DO20: 47218 | DP20: 47124 | DQ20: 45662 | DR20: 43425 | DS20: 38924
A21: Nepal | B21: Nepal | C21: Número de indivíduos/ Number of individuals | D21: 139 | E21: 137 | F21: 164 | G21: 199 | H21: 244 | I21: 247 | J21: 261 | K21: 294 | L21: 324 | M21: 363 | N21: 381 | O21: 378 | P21: 401 | Q21: 388 | R21: 498 | S21: 693 | T21: 883 | U21: 952 | V21: 991 | W21: 1129 | X21: 1244 | Y21: 1319 | Z21: 1361 | AA21: 1428 | AB21: 1509 | AC21: 1604 | AD21: 1845 | AE21: 2007 | AF21: 2098 | AG21: 2155 | AH21: 2303 | AI21: 2434 | AJ21: 2515 | AK21: 2595 | AL21: 2726 | AM21: 2812 | AN21: 2953 | AO21: 3077 | AP21: 3311 | AQ21: 3562 | AR21: 3705 | AS21: 3893 | AT21: 3950 | AU21: 4095 | AV21: 4154 | AW21: 4229 | AX21: 4313 | AY21: 4364 | AZ21: 4493 | BA21: 4655 | BB21: 5023 | BC21: 5583 | BD21: 6018 | BE21: 6522 | BF21: 6813 | BG21: 7093 | BH21: 7334 | BI21: 7449 | BJ21: 7396 | BK21: 7439 | BL21: 7595 | BM21: 7749 | BN21: 8447 | BO21: 9175 | BP21: 9877 | BQ21: 10208 | BR21: 10642 | BS21: 11072 | BT21: 11474 | BU21: 11343 | BV21: 11130 | BW21: 11018 | BX21: 11318 | BY21: 11452 | BZ21: 11711 | CA21: 11083 | CB21: 11542 | CC21: 11813 | CD21: 11772 | CE21: 12124 | CF21: 12283 | CG21: 12145 | CH21: 11765 | CI21: 11298 | CJ21: 10835 | CK21: 10675 | CL21: 11186 | CM21: 12227 | CN21: 12916 | CO21: 13532 | CP21: 13923 | CQ21: 14513 | CR21: 14902 | CS21: 14891 | CT21: 14616 | CU21: 14278 | CV21: 14114 | CW21: 14190 | CX21: 15130 | CY21: 16712 | CZ21: 18038 | DA21: 18916 | DB21: 19599 | DC21: 20312 | DD21: 21129 | DE21: 21480 | DF21: 21424 | DG21: 20638 | DH21: 20250 | DI21: 20514 | DJ21: 22193 | DK21: 24955 | DL21: 27349 | DM21: 28602 | DN21: 29259 | DO21: 30683 | DP21: 31012 | DQ21: 30603 | DR21: 29457 | DS21: 27784
A22: Europe | B22: Europa | C22: Número de indivíduos/ Number of individuals | D22: 27434 | E22: 27465 | F22: 28199 | G22: 29197 | H22: 29895 | I22: 30221 | J22: 30405 | K22: 30077 | L22: 30259 | M22: 30730 | N22: 30497 | O22: 29275 | P22: 28607 | Q22: 28804 | R22: 29869 | S22: 31075 | T22: 31888 | U22: 32287 | V22: 32712 | W22: 32449 | X22: 32693 | Y22: 32979 | Z22: 32752 | AA22: 32160 | AB22: 31411 | AC22: 31781 | AD22: 33423 | AE22: 34392 | AF22: 34981 | AG22: 35508 | AH22: 35611 | AI22: 35398 | AJ22: 35667 | AK22: 36395 | AL22: 36142 | AM22: 35381 | AN22: 34920 | AO22: 35405 | AP22: 36991 | AQ22: 38306 | AR22: 39528 | AS22: 40054 | AT22: 40437 | AU22: 40308 | AV22: 40659 | AW22: 41290 | AX22: 41323 | AY22: 40459 | AZ22: 40406 | BA22: 41145 | BB22: 42871 | BC22: 44219 | BD22: 45428 | BE22: 46020 | BF22: 46601 | BG22: 46286 | BH22: 46628 | BI22: 47281 | BJ22: 47177 | BK22: 46083 | BL22: 45956 | BM22: 46983 | BN22: 48524 | BO22: 49959 | BP22: 51148 | BQ22: 51493 | BR22: 52001 | BS22: 51590 | BT22: 52008 | BU22: 52466 | BV22: 52090 | BW22: 50876 | BX22: 50340 | BY22: 51393 | BZ22: 51822 | CA22: 48903 | CB22: 48861 | CC22: 49370 | CD22: 49898 | CE22: 49821 | CF22: 50372 | CG22: 50513 | CH22: 50570 | CI22: 49683 | CJ22: 49502 | CK22: 49631 | CL22: 50223 | CM22: 50823 | CN22: 52429 | CO22: 53684 | CP22: 53974 | CQ22: 53887 | CR22: 54559 | CS22: 55130 | CT22: 55352 | CU22: 54331 | CV22: 54097 | CW22: 54895 | CX22: 56483 | CY22: 58740 | CZ22: 60834 | DA22: 61869 | DB22: 61958 | DC22: 61945 | DD22: 62455 | DE22: 62860 | DF22: 62750 | DG22: 61322 | DH22: 61144 | DI22: 61607 | DJ22: 62779 | DK22: 63173 | DL22: 63935 | DM22: 63888 | DN22: 63672 | DO22: 63257 | DP22: 63281 | DQ22: 62893 | DR22: 61679 | DS22: 59596
A25: Fonte: Microdados da Segurança Social (cálculos do Banco de Portugal). | Notas: Foram considerados os trabalhadores por conta de outrem, em idade ativa (16-74 anos), com morada em Portugal e com, pelo menos, o equivalente a um dia de remuneração na empresa em cada mês. As principais nacionalidades representadas correspondem aos cinco países com maior número de indivíduos a trabalhar em Portugal em 2023.
A26: Source: Social Security microdata (Banco de Portugal calculations). | Notes: Employees of working age (16-74 years old), living in Portugal and with, at least, the equivalent of a day of remuneration at the firm each month were considered. The main nationalities represented correspond to the five countries with the highest number of individuals working in Portugal in 2023.

Sheet TED.G4
A5: Índice/Contents
A6: Boletim Económico - junho 2024/Economic Bulletin - June 2024
A7: =+Índice!A95 -> Parte II. Tema em Destaque: Caraterização dos trabalhadores estrangeiros por conta de outrem em Portugal / Part II Special Issue: Characterization of foreign employees in Portugal
A10: Gráfico 4 • Distribuição da idade dos trabalhadores por nacionalidade em 2023 | Anos
A11: Chart 4 • Employees' age distribution by nationality in 2023 | Years
A13: Unidade/Unit | C13: Anos/Years | E13: Anos/Years
C14: Panel A | E14: Panel B
C15: Painel A | E15: Painel B
C16: Portuguese nationality | D16: Foreign nationality | E16: Bangladesh | F16: Brazil | G16: Cape Verde | H16: India | I16: Nepal
C17: Nacionalidade portuguesa | D17: Nacionalidade estrangeira | E17: Bangladesh | F17: Brasil | G17: Cabo Verde | H17: Índia | I17: Nepal
A18: 10th percentile | B18: Percentil 10 | C18: 25.083333 | D18: 23.333333 | E18: 25 | F18: 23.083334 | G18: 21.583334 | H18: 23 | I18: 24
A19: 25th percentile | B19: Percentil 25 | C19: 32 | D19: 27.083333 | E19: 28 | F19: 27.083334 | G19: 24.666666 | H19: 26 | I19: 27
A20: Median | B20: Mediana | C20: 42.25 | D20: 33.083333 | E20: 33 | F20: 34 | G20: 31.083334 | H20: 30 | I20: 31
A21: 75th percentile | B21: Percentil 75 | C21: 51 | D21: 41 | E21: 38 | F21: 41.083332 | G21: 39.416668 | H21: 36 | I21: 36
A22: 90th percentile | B22: Percentil 90 | C22: 58 | D22: 49 | E22: 43.333332 | F22: 48.5 | G22: 50.25 | H22: 42 | I22: 41
A25: Fonte: Microdados da Segurança Social (cálculos do Banco de Portugal). | Notas: Foram considerados os trabalhadores por conta de outrem com, pelo menos, o equivalente a um dia de remuneração na empresa em cada mês. Os extremos inferior e superior representados nos diagramas representam, respetivamente, a média do percentil 10 e do percentil 90 das respetivas distribuições. As principais nacionalidades representadas no painel B correspondem aos cinco países com maior número de indivíduos a trabalhar em Portugal em 2023.
A26: Source: Social Security microdata (Banco de Portugal calculations). | Notes: employees with at least the equivalent of a day of remuneration at the firm each month were considered. The lower and upper extremes represented in the diagrams represent, respectively, the average of the 10th percentile and the 90th percentile of the respective distributions. The main nationalities represented in panel B correspond to the five countries with the highest number of individuals working in Portugal in 2023.

Sheet TED.G5
A5: Índice/Contents
A6: Boletim Económico - junho 2024/Economic Bulletin - June 2024
A7: =+Índice!A95 -> Parte II. Tema em Destaque: Caraterização dos trabalhadores estrangeiros por conta de outrem em Portugal / Part II Special Issue: Characterization of foreign employees in Portugal
A10: Gráfico 5 • Peso das mulheres no número total de trabalhadores por nacionalidade em 2023 | Percentagem
A11: Chart 5 • Share of women in the total number of employees by nationality in 2023 | Percentage
A13: Unidade/Unit | C13: %
C14: Share
C15: Peso
A16: Portuguese nationality | B16: Nacionalidade portuguesa | C16: 49.280275
A17: Foreign nationality | B17: Nacionalidade estrangeira | C17: 36.677067
A19: Bangladesh | B19: Bangladesh | C19: 2.5728813
A20: Brazil | B20: Brasil | C20: 44.250424
A21: Cape Verde | B21: Cabo Verde | C21: 46.396061
A22: India | B22: Índia | C22: 7.5476071
A23: Nepal | B23: Nepal | C23: 24.333915
A26: Fonte: Microdados da Segurança Social (cálculos do Banco de Portugal). | Notas: Foram considerados os trabalhadores por conta de outrem com, pelo menos, o equivalente a um dia de remuneração na empresa em cada mês. As principais nacionalidades representadas correspondem aos cinco países com maior número de indivíduos a trabalhar em Portugal em 2023.
A27: Source: Social Security microdata (Banco de Portugal calculations). | Notes: Employees with at least the equivalent of a day of remuneration at the firm each month were considered. The main nationalities represented correspond to the five countries with the highest number of individuals working in Portugal in 2023.

Sheet TED.G6
A5: Índice/Contents
A6: Boletim Económico - junho 2024/Economic Bulletin - June 2024
A7: =+Índice!A95 -> Parte II. Tema em Destaque: Caraterização dos trabalhadores estrangeiros por conta de outrem em Portugal / Part II Special Issue: Characterization of foreign employees in Portugal
A10: Gráfico 6 • Distribuição dos trabalhadores com nacionalidade estrangeira por concelho da sede da empresa em 2023 | Número de indivíduos (painel A) e peso dos estrangeiros no número total de trabalhadores por concelho (painel B)
A11: Chart 6 • Distribution of employees with foreign nationality by firm's headquarter municipality in 2023 | Number of individuals (panel A) and share of foreigners in the total number of employees per municipality (panel B)
A13: Unidade/Unit | C13: Número de indivíduos/ Number of individuals | D13: Peso/ Share (%)
B14: Firm municipality | C14: Panel A | D14: Panel B
B15: Concelho da empresa | C15: Painel A | D15: Painel B
B16: 0101 ÁGUEDA | C16: 1635.4167 | D16: 9.5715366
B17: 0102 ALBERGARIA-A-VELHA | C17: 793 | D17: 9.5412844
B18: 0103 ANADIA | C18: 552.08333 | D18: 7.5664995
B19: 0104 AROUCA | C19: 213.66667 | D19: 3.6049209
B20: 0105 AVEIRO | C20: 3349.5833 | D20: 11.223233
B21: 0106 CASTELO DE PAIVA | C21: 321.91667 | D21: 8.0846344
B22: 0107 ESPINHO | C22: 365.5 | D22: 5.8788049
B23: 0108 ESTARREJA | C23: 639.91667 | D23: 8.5661059
B24: 0109 SANTA MARIA DA FEIRA | C24: 1722.5 | D24: 4.4505786
B25: 0110 ÍLHAVO | C25: 1389.75 | D25: 11.648634
B26: 0111 MEALHADA | C26: 319.08333 | D26: 7.1375312
B27: 0112 MURTOSA | C27: 105.66667 | D27: 6.2959285
... B294: 1824 VOUZELA | C294: 117.75 | D294: 6.3241284
A296: Fonte: Microdados da Segurança Social (cálculos do Banco de Portugal). | Nota: Foram considerados os trabalhadores por conta de outrem, em idade ativa (16-74 anos) e com, pelo menos, o equivalente a um dia de remuneração na empresa em cada mês.
A297: Source: Social Security microdata (Banco de Portugal calculations). | Note: Employees of working age (16-74 years) and with, at least, the equivalent of a day of remuneration at the firm each month were considered.

Sheet TED.G7
A5: Índice/Contents
A6: Boletim Económico - junho 2024/Economic Bulletin - June 2024
A7: =+Índice!A95 -> Parte II. Tema em Destaque: Caraterização dos trabalhadores estrangeiros por conta de outrem em Portugal / Part II Special Issue: Characterization of foreign employees in Portugal
A10: Gráfico 7 • Distribuição do número de trabalhadores com nacionalidade estrangeira por setor de atividade | Número de indivíduos
A11: Chart 7 • Distribution of the number of employees with foreign nationality by activity sector | Number of individuals
A13: Unidade/Unit | D13: Número de indivíduos/ Number of individuals | E13: Número de indivíduos/ Number of individuals | F13: Número de indivíduos/ Number of individuals
D14: 2014 | E14: 2019 | F14: 2023
A15: Administrative activities | B15: Ativ. administrativas | D15: 7824.75 | E15: 34341.917 | F15: 95695.083
A16: Accommodation and food services | B16: Alojamento e restauração | D16: 8949.25 | E16: 41792.583 | F16: 93285.75
A17: Construction | B17: Construção | D17: 5399.5833 | E17: 23558.25 | F17: 69227.167
A18: Trade | B18: Comércio | D18: 7991.5 | E18: 22471.083 | F18: 58303.583
A19: Manufacturing | B19: Ind. transformadoras | D19: 5231.3333 | E19: 16339.083 | F19: 52999.333
A20: Agriculture and fishing | B20: Agricultura e pesca | D20: 5131.4167 | E20: 16091.25 | F20: 43495.833
A21: Information and communication | B21: Ativ. informação e comunicação | D21: 830.75 | E21: 5205.8333 | F21: 19207.083
A22: Consulting and scientific activities | B22: Ativ. consultoria e científicas | D22: 1297.4167 | E22: 6009.0833 | F22: 19084.167
A23: Transportation and storage | B23: Transportes e armazenagem | D23: 2391.5833 | E23: 5302.4167 | F23: 16831.5
A24: Other services | B24: Outros serviços | D24: 1491.75 | E24: 4065.1667 | F24: 7729.1667
A25: Real estate | B25: Imobiliárias | D25: 869.91667 | E25: 2180.6667 | F25: 5411.9167
A26: Artistic activities | B26: Ativ. artísticas | D26: 979.83333 | E26: 2649.6667 | F26: 5226.9167
... A30: Electricity and gas | B30: Eletricidade e gás | D30: 14.166667 | E30: 53.75 | F30: 193.58333
A33: Fonte: Microdados da Segurança Social (cálculos do Banco de Portugal). Nota: foram considerados os trabalhadores por conta de outrem, em idade ativa (16-74 anos), com morada em Portugal e com, pelo menos, o equivalente a um dia de remuneração na empresa em cada mês.
A34: Source: Social Security microdata (Banco de Portugal calculations). Note: Employees of working age (16-74 years old), living in Portugal and with, at least, the equivalent of a day of remuneration at the firm each month were considered.

Sheet TED.G8
A5: Índice/Contents
A6: Boletim Económico - junho 2024/Economic Bulletin - June 2024
A7: =+Índice!A95 -> Parte II. Tema em Destaque: Caraterização dos trabalhadores estrangeiros por conta de outrem em Portugal / Part II Special Issue: Characterization of foreign employees in Portugal
A10: Gráfico 8 • Peso dos trabalhadores com nacionalidade estrangeira no total de trabalhadores por setor de atividade | Percentagem
A11: Chart 8 • Share of employees with foreign nationality in the total number of employees by activity sector | Percentage
A13: Unidade/Unit | C13: % | D13: % | E13: %
C14: 2014 | D14: 2019 | E14: 2023
A15: Agriculture and fishing | B15: Agricultura e pesca | C15: 9.3074763 | D15: 20.78364 | E15: 41.107022
A16: Accommodation and food services | B16: Alojamento e restauração | C16: 5.263057 | D16: 15.876526 | E16: 31.123909
A17: Administrative activities | B17: Ativ. administrativas | C17: 3.3997351 | D17: 11.230572 | E17: 28.107216
A18: Construction | B18: Construção | C18: 2.9898857 | D18: 9.966587 | E18: 23.175085
A19: Real estate | B19: Imobiliárias | C19: 3.8045347 | D19: 7.1817642 | E19: 13.344275
A20: Artistic activities | B20: Ativ. artísticas | C20: 4.1923835 | D20: 8.0512807 | E20: 13.106568
A21: Information and communication | B21: Ativ. informação e comunicação | C21: 1.0783123 | D21: 4.9017965 | E21: 12.799512
A22: Other services | B22: Outros serviços | C22: 2.3234492 | D22: 5.5907421 | E22: 10.12496
A23: Consulting and scientific activities | B23: Ativ. consultoria e científicas | C23: 1.2596152 | D23: 4.1626461 | E23: 9.9394311
A24: Transportation and storage | B24: Transportes e armazenagem | C24: 1.8188482 | D24: 3.3049526 | E24: 9.4811744
A25: Trade | B25: Comércio | C25: 1.7445501 | D25: 3.9933371 | E25: 9.2351487
A26: Mining and quarrying | B26: Ind. extrativas | C26: 1.4952997 | D26: 2.8232107 | E26: 8.6948609
... A30: Electricity and gas | B30: Eletricidade e gás | C30: 0.11974996 | D30: 0.44379627 | E30: 1.7561119
A32: Fonte: Microdados da Segurança Social (cálculos do Banco de Portugal). | Notas: Foram considerados os trabalhadores por conta de outrem, em idade ativa (16-74 anos) e com, pelo menos, o equivalente a um dia de remuneração na empresa em cada mês. Os pesos foram calculados com base nos dias de remuneração dos trabalhadores com nacionalidade estrangeira no número total de dias de remuneração por setor. O cálculo destes pesos com base no número de trabalhadores mantém os resultados qualitativamente inalterados.
A33: Source: Social Security microdata (Banco de Portugal calculations). | Notes: Employees of working age (16-74 years) and with, at least, the equivalent of a day of remuneration at the firm each month were considered. The shares were calculated based on the days of remuneration for employees with foreign nationality in the total number of days of remuneration per sector. Calculating these weights based on the number of employees keeps the results qualitatively unchanged.

Sheet TED.Q2
A5: Índice/Contents
A6: Boletim Económico - junho 2024/Economic Bulletin - June 2024
A7: =+Índice!A95 -> Parte II. Tema em Destaque: Caraterização dos trabalhadores estrangeiros por conta de outrem em Portugal / Part II Special Issue: Characterization of foreign employees in Portugal
A10: Quadro 2 • Distribuição dos trabalhadores estrangeiros por nacionalidade em cada setor em 2023 | Percentagem
A11: Table 2 • Distribution of foreign employees by nationality in each sector in 2023 | Percentage
A13: Unidade/Unit | C13: % | D13: % | E13: % | F13: % | G13: % | H13: % | I13: %
C16: Main nationalities | H16: Others
C17: Principais nacionalidades | H17: Outros
C18: Bangladesh | D18: Brazil | E18: Cape Verde | F18: India | G18: Nepal | H18: Europe | I18: Outside Europe
C19: Bangladesh | D19: Brasil | E19: Cabo Verde | F19: Índia | G19: Nepal | H19: Europa | I19: Fora da Europa
A20: Agriculture and fishing | B20: Agricultura e pesca | C20: 13.829294 | D20: 4.9257592 | E20: 0.35616438 | F20: 34.625539 | G20: 15.323115 | H20: 8.1988696 | I20: 22.741259
A21: Accommodation and food services | B21: Alojamento e restauração | C21: 5.5487217 | D21: 42.177396 | E21: 5.5721265 | F21: 6.1693953 | G21: 13.841074 | H21: 7.1595429 | I21: 19.531743
A22: Administrative activities | B22: Ativ. administrativas | C22: 1.8797552 | D22: 42.427728 | E22: 5.7109343 | F22: 8.5839485 | G22: 3.0075561 | H22: 12.035711 | I22: 26.354367
A23: Construction | B23: Construção | C23: 1.7653233 | D23: 37.731695 | E23: 8.6596543 | F23: 7.9175324 | G23: 0.67904459 | H23: 8.1943986 | I23: 35.052352
A24: Real estate | B24: Imobiliárias | C24: 1.1486996 | D24: 41.214604 | E24: 5.802011 | F24: 3.6770707 | G24: 2.8055372 | H24: 21.474216 | I24: 23.877862
A25: Artistic activities | B25: Ativ. artísticas | C25: 1.9370885 | D25: 48.487796 | E25: 3.1678969 | F25: 1.6501124 | G25: 1.8382412 | H25: 20.604882 | I25: 22.313984
A26: Information and communication | B26: Ativ. informação e comunicação | C26: 0.42909517 | D26: 48.022214 | E26: 1.0382454 | F26: 2.5932273 | G26: 0.24209818 | H26: 32.986962 | I26: 14.688158
A27: Other services | B27: Outros serviços | C27: 1.4264151 | D27: 48.725606 | E27: 3.619407 | F27: 7.6743935 | G27: 2.283558 | H27: 14.222102 | I27: 22.048518
A28: Consulting and scientific activities | B28: Ativ. consultoria e científicas | C28: 0.92790708 | D28: 42.212567 | E28: 2.6129863 | F28: 2.515174 | G28: 0.63971006 | H28: 30.92616 | I28: 20.165495
A29: Transportation and storage | B29: Transportes e armazenagem | C29: 7.5854796 | D29: 48.25278 | E29: 3.5226609 | F29: 8.8692828 | G29: 1.1625028 | H29: 16.070562 | I29: 14.536732
A30: Trade | B30: Comércio | C30: 7.8935972 | D30: 46.325626 | E30: 3.5595296 | F30: 6.1401315 | G30: 3.3252673 | H30: 9.2255622 | I30: 23.530286
A31: Mining and quarrying | B31: Ind. extrativas | C31: 2.6624406 | D31: 33.312203 | E31: 4.3106181 | F31: 14.432118 | G31: 1.9228737 | H31: 19.535129 | I31: 23.824617
... A37: Total | B37: Total | C37: 3.7911093 | D37: 42.294513 | E37: 4.6 | F37: 8.3 | G37: 5.4 | H37: 12.636537 | I37: 22.988733
A40: Fonte: Microdados da Segurança Social (cálculos do Banco de Portugal). | Notas: Foram considerados os trabalhadores por conta de outrem, em idade ativa (16-74 anos) e com, pelo menos, o equivalente a um dia de remuneração na empresa em cada mês. As principais nacionalidades representadas correspondem aos cinco países com maior número de indivíduos a trabalhar em Portugal em 2023. Os setores encontram-se ordenados por ordem decrescente do peso dos trabalhadores com nacionalidade estrangeira no total de trabalhadores por setor de atividade.
A41: Source: Social Security microdata (Banco de Portugal calculations). | Notes: employees of working age (16-74 years) and with at least the equivalent of a day of remuneration at the firm each month were considered. The main nationalities represented correspond to the five countries with the highest number of individuals working in Portugal in 2023. The sectors are ordered in decreasing order of the weight of workers with foreign nationality in the total number of workers per sector of activity.

Sheet TED.G9
A5: Índice/Contents
A6: Boletim Económico - junho 2024/Economic Bulletin - June 2024
A7: =+Índice!A95 -> Parte II. Tema em Destaque: Caraterização dos trabalhadores estrangeiros por conta de outrem em Portugal / Part II Special Issue: Characterization of foreign employees in Portugal
A10: Gráfico 9 • Distribuição das remunerações regulares brutas nominais por idade e nacionalidade em 2023 | Euros
A11: Chart 9 • Distribution of nominal gross regular wages by age and nationality in 2023 | Euros
A13: Unidade/Unit | C13: Euros | D13: Euros | E13: Euros | F13: Euros
C15: Panel A – Up to 35 years old | E15: Panel B – More than 35 years old
C16: Painel A – 35 anos ou menos | E16: Painel B – Mais de 35 anos
C17: Portuguese nationality | D17: Foreign nationality | E17: Portuguese nationality | F17: Foreign nationality
C18: Nacionalidade portuguesa | D18: Nacionalidade estrangeira | E18: Nacionalidade portuguesa | F18: Nacionalidade estrangeira
A19: 10th percentile | B19: Percentil 10 | C19: 760 | D19: 741.91436 | E19: 760 | F19: 754.32436
A20: 25th percentile | B20: Percentil 25 | C20: 773.98167 | D20: 760 | E20: 781.15287 | F20: 760
A21: Median | B21: Mediana | C21: 902.33917 | D21: 768.75358 | E21: 944.73331 | F21: 781.09945
A22: 75th percentile | B22: Percentil 75 | C22: 1258.0663 | D22: 877.97326 | E22: 1458.1079 | F22: 935.10887
A23: 90th percentile | B23: Percentil 90 | C23: 1753.1608 | D23: 1174.8203 | E23: 2299.1404 | F23: 1400.6452
A26: Fonte: Microdados da Segurança Social (cálculos do Banco de Portugal). | Notas: Foram considerados os trabalhadores por conta de outrem, em idade ativa (16-74 anos) e com, pelo menos, o equivalente a um dia de remuneração na empresa em cada mês. As remunerações apresentadas correspondem a remunerações equivalentes a um mês completo, ou seja, foram obtidas através da divisão da remuneração pelo número de dias declarado e multiplicadas por 30 (número de dias correspondente a um mês de trabalho a tempo completo). As remunerações regulares incluem a remuneração base, o subsídio de refeição, os subsídios de caráter regular mensal e prémios, bónus e outras prestações de caráter mensal. Os extremos inferior e superior representados nos diagramas representam, respetivamente, a média do percentil 10 e do percentil 90 das respetivas distribuições.
A27: Source: Social Security microdata (Banco de Portugal calculations). | Notes: Employees of working age (16-74 years) and with, at least, the equivalent of a day of remuneration at the firm each month were considered. The remuneration presented corresponds to remuneration equivalent to a full month, that is, it was obtained by dividing the remuneration by the declared number of days and multiplied by 30 (number of days corresponding to a month of full-time work). Regular remuneration includes base remuneration, meal allowance, regular monthly allowances, and bonuses and other monthly payments. The lower and upper bounds in the diagrams represent, respectively, the average of the 10th percentile and the 90th percentile of the respective distributions.

Sheet TED.G10
A5: Índice/Contents
A6: Boletim Económico - junho 2024/Economic Bulletin - June 2024
A7: =+Índice!A95 -> Parte II. Tema em Destaque: Caraterização dos trabalhadores estrangeiros por conta de outrem em Portugal / Part II Special Issue: Characterization of foreign employees in Portugal
A10: Gráfico 10 • Média e mediana das remunerações regulares brutas nominais por nacionalidade em 2023 | Euros
A11: Chart 10 • Average and median of nominal gross regular wages by nationality in 2023 | Euros
A13: Unidade/Unit | C13: Euros | D13: Euros | E13: Euros | F13: Euros | G13: Euros | H13: Euros | I13: Euros | J13: Euros
C14: Panel A – Up to 35 years old | G14: Panel B – More than 35 years old
C15: Painel A – 35 anos ou menos | G15: Painel B – Mais de 35 anos
C16: Average remuneration - Portuguese nationality | D16: Average remuneration - Foreign nationality | E16: Median remuneration - Portuguese nationality | F16: Median remuneration - Foreign nationality | G16: Average remuneration - Portuguese nationality | H16: Average remuneration - Foreign nationality | I16: Median remuneration - Portuguese nationality | J16: Median remuneration - Foreign nationality
C17: Remuneração média - Nacionalidade portuguesa | D17: Remuneração média - Nacionalidade estrangeira | E17: Remuneração mediana - Nacionalidade portuguesa | F17: Remuneração mediana - Nacionalidade estrangeira | G17: Remuneração média - Nacionalidade portuguesa | H17: Remuneração média - Nacionalidade estrangeira | I17: Remuneração mediana - Nacionalidade portuguesa | J17: Remuneração mediana - Nacionalidade estrangeira
A18: Administrative activities | B18: Ativ. administrativas | C18: 955.17645 | D18: 848.32468 | E18: 837.92647 | F18: 770.44665 | G18: 1070.2051 | H18: 893.3271 | I18: 861.14214 | J18: 775.51041
A19: Accommodation and food services | B19: Alojamento e restauração | C19: 892.70795 | D19: 817.78203 | E19: 802.63555 | F19: 760.2586 | G19: 996.45652 | H19: 865.75102 | I19: 811.05177 | J19: 763.33305
A20: Construction | B20: Construção | C20: 964.34697 | D20: 826.33268 | E20: 812.01473 | F20: 772.8935 | G20: 1100.0541 | H20: 863.49382 | I20: 853.05246 | J20: 779.55076
A21: Trade | B21: Comércio | C21: 986.92175 | D21: 875.91055 | E21: 849.7825 | F21: 761.90901 | G21: 1252.888 | H21: 1038.1111 | I21: 938.76446 | J21: 772.82339
A22: Manufacturing | B22: Ind. transformadoras | C22: 1048.6954 | D22: 890.39624 | E22: 875.98917 | F22: 787.89905 | G22: 1227.3629 | H22: 1048.0864 | I22: 911.86489 | J22: 802.49476
A23: Agriculture and fishing | B23: Agricultura e pesca | C23: 979.99386 | D23: 777.05543 | E23: 819.84786 | F23: 760 | G23: 1030.019 | H23: 805.06654 | I23: 801.45516 | J23: 760.00163
A24: Information and communication | B24: Ativ. informação e comunicação | C24: 1748.7116 | D24: 2067.9206 | E24: 1484.9717 | F24: 1592.6744 | G24: 2368.7048 | H24: 2626.4771 | I24: 1981.1929 | J24: 1927.6076
A25: Consulting and scientific activities | B25: Ativ. consultoria e científicas | C25: 1365.121 | D25: 1401.4868 | E25: 1110.4973 | F25: 1000.2243 | G25: 1716.3628 | H25: 1900.01 | I25: 1210.4708 | J25: 1014.5392
A26: Transportation and storage | B26: Transportes e armazenagem | C26: 1217.599 | D26: 985.29671 | E26: 1009.8716 | F26: 778.80236 | G26: 1606.4337 | H26: 1253.984 | I26: 1310.8889 | J26: 1018.2794
A27: Other services | B27: Outros serviços | C27: 990.01792 | D27: 838.03106 | E27: 844.71732 | F27: 760 | G27: 1203.801 | H27: 939.22591 | I27: 888.85194 | J27: 760.00108
A28: Real estate | B28: Imobiliárias | C28: 1086.3544 | D28: 938.56093 | E28: 869.40208 | F28: 778.12773 | G28: 1205.6859 | H28: 1049.4872 | I28: 845.00595 | J28: 775.6554
A29: Artistic and sportive activities | B29: Ativ. Artísticas e desportivas | C29: 1092.7987 | D29: 1334.137 | E29: 860.49292 | F29: 789.2551 | G29: 1423.5151 | H29: 1691.2546 | I29: 1000.1627 | J29: 838.21691
... A33: Electricity and gas | B33: Eletricidade e gás | C33: 1825.8039 | D33: 1879.2049 | E33: 1577.7141 | F33: 1220.9369 | G33: 3041.9265 | H33: 3547.8028 | I33: 2852.2404 | J33: 1712.5938
A37: Fonte: Microdados da Segurança Social (cálculos do Banco de Portugal). | Notas: Foram considerados os trabalhadores por conta de outrem, em idade ativa (16-74 anos) e com, pelo menos, o equivalente a um dia de remuneração na empresa em cada mês. As remunerações apresentadas correspondem a remunerações equivalentes a um mês completo, ou seja, foram obtidas através da divisão da remuneração pelo número de dias declarado e multiplicadas por 30 (número de dias correspondente a um mês de trabalho a tempo completo). As remunerações regulares incluem a remuneração base, o subsídio de refeição, os subsídios de caráter regular mensal e prémios, bónus e outras prestações de caráter mensal. Os setores encontram-se ordenados por ordem decrescente do número de trabalhadores com nacionalidade estrangeira por setor de atividade.
A38: Source: Social Security microdata (Banco de Portugal calculations). | Notes: employees of working age (16-74 years) and with, at least, the equivalent of a day of remuneration at the firm each month were considered. The remuneration presented corresponds to remuneration equivalent to a full month, that is, it was obtained by dividing the remuneration by the declared number of days and multiplied by 30 (number of days corresponding to a month of full-time work). Regular remuneration includes base remuneration, meal allowance, regular monthly allowances, and bonuses and other monthly benefits. The sectors are arranged in descending order of the number of workers with foreign nationality by activity sector.

Sheet TED.C.G1
A5: Índice/Contents
A6: Boletim Económico - junho 2024/Economic Bulletin - June 2024
A7: =+Índice!A95 -> Parte II. Tema em Destaque: Caraterização dos trabalhadores estrangeiros por conta de outrem em Portugal / Part II Special Issue: Characterization of foreign employees in Portugal
A10: Gráfico C1.1 • População residente empregada (20 a 64 anos) por nacionalidade e escolaridade máxima| Percentagem do total da população da respetiva nacionalidade
A11: Chart C1.1 • Resident employed population (20 - 64 years) by nationality and maximum schooling attainment | As a percentage of total population of the respective nationality
A13: Unidade/Unit | C13: % | D13: % | E13: %
A14: Panel A - 2011 | B14: Painel A - 2011
C15: Primary education | D15: Secondary education | E15: Tertiary education
A16: Nationality | B16: Nacionalidade | C16: Ensino básico | D16: Ensino secundário | E16: Ensino superior
A17: Portuguese | B17: Portuguesa | C17: 55.335565 | D17: 21.816172 | E17: 22.848263
A18: Foreign | B18: Estrangeira | C18: 46.940442 | D18: 36.186356 | E18: 16.873203
A22: Panel B - 2021 | B22: Painel B - 2021
C23: Primary education | D23: Secondary education | E23: Tertiary education
A24: Nationality | B24: Nacionalidade | C24: Ensino básico | D24: Ensino secundário | E24: Ensino superior
A25: Portuguese | B25: Portuguesa | C25: 39.481392 | D25: 28.547603 | E25: 31.971005
A26: Foreign | B26: Estrangeira | C26: 32.92975 | D26: 40.66867 | E26: 26.40158
A29: Fonte: INE - Censos 2011 e 2021 (cálculos do Banco de Portugal).
A30: Source: Statistics Portugal - Census 2011 and 2021 (Banco de Portugal calculations).

Sheet TED.C.G2
A5: Índice/Contents
A6: Boletim Económico - junho 2024/Economic Bulletin - June 2024
A7: =+Índice!A95 -> Parte II. Tema em Destaque: Caraterização dos trabalhadores estrangeiros por conta de outrem em Portugal / Part II Special Issue: Characterization of foreign employees in Portugal
A10: Gráfico C1.2 • Pirâmide etária da população estrangeira empregada em Portugal, por nível máximo de ensino atingido | Número de indivíduos e percentagem com cada nível de ensino
A11: Chart C1.2 • Age pyramid of foreign population employed in Portugal by maximum schooling attainment | Number of individuals and their percentage at each level of schooling attainment
A13: Unidade/Unit | C13: Número de indivíduos/ Number of individuals | D13: Número de indivíduos/ Number of individuals | E13: Número de indivíduos/ Number of individuals | G13: Número de indivíduos/ Number of individuals | H13: Número de indivíduos/ Number of individuals | I13: Número de indivíduos/ Number of individuals
C15: Women | G15: Men
C16: Primary | D16: Secondary | E16: Tertiary | G16: Primary | H16: Secondary | I16: Tertiary
C18: Mulheres | G18: Homens
C19: Básico | D19: Secundário | E19: Superior | G19: Básico | H19: Secundário | I19: Superior
A20: 15 - 19 years | B20: 15 - 19 anos | C20: 207 | D20: 386 | E20: 4 | G20: 488 | H20: 506 | I20: 0
A21: 20 - 24 years | B21: 20 - 24 anos | C21: 2008 | D21: 5458 | E21: 1155 | G21: 4355 | H21: 7587 | I21: 975
A22: 25 - 29 years | B22: 25 - 29 anos | C22: 3487 | D22: 7298 | E22: 5836 | G22: 7154 | H22: 11374 | I22: 4950
A23: 30 - 34 years | B23: 30 - 34 anos | C23: 4705 | D23: 7328 | E23: 7575 | G23: 8296 | H23: 11098 | I23: 6952
A24: 35 - 39 years | B24: 35 - 39 anos | C24: 5156 | D24: 7258 | E24: 6726 | G24: 7977 | H24: 9576 | I24: 6351
A25: 40 - 44 years | B25: 40 - 44 anos | C25: 5506 | D25: 6560 | E25: 5451 | G25: 7273 | H25: 7593 | I25: 4794
A26: 45 - 49 years | B26: 45 - 49 anos | C26: 5240 | D26: 5022 | E26: 3716 | G26: 6050 | H26: 5217 | I26: 3596
A27: 50 - 54 years | B27: 50 - 54 anos | C27: 4265 | D27: 3422 | E27: 2419 | G27: 4538 | H27: 3643 | I27: 2567
A28: 55 - 59 years | B28: 55 - 59 anos | C28: 2962 | D28: 2220 | E28: 1556 | G28: 3023 | H28: 2335 | I28: 1860
A29: 60 - 64 years | B29: 60 - 64 anos | C29: 1642 | D29: 1102 | E29: 837 | G29: 1737 | H29: 1347 | I29: 1133
A30: 65 + years | B30: 65 + anos | C30: 657 | D30: 344 | E30: 365 | G30: 818 | H30: 508 | I30: 795
A33: Fonte: INE - Censos 2021 (cálculos do Banco de Portugal).
A34: Source: Statistics Portugal - Census 2021 (Banco de Portugal calculations).

Sheet TED.C.G3
A5: Índice/Contents
A6: Boletim Económico - junho 2024/Economic Bulletin - June 2024
A7: =+Índice!A95 -> Parte II. Tema em Destaque: Caraterização dos trabalhadores estrangeiros por conta de outrem em Portugal / Part II Special Issue: Characterization of foreign employees in Portugal
A10: Gráfico C1.3 • Pirâmide etária da população portuguesa empregada em Portugal, por nível máximo de ensino atingido | Número de indivíduos em cada nível de ensino
A11: Chart C1.3 • Age pyramid of Portuguese population employed in Portugal by maximum schooling attainment | Number of persons at each level of schooling attainment
A13: Unidade/Unit | C13: Número de indivíduos/ Number of individuals | D13: Número de indivíduos/ Number of individuals | E13: Número de indivíduos/ Number of individuals | G13: Número de indivíduos/ Number of individuals | H13: Número de indivíduos/ Number of individuals | I13: Número de indivíduos/ Number of individuals
C16: Women | G16: Men
C17: Primary | D17: Secondary | E17: Tertiary | G17: Primary | H17: Secondary | I17: Tertiary
C19: Mulheres | G19: Homens
C20: Básico | D20: Secundário | E20: Superior | G20: Básico | H20: Secundário | I20: Superior
A21: 15 - 19 years | B21: 15 - 19 anos | C21: 1690 | D21: 5887 | E21: 24 | G21: 4567 | H21: 7834 | I21: 88
A22: 20 - 24 years | B22: 20 - 24 anos | C22: 11268 | D22: 56741 | E22: 33787 | G22: 26554 | H22: 72753 | I22: 19931
A23: 25 - 29 years | B23: 25 - 29 anos | C23: 19028 | D23: 67277 | E23: 97042 | G23: 39567 | H23: 84017 | I23: 61876
A24: 30 - 34 years | B24: 30 - 34 anos | C24: 32606 | D24: 67242 | E24: 101510 | G24: 60292 | H24: 78573 | I24: 66326
A25: 35 - 39 years | B25: 35 - 39 anos | C25: 50368 | D25: 77877 | E25: 114166 | G25: 87711 | H25: 83500 | I25: 70907
A26: 40 - 44 years | B26: 40 - 44 anos | C26: 74178 | D26: 92067 | E26: 127658 | G26: 116674 | H26: 93182 | I26: 80122
A27: 45 - 49 years | B27: 45 - 49 anos | C27: 105800 | D27: 88931 | E27: 112249 | G27: 147052 | H27: 85761 | I27: 72064
A28: 50 - 54 years | B28: 50 - 54 anos | C28: 125570 | D28: 70236 | E28: 75337 | G28: 161461 | H28: 64261 | I28: 49298
A29: 55 - 59 years | B29: 55 - 59 anos | C29: 127374 | D29: 53725 | E29: 57661 | G29: 160685 | H29: 47883 | I29: 36128
A30: 60 - 64 years | B30: 60 - 64 anos | C30: 84907 | D30: 31195 | E30: 37180 | G30: 99826 | H30: 28000 | I30: 26458
A31: 65 + years | B31: 65 + anos | C31: 33404 | D31: 6436 | E31: 11641 | G31: 48463 | H31: 8604 | I31: 19642
A34: Fonte: INE - Censos 2021 (cálculos do Banco de Portugal).
A35: Source: Statistics Portugal - Census 2021 (Banco de Portugal calculations).

Sheet TED.C.G4
A5: Índice/Contents
A6: Boletim Económico - junho 2024/Economic Bulletin - June 2024
A7: =+Índice!A95 -> Parte II. Tema em Destaque: Caraterização dos trabalhadores estrangeiros por conta de outrem em Portugal / Part II Special Issue: Characterization of foreign employees in Portugal
A10: Gráfico C1.4 • População empregada (15 ou mais anos) estrangeira e portuguesa por setor de atividade e nível máximo de ensino | Percentagem do total de cada setor em cada nacionalidade
A11: Chart C1.4 • Foreign and Portuguese employed population (15 and more years) by sector of activity and maximum schooling attainment | Percentage of each sector in the respective nationality
A13: Unidade/Unit | C13: % | D13: % | E13: % | G13: % | H13: % | I13: %
C14: Foreign | G14: Portuguese
C15: Primary | D15: Secondary | E15: Tertiary | G15: Primary | H15: Secondary | I15: Tertiary
C18: Estrangeiros | G18: Portugueses
C19: Básico | D19: Secundário | E19: Superior | G19: Básico | H19: Secundário | I19: Superior
A20: Education | B20: Educação | C20: 10.435738 | D20: 17.649213 | E20: 71.915049 | G20: 6.909531 | H20: 21.384465 | I20: 71.706004
A21: Consulting and scientific activities | B21: Ativ. consultoria e científicas | C21: 7.7989747 | D21: 22.203547 | E21: 69.997479 | G21: 12.821226 | H21: 17.133502 | I21: 70.045272
A22: Information and communication | B22: Ativ. Inform. e comunicação | C22: 8.9271089 | D22: 30.310476 | E22: 60.762415 | G22: 6.8176947 | H22: 31.968661 | I22: 61.213644
A23: Financial and insurance activities | B23: Ativ. financeiras e seguros | C23: 14.097456 | D23: 26.478701 | E23: 59.423843 | G23: 8.1038496 | H23: 33.185935 | I23: 58.710215
A24: Real estate | B24: Atividades imobiliárias | C24: 19.368088 | D24: 36.208531 | E24: 44.423381 | G24: 25.389293 | H24: 25.52785 | I24: 49.082857
A25: Electricity and gas | B25: Electricidade, gás e água | C25: 18.346253 | D25: 39.922481 | E25: 41.731266 | G25: 19.250116 | H25: 34.442237 | I25: 46.307647
A26: Public administration; Social Security | B26: Adm. Pública; Seg. Social | C26: 25.774059 | D26: 33.835425 | E26: 40.390516 | G26: 21.284333 | H26: 38.818827 | I26: 39.896841
A27: Artistic and sports activities | B27: Ativ. artísticas e desportivas | C27: 16.285714 | D27: 44.987013 | E27: 38.727273 | G27: 25.524219 | H27: 36.251625 | I27: 38.224156
A28: Health and social assistance | B28: Saúde e apoio social | C28: 26.315233 | D28: 39.137101 | E28: 34.547666 | G28: 24.879488 | H28: 39.270777 | I28: 35.849735
A29: Mining and quarrying | B29: Indústrias extrativas | C29: 36.338798 | D29: 41.803279 | E29: 21.857923 | G29: 50.022293 | H29: 29.101911 | I29: 20.875796
A30: Administrative activities | B30: Ativ. administrativas | C30: 38.732305 | D30: 39.654806 | E30: 21.61289 | G30: 41.744719 | H30: 39.43408 | I30: 18.821202
A31: Transportation and storage | B31: Transportes e armazenagem | C31: 28.036241 | D31: 50.391937 | E31: 21.571821 | G31: 50.093408 | H31: 31.554844 | I31: 18.351748
... A39: Agriculture and fishing | B39: Agricultura e pesca | C39: 55.662371 | D39: 36.810527 | E39: 7.5271017 | G39: 81.485423 | H39: 15.791791 | I39: 2.7227859
A42: Fonte: INE - Censos 2021 (cálculos do Banco de Portugal). | Nota: Os setores encontram-se ordenados pelo peso decrescente dos trabalhadores estrangeiros com ensino superior.
A43: Source: Statistics Portugal - Census 2021 (Banco de Portugal calculations). | Note: Sectores are presented by the descendent weight of the foreign workers with tertiary education.

Sheet TED.C.Q1
A5: Índice/Contents
A6: Boletim Económico - junho 2024/Economic Bulletin - June 2024
A7: =+Índice!A95 -> Parte II. Tema em Destaque: Caraterização dos trabalhadores estrangeiros por conta de outrem em Portugal / Part II Special Issue: Characterization of foreign employees in Portugal
A10: Quadro C1.1 • População estrangeira empregada (15 ou mais anos), por nacionalidade e nível máximo de ensino | Número de indivíduos e distribuição por nível de ensino em percentagem
A11: Table C1.1 • Foreign employed population (15 or more years) by nationality and maximum schooling attainment | Total number of individuals and breakdown as a percentage of each educational level for each nationality
A13: Unidade/Unit | C13: Número de indivíduos/ Number of individuals | D13: % | E13: % | F13: %
C15: Total | D15: Primary | E15: Secondary | F15: Tertiary
C17: Total | D17: Básico | E17: Secundário | F17: Superior
A18: Total | B18: Total | C18: 264339 | D18: 33.118079 | E18: 40.547176 | F18: 26.334744
A20: Brazil | B20: Brasil | C20: 107638 | D20: 27.139114 | E20: 47.54176 | F20: 25.319125
A21: Cape Verde | B21: Cabo Verde | C21: 12869 | D21: 57.790038 | E21: 33.67783 | F21: 8.5321315
A22: Ukraine | B22: Ucrânia | C22: 12627 | D22: 29.547794 | E22: 48.435891 | F22: 22.016314
A23: Angola | B23: Angola | C23: 11746 | D23: 38.404563 | E23: 38.344968 | F23: 23.250468
A24: India | B24: Índia | C24: 9350 | D24: 46.213904 | E24: 41.315508 | F24: 12.470588
A25: China | B25: China | C25: 8711 | D25: 65.939617 | E25: 25.794972 | F25: 8.2654115
A26: Romenia | B26: Roménia | C26: 8608 | D26: 44.783922 | E26: 44.11013 | F26: 11.105948
A27: Nepal | B27: Nepal | C27: 8312 | D27: 43.996631 | E27: 43.635707 | F27: 12.367661
A28: Guiné-Bissau | B28: Guiné-Bissau | C28: 6656 | D28: 50.570913 | E28: 37.5 | F28: 11.929087
A29: Spain | B29: Espanha | C29: 6266 | D29: 14.889882 | E29: 22.422598 | F29: 62.68752
A30: Italy | B30: Itália | C30: 5971 | D30: 11.807067 | E30: 25.506615 | F30: 62.686317
... A36: Other - outside Europe | B36: Outros - não europeus | C36: 30057 | D36: 37.289151 | E36: 33.799115 | F36: 28.911734
A40: Fonte: INE - Censos 2021 (cálculos do Banco de Portugal). | Nota: Os países identificados encontram-se ordenados pelo número decrescente dos trabalhadores em Portugal da respetiva nacionalidade.
A41: Source: Statistics Portugal - Census 2021 (Banco de Portugal calculations). | Note: Singular countries are presented by the descendent number of individuals of the respective nationality working in Portugal.

Sheet PEA.G1
A5: Índice/Contents
A6: Boletim Económico - junho 2024/Economic Bulletin - June 2024
A7: =+Índice!A136 -> Parte III. Políticas em análise: Juros e gestão da dívida pública em Portugal/Policy insights: Interest expenditure and public debt management in Portugal
A10: Gráfico 1 • Despesa com juros da dívida pública em Portugal e na área do euro | Em percentagem do PIB
A11: Chart 1 • Interest expenditure of public debt in Portugal and the euro area | Percentage of GDP
C13: Unidade/Unit
D15: 2000 | E15: =+D15+1 -> 2001 | F15: =+E15+1 -> 2002 | G15: =+F15+1 -> 2003 | H15: =+G15+1 -> 2004 | I15: =+H15+1 -> 2005 | J15: =+I15+1 -> 2006 | K15: =+J15+1 -> 2007 | L15: =+K15+1 -> 2008 | ... AA15: =+Z15+1 -> 2023
A16: Portugal | B16: Portugal | C16: Em percentagem do PIB/ In percentage of GDP | D16: 3.0090862 | E16: 2.9905358 | F16: 2.8377958 | G16: 2.6596535 | H16: 2.567646 | I16: 2.5677898 | J16: 2.7826212 | K16: 2.9669473 | L16: 3.1197726 | M16: 2.9868929 | N16: 2.9411372 | O16: 4.321104 | P16: 4.8741619 | Q16: 4.8307167 | R16: 4.879757 | S16: 4.5846938 | T16: 4.1497712 | U16: 3.7759662 | V16: 3.3640521 | W16: 2.9500696 | X16: 2.8859624 | Y16: 2.4026027 | Z16: 1.924645 | AA16: 2.1663032
A17: Área do euro | B17: Euro area | C17: Em percentagem do PIB/ In percentage of GDP | D17: 3.8234145 | E17: 3.7111929 | F17: 3.4650094 | G17: 3.2333472 | H17: 3.045755 | I17: 2.9355909 | J17: 2.8339729 | K17: 2.877921 | L17: 2.9493097 | M17: 2.8331767 | N17: 2.7806165 | O17: 3.0127967 | P17: 3.0415425 | Q17: 2.7922232 | R17: 2.6217187 | S17: 2.3310139 | T17: 2.1285705 | U17: 1.9541729 | V17: 1.8438072 | W17: 1.6388903 | X17: 1.5075598 | Y17: 1.4549689 | Z17: 1.6943024 | AA17: 1.7257703
A18: Minimum | B18: Mínimo | C18: Em percentagem do PIB/ In percentage of GDP | D18: 0.28517726 | E18: 0.22040618 | F18: 0.25950451 | G18: 0.2298614 | H18: 0.18624022 | I18: 0.18865762 | J18: 0.16582037 | K18: 0.16401139 | L18: 0.20640145 | M18: 0.18539616 | N18: 0.088188805 | O18: 0.092940704 | P18: 0.10716259 | Q18: 0.07403177 | R18: 0.067836514 | S18: 0.056224977 | T18: 0.034026274 | U18: 0.032726907 | V18: 0.032392161 | W18: 0.02719044 | X18: 0.076193948 | Y18: 0.066091309 | Z18: 0.078864572 | AA18: 0.30223327
A19: Maximum | B19: Máximo | C19: Em percentagem do PIB/ In percentage of GDP | D19: 6.8525487 | E19: 6.5714743 | F19: 5.8391786 | G19: 5.4167102 | H19: 4.8579323 | I19: 4.6942843 | J19: 4.4361812 | K19: 4.7479013 | L19: 4.9115241 | M19: 5.0401163 | N19: 6.0943942 | O19: 7.6725877 | P19: 5.3487461 | Q19: 4.8307167 | R19: 4.879757 | S19: 4.5846938 | T19: 4.1497712 | U19: 3.7759662 | V19: 3.6466253 | W19: 3.3618151 | X19: 3.4497729 | Y19: 3.4959542 | Z19: 4.2223388 | AA19: 3.7696327
A23: Fontes: Eurostat (cálculos do Banco de Portugal). | Notas: Os juros da dívida pública correspondem aos das administrações públicas, calculados em contas nacionais. A área do euro compreende 19 países, excluindo a Croácia.
A24: Source: Eurostat (Banco de Portugal calculations). | Notes: Public debt interest corresponds to that of the general government, calculated in national accounts. The euro area comprises 19 countries, excluding Croatia.

Sheet PEA.G2
A5: Índice/Contents
A6: Boletim Económico - junho 2024/Economic Bulletin - June 2024
A7: =+Índice!A136 -> Parte III. Políticas em análise: Juros e gestão da dívida pública em Portugal/Policy insights: Interest expenditure and public debt management in Portugal
A10: Gráfico 2 • Dívida pública em Portugal | Em percentagem do PIB e milhões de euros
A11: Chart 2 • Public debt in Portugal | Percentage of GDP and million euros
B13: Unidade/Unit
C15: 2000 | D15: =+C15+1 -> 2001 | E15: =+D15+1 -> 2002 | F15: =+E15+1 -> 2003 | G15: =+F15+1 -> 2004 | H15: =+G15+1 -> 2005 | I15: =+H15+1 -> 2006 | J15: =+I15+1 -> 2007 | K15: =+J15+1 -> 2008 | ... Z15: =+Y15+1 -> 2023
B16: Em percentagem do PIB/ In percentage of GDP | C16: 54.2 | D16: 57.4 | E16: 60 | F16: 63.9 | G16: 67.1 | H16: 72.2 | I16: 73.7 | J16: 72.7 | K16: 75.6 | L16: 87.8 | M16: 100.2 | N16: 114.4 | O16: 129 | P16: 131.4 | Q16: 132.9 | R16: 131.2 | S16: 131.5 | T16: 126.1 | U16: 121.5 | V16: 116.6 | W16: 134.9 | X16: 124.5 | Y16: 112.4 | Z16: 99.1
B17: Em milhões de euros/ Million euros | C17: 69591.8 | D17: 77908 | E17: 85594.9 | F17: 93333.4 | G17: 102157.9 | H17: 114552.9 | I17: 122499.7 | J17: 127625.5 | K17: 135477.9 | L17: 154014 | M17: 179996 | N17: 201459.4 | O17: 217160.3 | P17: 224077.6 | Q17: 230058.8 | R17: 235746.1 | S17: 245244.8 | T17: 247174.5 | U17: 249260.5 | V17: 249977.5 | W17: 270494.9 | X17: 269089 | Y17: 272427.2 | Z17: 263084.8
A20: Fontes: INE e Banco de Portugal.
A21: Sources: Statistics Portugal and Banco de Portugal.

Sheet PEA.G3
A5: Índice/Contents
A6: Boletim Económico - junho 2024/Economic Bulletin - June 2024
A7: =+Índice!A136 -> Parte III. Políticas em análise: Juros e gestão da dívida pública em Portugal/Policy insights: Interest expenditure and public debt management in Portugal
A10: Gráfico 3 • Dívida pública em Portugal e na área do euro | Em percentagem do PIB
A11: Chart 3 • Public debt in Portugal and the euro area | Percentage of GDP
C13: Unidade/Unit
D15: 2000 | E15: =+D15+1 -> 2001 | F15: =+E15+1 -> 2002 | G15: =+F15+1 -> 2003 | H15: =+G15+1 -> 2004 | I15: =+H15+1 -> 2005 | J15: =+I15+1 -> 2006 | K15: =+J15+1 -> 2007 | L15: =+K15+1 -> 2008 | ... AA15: =+Z15+1 -> 2023
A16: Portugal | B16: Portugal | C16: Em percentagem do PIB/ In percentage of GDP | D16: 54.2 | E16: 57.4 | F16: 60 | G16: 63.9 | H16: 67.1 | I16: 72.2 | J16: 73.7 | K16: 72.7 | L16: 75.6 | M16: 87.8 | N16: 100.2 | O16: 114.4 | P16: 129 | Q16: 131.4 | R16: 132.9 | S16: 131.2 | T16: 131.5 | U16: 126.1 | V16: 121.5 | W16: 116.6 | X16: 134.9 | Y16: 124.5 | Z16: 112.4 | AA16: 99.1
A17: Euro area | B17: Área do euro | C17: Em percentagem do PIB/ In percentage of GDP | D17: 69591.8 | E17: 77908 | F17: 85594.9 | G17: 93333.4 | H17: 102157.9 | I17: 114552.9 | J17: 122499.7 | K17: 127625.5 | L17: 135477.9 | M17: 154014 | N17: 179996 | O17: 201459.4 | P17: 217160.3 | Q17: 224077.6 | R17: 230058.8 | S17: 235746.1 | T17: 245244.8 | U17: 247174.5 | V17: 249260.5 | W17: 249977.5 | X17: 270494.9 | Y17: 269089 | Z17: 272427.2 | AA17: 263084.8
A18: Minimum | B18: Mínimo | C18: Em percentagem do PIB/ In percentage of GDP | D18: 5.1137468 | E18: 4.7716506 | F18: 5.6618004 | G18: 5.6001555 | H18: 5.1127589 | I18: 4.6996906 | J18: 4.6289677 | K18: 3.7649455 | L18: 4.5095408 | M18: 7.2396493 | N18: 6.6609683 | O18: 6.1604696 | P18: 9.837191 | Q18: 10.228018 | R18: 10.623896 | S18: 10.069118 | T18: 9.9968273 | U18: 9.1215763 | V18: 8.2037004 | W18: 8.4912883 | X18: 18.572366 | Y18: 17.753216 | Z18: 18.487078 | AA18: 19.57041
A19: Maximum | B19: Máximo | C19: Em percentagem do PIB/ In percentage of GDP | D19: 109.58868 | E19: 108.88632 | F19: 106.36048 | G19: 105.49458 | H19: 105.10091 | I19: 107.39487 | J19: 106.73976 | K19: 103.89015 | L19: 109.4155 | M19: 126.7447 | N19: 147.49424 | O19: 175.2192 | P19: 161.95139 | Q19: 178.16887 | R19: 180.3409 | S19: 176.74828 | T19: 180.52864 | U19: 179.46574 | V19: 186.41417 | W19: 180.61014 | X19: 207.00333 | Y19: 194.99131 | Z19: 172.68188 | AA19: 161.91139
A22: Fontes: Eurostat (cálculos do Banco de Portugal). | Notas: O conceito de dívida pública utilizado é o de Maastricht, ou seja, corresponde à dívida bruta das administrações públicas, consolidada e valorizada pelo respetivo valor facial. A média da área do euro é obtida pela soma dos diferentes países, não sendo deduzidos os empréstimos entre países no âmbito dos programas de assistência financeira.
A23: Source: Eurostat (Banco de Portugal calculations). | Notes: The concept of public debt used is that of Maastricht, meaning it corresponds to the consolidated gross debt of the general government at face value. The average for the euro area is obtained by summing member states' debts, without deducting loans between countries within the framework of financial assistance programs.

Sheet PEA.G4
A5: Índice/Contents
A6: Boletim Económico - junho 2024/Economic Bulletin - June 2024
A7: =+Índice!A136 -> Parte III. Políticas em análise: Juros e gestão da dívida pública em Portugal/Policy insights: Interest expenditure and public debt management in Portugal
A10: Gráfico 4 • Decomposição da variação da despesa com juros da dívida pública em percentagem do PIB, em Portugal e na área do euro | Médias anuais, em pontos percentuais
A11: Chart 4 • Decomposition of the change in public debt interest expenditure as a percentage of GDP in Portugal and the euro area | Yearly averages, in percentage points
C13: Unidade/Unit
D14: Portugal | I14: Área do euro / Euro area
D15: 2001-2010 | E15: 2011-2014 | F15: 2015-2021 | G15: 2022-2023 | I15: 2001-2010 | J15: 2011-2014 | K15: 2015-2021 | L15: 2022-2023
A16: Economic growth effect | B16: Efeito crescimento económico | C16: pp | D16: -0.96668269 | E16: 0.16410254 | F16: -0.81471846 | G16: -0.44122388 | I16: -0.9784524 | J16: -0.18478503 | K16: -0.38544601 | L16: -0.25015362
A17: Interest rate effect | B17: Efeito taxa de juro | C17: pp | D17: -1.6021852 | E17: 0.22933921 | F17: -2.3766889 | G17: 0.19353565 | I17: -1.4824364 | J17: -0.69565709 | K17: -1.1192406 | L17: 0.37925589
A18: Debt stock effect | B18: Efeito stock da dívida | C18: pp | D18: 2.5009188 | E18: 1.5451781 | F18: 0.71425312 | G18: 0.011388748 | I18: 1.4180908 | J18: 0.72154433 | K18: 0.33793675 | L18: 0.14169913
A19: Total change | B19: Var. total | C19: pp | D19: -0.067949038 | E19: 1.9386198 | F19: -2.4771543 | G19: -0.23629949 | I19: -1.042798 | J19: -0.15889779 | K19: -1.1667498 | L19: 0.27080139
A22: Fontes: Eurostat (cálculos do Banco de Portugal).
A23: Source: Eurostat (Banco de Portugal calculations).

Sheet PEA.G5
A5: Índice/Contents
A6: Boletim Económico - junho 2024/Economic Bulletin - June 2024
A7: =+Índice!A136 -> Parte III. Políticas em análise: Juros e gestão da dívida pública em Portugal/Policy insights: Interest expenditure and public debt management in Portugal
A10: Gráfico 5 • Taxa de juro implícita na dívida pública em Portugal e na área do euro | Em percentagem
A11: Chart 5 • Implicit interest rate on public debt in Portugal and the euro area | Percentage
C13: Unidade/Unit
D15: 2001 | E15: =+D15+1 -> 2002 | F15: =+E15+1 -> 2003 | G15: =+F15+1 -> 2004 | H15: =+G15+1 -> 2005 | I15: =+H15+1 -> 2006 | J15: =+I15+1 -> 2007 | K15: =+J15+1 -> 2008 | L15: =+K15+1 -> 2009 | ... Z15: =+Y15+1 -> 2023
A16: Portugal | B16: Portugal | C16: % | D16: 5.8345955 | E16: 5.1925348 | F16: 4.538705 | G16: 4.1884256 | H16: 3.9853012 | I16: 4.0386581 | J16: 4.2502145 | K16: 4.3781219 | L16: 3.8674204 | M16: 3.4299479 | N16: 4.2274828 | O16: 4.0717882 | P16: 3.7925901 | Q16: 3.7686052 | R16: 3.5813888 | S16: 3.2827266 | T16: 3.0169447 | U16: 2.7925615 | V16: 2.537185 | W16: 2.3149683 | X16: 1.919038 | Y16: 1.7333299 | Z16: 2.1112429
A17: Euro area | B17: Área do euro | C17: % | D17: 5.6071944 | E17: 5.2461639 | F17: 4.8763152 | G17: 4.5666957 | H17: 4.3525361 | I17: 4.2296596 | J17: 4.429438 | K17: 4.5663035 | L17: 3.9061733 | M17: 3.55011 | N17: 3.592613 | O17: 3.4476608 | P17: 3.024162 | Q17: 2.8057035 | R17: 2.5160417 | S17: 2.3322738 | T17: 2.1899598 | U17: 2.1117665 | V17: 1.9202585 | W17: 1.6746323 | X17: 1.5875662 | Y17: 1.897523 | Z17: 1.9836006
A18: Minimum | B18: Mínimo | C18: % | D18: 4.2610008 | E18: 3.6640299 | F18: 3.4034786 | G18: 2.6924458 | H18: 2.6232331 | I18: 3.0572402 | J18: 3.7659142 | K18: 4.028809 | L18: 2.4178115 | M18: 1.270648 | N18: 1.5785722 | O18: 1.868795 | P18: 0.79432624 | Q18: 0.70313308 | R18: 0.54462651 | S18: 0.3562145 | T18: 0.35876915 | U18: 0.38638454 | V18: 0.35724358 | W18: 0.88059324 | X18: 0.40436558 | Y18: 0.51323755 | Z18: 1.2500261
